Workbook

Sheet Patient Prices
K2: Price | P2: Price | R2: Friends & Family: BAC is an additional price
A3: New Patient | I3: ='BPC+TB500'!A1 -> BPC157 + TB500 20mg | N3: MOTS-C 10mg | U3: BOTTLES
B4: Without Boodwork | C4: $200 covers the first two visits | J4: Month 1 | K4: ='BPC+TB500'!K37 -> 298 | O4: Month 1 | P4: ='MotsC 10'!K36 -> 138 | R4: ='Pep Costs'!A5 -> AOD-9604 5mg | S4: ='Pep Costs'!C5 -> 55 | V4: ='Pep Costs'!A45 -> Selank 10mg | W4: ='Pep Costs'!C45 -> 145
D5: 1st visit: Health HX and RX for Blood | J5: Month 2 | K5: ='BPC+TB500'!K50 -> 376 | O5: Month 2 | P5: ='MotsC 10'!K48 -> 321 | R5: ='Pep Costs'!A6 -> BAC Water 10ml | S5: 5 | V5: ='Pep Costs'!A46 -> Semax 10mg | W5: ='Pep Costs'!C46 -> 145
D6: 2nd visit: review Blood and RX for Peptides | J6: Month 3 | K6: ='BPC+TB500'!K62 -> 376 | O6: Month 3++ | P6: ='MotsC 10'!K60 -> 458 | R6: ='Pep Costs'!A7 -> BB10 5/5 | S6: ='Pep Costs'!C7 -> 165 | V6: ='Pep Costs'!A47 -> SS-31 10mg | W6: ='Pep Costs'!C47 -> 207.75
J7: Mont 4+ per RX | N7: ='NAD+ Acute'!A1 -> NAD+ 1000mg (Acute) | R7: ='Pep Costs'!A8 -> BB20 | S7: ='Pep Costs'!C8 -> 185 | V7: ='Pep Costs'!A48 -> Sterile Deion Water 10ml | W7: ='Pep Costs'!C48 -> 115
B8: WITH Bloodwork | C8: 150 | I8: ='Wolv Slow Tit'!A1 -> BPC157 + TB500 20mg (Slow Titration) | O8: Month 1 | P8: ='NAD+ Acute'!K36 -> 523 | R8: ='Pep Costs'!A10 -> BPC-157 10mg | S8: ='Pep Costs'!C10 -> 148.4875 | V8: ='Pep Costs'!A50 -> TB500 10mg | W8: ='Pep Costs'!C50 -> 160
C9: (1) visit: review blood and RX for Peptides | J9: Month 1 | K9: ='Wolv Slow Tit'!K18 -> 122 | O9: Month 2 | P9: ='NAD+ Acute'!K48 -> 542 | R9: ='Pep Costs'!A11 -> BPC-157 /TB500 20 mg | S9: ='Pep Costs'!C11 -> 250 | V9: ='Pep Costs'!A51 -> Tesamorelin 10mg | W9: ='Pep Costs'!C51 -> 175
J10: Month 2 | K10: ='Wolv Slow Tit'!K30 -> 215 | O10: Month 3 | P10: ='NAD+ Acute'!K60 -> 542 | R10: ='Pep Costs'!A12 -> BPC-157 20 mg | S10: ='Pep Costs'!C12 -> 255 | V10: ='Pep Costs'!A52 -> Tesofensine | W10: ='Pep Costs'!C52 -> 225
A11: Follow-up Appointments | J11: Month 3 | K11: ='Wolv Slow Tit'!K42 -> 215 | O11: Mont 4+ per RX | R11: ='Pep Costs'!A13 -> Cag 5mg | S11: ='Pep Costs'!C13 -> 165 | V11: ='Pep Costs'!A53 -> Tirz 10mg | W11: ='Pep Costs'!C53 -> 205
B12: 20 minutes | C12: Face to Face $100 | J12: Mont 4+ per RX * | N12: ='NAD semiAct'!A1 -> NAD+ 1000mg (Semi-Acute) | R12: ='Pep Costs'!A14 -> Cag 10mg | S12: ='Pep Costs'!C14 -> 205 | V12: ='Pep Costs'!A54 -> Tirz 15mg | W12: ='Pep Costs'!C54 -> 245
C13: Telehealth $75 | I13: ='Wolv Maintenance'!A1 -> BPC157 + TB500 20mg (Maintenance) | O13: Month 1 | P13: ='NAD semiAct'!K19 -> 252 | R13: ='Pep Costs'!A15 -> CJC-1295/Ipa 5/5 | S13: ='Pep Costs'!C15 -> 160 | V13: ='Pep Costs'!A55 -> Tirz 30mg | W13: ='Pep Costs'!C55 -> 295
J14: Maintenance | K14: ='Wolv Maintenance'!K18 -> 150 | L14: 3 month min. | O14: Month 2 | P14: ='NAD semiAct'!K31 -> 310 | R14: ='Pep Costs'!A16 -> DSIP 5mg | S14: ='Pep Costs'!C16 -> 137 | V14: ='Pep Costs'!A56 -> Tirz 5mg | W14: ='Pep Costs'!C56 -> 175
I15: ='DSIP 5mg'!A1 -> DSIP 5mg | O15: Month 3 | P15: ='NAD semiAct'!K43 -> 310 | R15: ='Pep Costs'!A17 -> DSIP 10mg | S15: ='Pep Costs'!C17 -> 147 | V15: ='Pep Costs'!A57 -> Tirz 60mg | W15: ='Pep Costs'!C57 -> 355
A16: Multiple Peptides: | J16: Month 1 | K16: ='DSIP 5mg'!K35 -> 153 | O16: Mont 4+ per RX | R16: ='Pep Costs'!A18 -> Epithalon 5mg | S16: ='Pep Costs'!C18 -> 137 | V16: ='Pep Costs'!A58 -> VIP 10mg | W16: ='Pep Costs'!C58 -> 155
B17: Patient can ONLY start ONE at a time to watch for allergic reactions, otherwise it is impossible to know which one the patient is allergic to. So one this week and one next week So start #1 on the first week and then next week they can come start the next pept | J17: Month 2 | K17: ='DSIP 5mg'!K47 -> 251 | N17: ='PT-141 10mg'!A1 -> PT-141 10mg | R17: ='Pep Costs'!A19 -> Epithalon 10mg | S17: ='Pep Costs'!C19 -> 145 | V17: ='Pep Costs'!A59 -> Tablets/Caps
J18: Month 3 | K18: ='DSIP 5mg'!K65 -> 285 | O18: Week 1-8 | P18: 15 Unit | R18: ='Pep Costs'!A20 -> Epithalon 50mg | S18: ='Pep Costs'!C20 -> 175.425 | V18: ='Pep Costs'!A60 -> 5 Amino 1q 50mg | W18: ='Pep Costs'!C60 -> 170.0375
J19: Mont 4+ per RX | O19: Week 9-12 | P19: 30 Unit | R19: ='Pep Costs'!A21 -> GHK-CU 50mg | S19: ='Pep Costs'!C21 -> 145 | V19: ='Pep Costs'!A61 -> BPC 500mcg | W19: ='Pep Costs'!C61 -> 214
A20: If they decide to randomly start a new peptide, they will need to come in monthly (at least) for that pept. | I20: ='DSIP 10mg'!A1 -> DSIP 10mg | O20: Week 13-16 | P20: 45 Unit | R20: ='Pep Costs'!A22 -> GHK-CU 100mg | S20: ='Pep Costs'!C22 -> 165 | V20: ='Pep Costs'!A62 -> Methaline Blue 20mg | W20: ='Pep Costs'!C62 -> 185
J21: Month 1 | K21: ='DSIP 10mg'!K34 -> 85 | N21: ='Tesam 10'!A1 -> Tesamorelin 10mg | R21: ='Pep Costs'!A23 -> GLOW 50mg | S21: ='Pep Costs'!C23 -> 165 | V21: ='Pep Costs'!A63 -> Tesofensine 500mcg (1tab daily) | W21: ='Pep Costs'!C63 -> 165
J22: Month 2 | K22: ='DSIP 10mg'!K46 -> 139 | O22: Month 1 | P22: ='Tesam 10'!K33 -> 560 | R22: ='Pep Costs'!A24 -> GLOW 70mg | S22: ='Pep Costs'!C24 -> 205 | V22: ='Pep Costs'!A64 -> Semaglutide 10mg | W22: ='Pep Costs'!C64 -> 185
J23: Month 3 | K23: ='DSIP 10mg'!K46 -> 139 | O23: Month 2 | P23: ='Tesam 10'!K45 -> 747 | R23: ='Pep Costs'!A25 -> Glutathione 600mg | S23: ='Pep Costs'!C25 -> 145 | V23: ='Pep Costs'!A65 -> GHK-CU 100mg | W23: ='Pep Costs'!C65 -> 165
H24: **so they are always "seen" at the beginnng of that month's TX | J24: Mont 4+ per RX | O24: Month 3 | P24: ='Tesam 10'!K45 -> 747 | R24: ='Pep Costs'!A26 -> HCG 5000IU | S24: ='Pep Costs'!C26 -> 145 | V24: ='Pep Costs'!A66 -> BPC-157 10mg | W24: ='Pep Costs'!C66 -> 155
A25: • Month 1 (Week 1-4): RX visit | I25: ='GHK-CU 50'!A1 -> GHK-CU 50mg | O25: Mont 4+ per RX | R25: ='Pep Costs'!A27 -> Hexarelin 10 mg | S25: ='Pep Costs'!C27 -> 170 | V25: ='Pep Costs'!A67 -> SLU PP 332(500mcg)x100 | W25: ='Pep Costs'!C67 -> 170
J26: Month 1 | K26: ='GHK-CU 50'!K34 -> 92 | N26: GLP-3Re 20mg | R26: ='Pep Costs'!A28 -> HGH 15IU | S26: ='Pep Costs'!C28 -> 165 | V26: ='Pep Costs'!A68 -> SLUP PP 332(1mg) x100 | W26: ='Pep Costs'!C68 -> 190
A27: • Month 2 (start of Week 5-8): vitals, monitor, take home RX for month 2 | J27: Month 2 | K27: ='GHK-CU 50'!K46 -> 138 | O27: $350/month | R27: ='Pep Costs'!A29 -> HGH 24IU | S27: ='Pep Costs'!C29 -> 177 | V27: ='Pep Costs'!A69 -> Slu PP 332(5mg)x100 | W27: ='Pep Costs'!C69 -> 210
J28: Month 3 | K28: ='GHK-CU 50'!K58 -> 183 | R28: ='Pep Costs'!A30 -> HGH 36IU | S28: ='Pep Costs'!C30 -> 190 | V28: ='Pep Costs'!A70 -> Nasal Sprays
A29: • Month 3 (start of Week 9-12): vitals, monitor, take home RX for month 3, AND RX BLOOD | J29: Mont 4+ per RX | N29: ='Tirz 30mg'!A1 -> Tirzepatide 30mg | R29: ='Pep Costs'!A31 -> Kisspep 10mg | S29: ='Pep Costs'!C31 -> 150 | V29: ='Pep Costs'!A71 -> DSIP | W29: ='Pep Costs'!C71 -> 170
I30: ='Glow 70'!A1 -> GLOW 70 | J30: Month 1 | K30: ='Glow 70'!K36 -> 209 | O30: $350/month | R30: ='Pep Costs'!A32 -> KLOW 80mg | S30: ='Pep Costs'!C32 -> 225 | V30: ='Pep Costs'!A72 -> Selank Nasal | W30: ='Pep Costs'!C72 -> 175
A31: • Month 4&5 (start of Week 13-20): vitals, monitor, review BLOOD (no blood no more RX), at NP discretion pt can return in 4 or 8 weeks (send home RX accordingly). | J31: By RX only | R31: ='Pep Costs'!A33 -> Lipo-C w/ B12 | S31: ='Pep Costs'!C33 -> 155 | V31: ='Pep Costs'!A73 -> Semax Nasal | W31: ='Pep Costs'!C73 -> 175
I32: =Kissp!A1 -> Kisspeptine 10mg | R32: ='Pep Costs'!A34 -> Melatonin-11 | S32: ='Pep Costs'!C34 -> 145 | V32: ='Pep Costs'!A74 -> Oxytocin Nasal | W32: ='Pep Costs'!C74 -> 86.25
J33: Month 1 | K33: =Kissp!K33 -> 71 | R33: ='Pep Costs'!A35 -> Mots-C 10mg | S33: ='Pep Costs'!C35 -> 159.2625
A34: • Month 6&7 (start of Week 21-28): vitals, monitor, at NP discretion pt can return in 4 or 8 weeks (send home RX accordingly). RX for blood and review over Telehealth | J34: Month 2 | K34: =Kissp!K45 -> 95 | R34: ='Pep Costs'!A36 -> MT 2 10mg | S34: ='Pep Costs'!C36 -> 145
J35: Month 3 | K35: =Kissp!K57 -> 95 | R35: ='Pep Costs'!A37 -> NAD+ 1000mg | S35: ='Pep Costs'!C37 -> 175
J36: Mont 4+ per RX | R36: ='Pep Costs'!A38 -> NAD+ 500mg | S36: ='Pep Costs'!C38 -> 155
A37: • Month 8,9&10 (start of Week 29-36): *if they did not do blood then no more RX…..Vitals, monitor, at NP discretion pt can return in 4-12 weeks (send home RX accordingly). | I37: ='KLOW 80'!A1 -> KLOW 80mg | R37: ='Pep Costs'!A40 -> Oxytocin 5mg | S37: ='Pep Costs'!C40 -> 145 | V37: Peptide Pen | W37: 60
J38: Month 1 | K38: ='KLOW 80'!K33 -> 250 | R38: ='Pep Costs'!A41 -> PT141 10 mg | S38: ='Pep Costs'!C41 -> 155 | V38: Pack of 15 needles, 15 alcohol Prep | W38: 10
J39: Month 2 | K39: ='KLOW 80'!K45 -> 500 | O39: Peptide Pen | Q39: 85 | R39: ='Pep Costs'!A42 -> Reta 10mg | S39: ='Pep Costs'!C42 -> 200 | V39: Pack of 30 needles, 15 alcohol Prep | W39: 15
A40: • Month 11,12&13 (start of Week 37-48): vitals, monitor, at NP discretion pt can return in 4-12 weeks (send home RX accordingly). RX for blood and review over Telehealth | J40: Month 3 | K40: ='KLOW 80'!K57 -> 341 | O40: Pack of 15 needles & alcohol Prep | Q40: 10 | R40: ='Pep Costs'!A43 -> Reta 20mg | S40: 350 | V40: Pep Pen Cartridge | W40: 1
J41: Mont 4+ per RX | O41: Pack of 30 needles & 15 alcohol Prep | Q41: 15 | R41: ='Pep Costs'!A44 -> Reta 30mg | S41: ='Pep Costs'!C44 -> 270
O42: Pep Pen Cartridge | Q42: 1
A43: Obvioulsy every 6 months they need to do blood (or at the NP discretion).

Sheet Pep Costs
A1: VIP Membership | B1: N/A | D1: 0 | E1: 200
A2: Monthly Offive Visit | D2: $150/visit | E2: $0/visit
A4: Peptide | B4: 2/2/2026 COST | C4: Plus $100 (includes BAC) | D4: Regular Price Per Unit | E4: VIP Price Per Unit | F4: Column1 | K4: Week 1-4 | L4: Week 5-8 | M4: Week 9-12 | N4: Week 13-16
A5: AOD-9604 5mg | B5: 45 | C5: =+B5+10 -> 55 | F5: downloaded
A6: BAC Water 10ml | B6: 24 | C6: =+B6+100 -> 124
A7: BB10 5/5 | B7: 65 | C7: =+B7+100 -> 165
A8: BB20 | B8: 85 | C8: =+B8+100 -> 185
A9: BPC-157 5mg | B9: 40 | C9: =+B9+100 -> 140 | F9: downloaded
A10: BPC-157 10mg | B10: =45*1.0775 -> 48.4875 | C10: =+B10+100 -> 148.4875 | F10: downloaded
A11: BPC-157 /TB500 20 mg | B11: 150 | C11: =+B11+100 -> 250 | D11: ='BPC+TB500'!J2 -> 0 | E11: ='BPC+TB500'!K2 -> 0 | F11: downloaded | G11: 4/4/26 price now $110 | K11: 238 units (.79 vial) | L11: 420 units (1.4 vials) | M11: 420 units (1.4 vials) | O11: from the start, 2 vials will last almost 8 weeks…..To get from Week 1-12 you need 3.59 vials
A12: BPC-157 20 mg | B12: 155 | C12: =+B12+100 -> 255
A13: Cag 5mg | B13: 65 | C13: =+B13+100 -> 165
A14: Cag 10mg | B14: 105 | C14: =+B14+100 -> 205
A15: CJC-1295/Ipa 5/5 | B15: 60 | C15: =+B15+100 -> 160
A16: DSIP 5mg | B16: 37 | C16: =+B16+100 -> 137 | D16: ='DSIP 5mg'!J2 -> 0 | E16: ='DSIP 5mg'!K2 -> 0 | F16: downloaded | K16: 294 units (1 vial) | L16: 546 units (1.84 vials) | M16: 714 units (2.38 vials) | O16: from the strat 1 vial will last 1 month….To get from Week1 -12 you need 5.22 vials
A17: DSIP 10mg | B17: 47 | C17: =+B17+100 -> 147 | D17: ='DSIP 10mg'!J2 -> 0 | E17: ='DSIP 10mg'!K2 -> 0 | F17: downloaded | K17: 154 units (.51 vials) | L17: 252 units (0.84 vials) | M17: 252 units (0.84 vials) | O17: from the start 2 vials will last approx 6.5 weeks….To get from week 1-12 you need 2.19 vials
A18: Epithalon 5mg | B18: 37 | C18: =+B18+100 -> 137
A19: Epithalon 10mg | B19: 45 | C19: =+B19+100 -> 145 | F19: downloaded
A20: Epithalon 50mg | B20: =70*1.0775 -> 75.425 | C20: =+B20+100 -> 175.425
A21: GHK-CU 50mg | B21: 45 | C21: =+B21+100 -> 145 | D21: ='GHK-CU 50'!K2 -> 0 | E21: ='GHK-CU 50'!L2 -> 0 | F21: downloaded | K21: 168 units (0.56 vials) | L21: 252 units (0.84 vials) | M21: 336 units (1.12 vials) | O21: from the start 2 vials will last 6 weeks….To get from week 1-12 you need 2.52 vials
A22: GHK-CU 100mg | B22: 65 | C22: =+B22+100 -> 165 | F22: downloaded
A23: GLOW 50mg | B23: 65 | C23: =+B23+100 -> 165
A24: GLOW 70mg | B24: 105 | C24: =+B24+100 -> 205 | D24: ='Glow 70'!K2 -> 0 | E24: ='Glow 70'!L2 -> 0 | F24: downloaded | K24: 280 units (0.93 vials) | O24: I only have a 1 month protocol
A25: Glutathione 600mg | B25: 45 | C25: =+B25+100 -> 145 | F25: downloaded
A26: HCG 5000IU | B26: 45 | C26: =+B26+100 -> 145 | F26: downloaded
A27: Hexarelin 10 mg | B27: 70 | C27: =+B27+100 -> 170 | F27: fhgh
A28: HGH 15IU | B28: 65 | C28: =+B28+100 -> 165
A29: HGH 24IU | B29: 77 | C29: =+B29+100 -> 177
A30: HGH 36IU | B30: 90 | C30: =+B30+100 -> 190
A31: Kisspep 10mg | B31: 50 | C31: =+B31+100 -> 150 | D31: =Kissp!K2 -> 0 | E31: =Kissp!L2 -> 0 | F31: downloaded | K31: 126 units (0.42 vials) | L31: 168 units (0.56 vials) | M31: 168 units (0.56 vials) | O31: from the start 1 vial will last 8 weeks….To get from week 1-12 you need 1.54 vials
A32: KLOW 80mg | B32: 125 | C32: =+B32+100 -> 225 | D32: ='KLOW 80'!K2 -> 0 | E32: ='KLOW 80'!L2 -> 0 | F32: email | K32: 308 units (1.03 vials) | L32: 616 units (2.05 vials) | M32: 420 units (1.4 vials) | O32: from the start 1 vial will last the first month…..To get from week 1-12 you need 4.48 vials
A33: Lipo-C w/ B12 | B33: 55 | C33: =+B33+100 -> 155
A34: Melatonin-11 | B34: 45 | C34: =+B34+100 -> 145
A35: Mots-C 10mg | B35: =55*1.0775 -> 59.2625 | C35: =+B35+100 -> 159.2625 | F35: downloaded | K35: 252 units (0.84 vials) | L35: 588 units (1.96 vials) | M35: 840 units (2.8 vials) | O35: from the start 2 vials will last just over 6 weeks….To get from week 1-12 you need 5.6 vials
A36: MT 2 10mg | B36: 45 | C36: =+B36+100 -> 145
A37: NAD+ 1000mg | B37: 75 | C37: =+B37+100 -> 175 | D37: =+'NAD+ Acute'!K2 -> 0 | E37: ='NAD+ Acute'!L2 -> 0 | F37: downloaded
A38: NAD+ 500mg | B38: 55 | C38: =+B38+100 -> 155 | F38: downloaded | K38: Acute: 679 units (2.26 vials) | L38: 840 units (2.8 vials) | M38: 840 units (2.8 vials) | O38: from the start 2.26 vials last 4 weeks…To get from week 1-12 you need 7.86 vials
A39: NAT+ 700mg | B39: =46*1.0775 -> 49.565 | C39: =+B39+50 -> 99.565 | D39: =+B39+50 -> 99.565 | E39: =+B39+30 -> 79.565
A40: Oxytocin 5mg | B40: 45 | C40: =+B40+100 -> 145 | F40: downloaded
A41: PT141 10 mg | B41: 55 | C41: =+B41+100 -> 155 | D41: ='PT-141 10mg'!K2 -> 0 | E41: ='PT-141 10mg'!#REF! -> #REF! | F41: downloaded
A42: Reta 10mg | B42: 100 | C42: =+B42+100 -> 200 | F42: downloaded | G42: 2/2/26: $100 | H42: 2/25/26: $85
A43: Reta 20mg | B43: 140 | C43: =+B43+100 -> 240 | D43: $350/mo | E43: $350/mo | F43: downloaded | G43: 2/2/26: $140 | H43: 2/25/26: $130 | I43: 4/4/2: $75 | J43: 4/24/26: $70.04 | K43: 120 units (.4 vial) | L43: 240 units (0.8 vial) | M43: 360 units (1.2 vials) | N43: 480 units (1.8 vials) | O43: from the start 1 vial will last almost 8 weeks…... To get from Week 1 to Week 16 you need 4.2 vials
A44: Reta 30mg | B44: 170 | C44: =+B44+100 -> 270 | F44: downloaded | G44: 2/2/26: $170 | H44: 2/25/26: $150
A45: Selank 10mg | B45: 45 | C45: =+B45+100 -> 145 | F45: downloaded
A46: Semax 10mg | B46: 45 | C46: =+B46+100 -> 145 | F46: downloaded
A47: SS-31 10mg | B47: =100*1.0775 -> 107.75 | C47: =+B47+100 -> 207.75 | F47: downloaded
A48: Sterile Deion Water 10ml | B48: 15 | C48: =+B48+100 -> 115
A49: Sterile Water 3ml | B49: 10 | C49: =+B49+100 -> 110
A50: TB500 10mg | B50: 60 | C50: =+B50+100 -> 160 | F50: downloaded
A51: Tesamorelin 10mg | B51: 75 | C51: =+B51+100 -> 175 | D51: ='Tesam 10'!K2 -> 0 | E51: ='Tesam 10'!L2 -> 0 | F51: downloaded | K51: 1470 units (4.9 vials) | L51: 1680 units (5.6 vials) | M51: 1680 units (5.6 vials) | O51: so the first month you need 5 vials….to get from Week 1-12 you need 16.1 vials
A52: Tesofensine | B52: 125 | C52: =+B52+100 -> 225
A53: Tirz 10mg | B53: 105 | C53: =+B53+100 -> 205 | F53: downloaded | G53: 2/2/26: $105 | H53: 2/25/26: $95
A54: Tirz 15mg | B54: 145 | C54: =+B54+100 -> 245 | F54: downloaded | G54: 2/2/26: $145 | H54: 2/25/26: $125
A55: Tirz 30mg | B55: 195 | C55: =+B55+100 -> 295 | D55: $350/mo | E55: $350/mo | F55: downloaded | G55: 2/2/26: $195 | H55: 2/25/26: $170 | K55: 100 units (0.3 vials) | L55: 200 units (.67 vials) | M55: 300 units (1 vial) | N55: 400 units (1.3 vials) | O55: from the start 2 vials will last 12 weeks…..to get from Week 1-16 you need 3.33 vials)
A56: Tirz 5mg | B56: 75 | C56: =+B56+100 -> 175 | F56: downloaded
A57: Tirz 60mg | B57: 255 | C57: =+B57+100 -> 355
A58: VIP 10mg | B58: 55 | C58: =+B58+100 -> 155
A59: Tablets/Caps | B59: COST | C59: Plus $50 | D59: Regular Price | E59: VIP Price
A60: 5 Amino 1q 50mg | B60: =65*1.0775 -> 70.0375 | C60: =+Table5[[#This Row],[2/2/2026 COST]]+100 -> 170.0375 | D60: =+Table5[[#This Row],[2/2/2026 COST]]+100 -> 170.0375 | E60: =+Table5[[#This Row],[2/2/2026 COST]]+30 -> 100.0375
A61: BPC 500mcg | B61: 114 | C61: =+Table5[[#This Row],[2/2/2026 COST]]+100 -> 214 | D61: =+Table5[[#This Row],[2/2/2026 COST]]+100 -> 214 | E61: =+Table5[[#This Row],[2/2/2026 COST]]+30 -> 144
A62: Methaline Blue 20mg | B62: 85 | C62: =+Table5[[#This Row],[2/2/2026 COST]]+100 -> 185 | D62: =+Table5[[#This Row],[2/2/2026 COST]]+100 -> 185 | E62: =+Table5[[#This Row],[2/2/2026 COST]]+30 -> 115
A63: Tesofensine 500mcg (1tab daily) | B63: 65 | C63: =+Table5[[#This Row],[2/2/2026 COST]]+100 -> 165 | D63: =+Table5[[#This Row],[2/2/2026 COST]]+100 -> 165 | E63: =+Table5[[#This Row],[2/2/2026 COST]]+30 -> 95
A64: Semaglutide 10mg | B64: 85 | C64: =+Table5[[#This Row],[2/2/2026 COST]]+100 -> 185 | D64: =+Table5[[#This Row],[2/2/2026 COST]]+100 -> 185 | E64: =+Table5[[#This Row],[2/2/2026 COST]]+30 -> 115
A65: GHK-CU 100mg | B65: 65 | C65: =+Table5[[#This Row],[2/2/2026 COST]]+100 -> 165 | D65: =+Table5[[#This Row],[2/2/2026 COST]]+100 -> 165 | E65: =+Table5[[#This Row],[2/2/2026 COST]]+30 -> 95
A66: BPC-157 10mg | B66: 55 | C66: =+Table5[[#This Row],[2/2/2026 COST]]+100 -> 155 | D66: =+Table5[[#This Row],[2/2/2026 COST]]+100 -> 155 | E66: =+Table5[[#This Row],[2/2/2026 COST]]+30 -> 85
A67: SLU PP 332(500mcg)x100 | B67: 70 | C67: =+Table5[[#This Row],[2/2/2026 COST]]+100 -> 170 | D67: =+Table5[[#This Row],[2/2/2026 COST]]+100 -> 170 | E67: =+Table5[[#This Row],[2/2/2026 COST]]+30 -> 100
A68: SLUP PP 332(1mg) x100 | B68: 90 | C68: =+Table5[[#This Row],[2/2/2026 COST]]+100 -> 190 | D68: =+Table5[[#This Row],[2/2/2026 COST]]+100 -> 190 | E68: =+Table5[[#This Row],[2/2/2026 COST]]+30 -> 120
A69: Slu PP 332(5mg)x100 | B69: 110 | C69: =+Table5[[#This Row],[2/2/2026 COST]]+100 -> 210 | D69: =+Table5[[#This Row],[2/2/2026 COST]]+100 -> 210 | E69: =+Table5[[#This Row],[2/2/2026 COST]]+30 -> 140
A70: Nasal Sprays | B70: COST | C70: Plus $50 | D70: Regular Price | E70: VIP Price
A71: DSIP | B71: 70 | C71: =+Table5[[#This Row],[2/2/2026 COST]]+100 -> 170 | D71: =+Table5[[#This Row],[2/2/2026 COST]]+100 -> 170 | E71: =+Table5[[#This Row],[2/2/2026 COST]]+30 -> 100
A72: Selank Nasal | B72: 75 | C72: =+Table5[[#This Row],[2/2/2026 COST]]+100 -> 175 | D72: =+Table5[[#This Row],[2/2/2026 COST]]+100 -> 175 | E72: =+Table5[[#This Row],[2/2/2026 COST]]+30 -> 105
A73: Semax Nasal | B73: 75 | C73: =+Table5[[#This Row],[2/2/2026 COST]]+100 -> 175 | D73: =+Table5[[#This Row],[2/2/2026 COST]]+100 -> 175 | E73: =+Table5[[#This Row],[2/2/2026 COST]]+30 -> 105
A74: Oxytocin Nasal | B74: 75 | C74: =+Table5[[#This Row],[2/2/2026 COST]]*1.15 -> 86.25 | D74: =+Table5[[#This Row],[2/2/2026 COST]]+100 -> 175 | E74: =+Table5[[#This Row],[2/2/2026 COST]]+30 -> 105
A75: Supplies | B75: Cost | C75: 0.15 | D75: Regular Price | E75: VIP Price
A76: Peptide Pens | B76: 25 | D76: 85 | E76: 85
A77: Peptide Pen Needle Tips (500 for $55) | B77: 0.11
A78: Pep Pen Cartrdiges (100 for $60) | B78: 0.6
A79: 31 Gauge Syringe (700): Each | B79: 0.11
A85: ARA-290 10mg | B85: =55*1.0775 -> 59.2625 | G85: as of 4/24/26

Sheet FAQ
A1: Frequently asked questions
A3: What is a peptide? Are short chains of amino acids, the same building blocks that make up proteins.
A5: How does it work? Think of a text message in your body - it tells yourself to "stimulate collagen" or " lower inflammation"
A6: It goes straight tho the source, bind to a receptor and triggers a targeted response. They support natural functions. It nudges your system.
A8: How young can you start peptides? Age 15
A10: Should everyone get the same regimine? No. This is not a one size fits all. Different options because of sex, age, athletes vs busy professionals
A11: autoimmune issues vs those chasing peak performance. .
A13: Are peptides synthetic? Yes and No. Some peptides are produced naturally in our body for example insulin (which manages blood sugar),
A14: oxytocin (which influences mood and and bonding), and glucagon (which helps regulate glucose levels). Others are made synthetically in labs
A15: That word- synthetic- tends to scare people but it shouldn’t. Synthetic peptides are not foreign nor dangerous by default. They are simply
A16: Engineered copies of what your body already produces, sometimes with slight modifications to make them more stable, longer -lasing or
A17: more effective.
... A22: Are peptides safe for long term use? Yes, as long a cycled, monitored and respected. Go on, assess, go off, then reassess.

Sheet Whats it for
A1: Wha is it for? | F1: Peptides | G1: Category
A3: Peptide | B3: Column1 | C3: Column4 | D3: Column5
A4: AOD-9604 5mg | B4: Fat Loss and Metabolic support
A5: BAC Water 10ml
A6: BB10 5/5
A7: BB20
A8: BPC-157 5mg | B8: Muscle growth and recovery | C8: Pain relief/gut repair/resilience
A9: BPC-157 10mg | B9: Muscle growth and recovery | C9: Pain relief/gut repair/resilience
A10: BPC-157 /TB500 20 mg | B10: Muscle growth and recovery | C10: Pain relief/gut repair/resilience
A11: BPC-157 20 mg | B11: Muscle growth and recovery | C11: Pain relief/gut repair/resilience
A12: Cag 5mg
A13: Cag 10mg
A14: CJC-1295/Ipa 5/5 | B14: Muscle growth and recovery
A15: DSIP 5mg | B15: Stress and Anxiety | C15: Sleep
A16: DSIP 10mg | B16: Stress and Anxiety | C16: Sleep
A17: Epithalon 5mg | B17: Longevity and cellular renewal | C17: Sleep
A18: Epithalon 10mg | B18: Longevity and cellular renewal | C18: Sleep
A19: Epithalon 50mg | B19: Longevity and cellular renewal | C19: Sleep
A20: GHK-CU 50mg | B20: Skin and aesthetics/Anti -aging
A21: GHK-CU 100mg | B21: Skin and aesthetics/Anti -aging
A22: GLOW 50mg | B22: Skin and aesthetics/Anti -aging
A23: GLOW 70mg | B23: Skin and aesthetics/Anti -aging
A24: Glutathione 600mg
A25: HCG 5000IU
A26: Hexarelin 10 mg
A27: HGH 15IU
A28: HGH 24IU
A29: HGH 36IU
A30: Kisspep 10mg | B30: Hormonal balance 40+
A31: KLOW 80mg | B31: Skin and aesthetics/Anti -aging
A32: Lipo-C w/ B12
A33: Melatonin-11 | B33: Sexual Health
A34: Mots-C 10mg | B34: Fat Loss and Metabolic support | C34: Longevity and cellular renewal | D34: Mitochondrial repair and Energy
A35: MT 2 10mg
A36: NAD+ 1000mg
A37: NAD+ 500mg
A38: Oxytocin 5mg | B38: Stress and Anxiety | C38: Sexual Health
A39: PT141 10 mg | B39: Sexual Health | G39: EXTRAS:
A40: Reta 10mg | B40: Cardiometabolic/lipids/ liver/glucose control/weight management | G40: 29-31 gauge needles,
A41: Reta 20mg | B41: Cardiometabolic/lipids/ liver/glucose control/weight management | G41: sub Q for most
A42: Reta 30mg | B42: Cardiometabolic/lipids/ liver/glucose control/weight management | G42: semax, selank and epitalon have intranasal option
A43: Selank 10mg | B43: Stress and Anxiety | G43: topical exists for GHKCu, and AOD 9604
A44: Semax 10mg | B44: Brain Health: focus, mood, and mental clarity | G44: inject same day and time and rotate site of injection
A45: SS-31 10mg | B45: Longevity and cellular renewal | C45: Mitochondrial repair and Energy | G45: track key metrics: sleep, energy, and mood
A46: Sterile Deion Water 10ml | G46: Cycle peptides no longer than 12 weeks. 2-4 week break between
A47: Sterile Water 3ml
A48: TB500 10mg | B48: Muscle growth and recovery | G48: Run baseline and fup labs.
A49: Tesamorelin 10mg | B49: Hormonal balance 40+ | G49: Baseline labs:
A50: Tesofensine | G50: IGF-1: for gh related peptides (cjc and ipa)
A51: Tirz 10mg | G51: fasing insulin +Glucose+A1C : for metabolic markers
A52: Tirz 15mg | G52: CRP for systemic inflammation
A53: Tirz 30mg | G53: Vit D: for immune, mood and recovery support
A54: Tirz 5mg | G54: CBC with differential : for immune baseline
A55: Tirz 60mg | G55: TSH, free T3, free T4, : for thyroid health
A56: VIP 10mg | G56: Ferritin, and B12: for energy metabolism
A57: Dihexa | B57: Brain Health: focus, mood, and mental clarity
A58: Cerebrolysin | B58: Brain Health: focus, mood, and mental clarity
A59: Ipamoralin | B59: Muscle growth and recovery
A60: KPV | B60: Pain relief/gut repair/resilience
A61: Thymosin-alpha -1 | B61: Pain relief/gut repair/resilience | C61: Immune and support defense
A62: LL-37 | B62: Immune and support defense
A63: Epitalon | B63: Longevity and cellular renewal
A64: Melanotan I | B64: Tanning
A74: Tablets/Caps | B74: Column3 | C74: Column4
A75: 5 Amino 1q 50mg | B75: Fat Loss and Metabolic support | C75: Mitochondrial repair and Energy
A76: BPC 500mcg | B76: Muscle growth and recovery | C76: Pain relief/gut repair/resilience
A77: Methaline Blue 20mg
A78: Tesofensine 500mcg (1tab daily)
A79: Semaglutide 10mg
A80: GHK-CU 100mg | B80: Skin and aesthetics/Anti -aging
A81: BPC-157 10mg | B81: Muscle growth and recovery
A82: SLU PP 332(500mcg)x100 | B82: Exercise | C82: *Start at 500mcg. You can start at 1. Depends on effect and wht they feel in7 days. Daily 30-40min before exercise or without exercise in the morning.
A83: SLUP PP 332(1mg) x100 | B83: Exercise | C83: *Start at 500mcg. You can start at 1. Depends on effect and wht they feel in7 days. Daily 30-40min before exercise or without exercise in the morning.
A84: Slu PP 332(5mg)x100 | B84: Exercise | C84: *Start at 500mcg. You can start at 1. Depends on effect and wht they feel in7 days. Daily 30-40min before exercise or without exercise in the morning.
A87: Nasal Sprays | B87: Column3 | C87: Column4
A88: DSIP | B88: Stress and Anxiety
A89: Selank Nasal | B89: Stress and Anxiety
A90: Semax Nasal | B90: Brain Health: focus, mood, and mental clarity
A91: Oxytocin Nasal | B91: Stress and Anxiety | C91: Sexual Health

Sheet COSTS
A1: Amazon | B1: Cost | C1: With Tax | D1: Cost EACh | F1: COST | G1: Sell
A2: Bubble Wrap (200) | B2: 24.69 | C2: =+B2*1.1 -> 27.159 | D2: =+C2/200 -> 0.135795 | E2: One | F2: 0.12
A3: Mailer (30) | B3: 26.99 | C3: =+B3*1.1 -> 29.689 | D3: =+C3/30 -> 0.98963333 | E3: One | F3: 0.9
A4: Labels (315) | B4: 1.68 | C4: =+B4*1.1 -> 1.848 | D4: =+C4/315 -> 0.0058666667 | E4: One | F4: 0.01
A5: Gift Bag (50) | B5: 17.09 | C5: =+B5*1.1 -> 18.799 | D5: =+C5/50 -> 0.37598 | E5: One | F5: 0.37
A6: Sticker
A7: Pencil Case (6) | B7: 19.93 | C7: =+B7*1.1 -> 21.923 | D7: =+C7/6 -> 3.6538333 | E7: One | F7: 3.32 | G7: 4 | I7: =SUM(F2:F7) -> 4.72
A8: Alcohol Prep (Box of 100) | B8: 3.98 | C8: =+B8*1.1 -> 4.378 | D8: =+C8/100 -> 0.04378 | E8: Box | F8: 3.98 | G8: 5
A9: Orange 0.5ml Syrnge (100) | B9: 21.99 | C9: =+B9*1.1 -> 24.189 | D9: =+C9/100 -> 0.24189 | E9: Ten | F9: =10*0.22 -> 2.2
A10: Blue 3ml Syring (100) | B10: 17.99 | C10: =+B10*1.1 -> 19.789 | D10: =+C10/100 -> 0.19789 | E10: Two | F10: =0.18*2 -> 0.36
A11: Vial Caps (14) | B11: 3.79 | C11: =+B11*1.1 -> 4.169 | D11: =+C11/14 -> 0.29778571 | E11: One | F11: 0.27
A12: Peptide Needles 100 31g 6mm | B12: 9.99 | D12: =+B12/100 -> 0.0999 | E12: Each
A13: BAC 10ml (10) | B13: 30 | C13: =+B13*1.1 -> 33 | D13: =C13/10 -> 3.3 | E13: Each | G13: 10
A14: BAC 3ml (10) | B14: 30 | C14: =+B14*1.1 -> 33 | D14: =+C14/10 -> 3.3 | E14: Each | G14: 10
A15: BACK 30ml (4) | B15: 20.13 | C15: =+B15*1.1 -> 22.143 | D15: =+C15/4 -> 5.53575 | E15: Each | G15: 10
A16: BACK 20ml (6) | B16: 25.99 | C16: =+B16*1.1 -> 28.589 | D16: =+C16/6 -> 4.7648333 | E16: Each | G16: 10
A21: Mackay | B21: Each pen comes with a case and Two cartridges, so thent he patient only need to by the difference in cartridges
A22: Peptide Pen | D22: 45 | E22: Each | G22: 85
A23: 100 cartridges ($0.60 each) | B23: =0.6*100 -> 60 | D23: =+B23/100 -> 0.6 | E23: Each | G23: 2 | H23: each cartridge to the patient | L23: 46114
A24: 100 insulin syringe ( orange?) | B24: 34 | D24: =+B24/100 -> 0.34 | E24: Each
A25: 0.5ml syringe (1000 for $100) | B25: 100 | D25: =+B25/1000 -> 0.1 | E25: Each | L25: 46114
A26: BAC
A28: McKesson
A29: 30ml BAC $24.99 for 75) | B29: 24.99 | D29: =+B29/75 -> 0.3332
B1048566: =SUM(B1:B1048565) -> 473.23 | D1048566: =SUM(D1:D1048565) -> 69.316137

Sheet GLP-3Re
A1: GLP-3Re 20mg | N1: Daily
A2: cost | B2: ='Pep Costs'!B43 -> 140 | E2: Reg Price per VIAL | H2: Per Unruh Reta is going to be a FLAT $350.00 per month for the first 4 months up to 120 units per week for one month. | N2: Every Other Day
A3: BAC | B3: 3.3 | D3: ADD per vial | N3: Weekly
B4: =SUM(B2:B3) -> 143.3 | D4: 100 | E4: =+D4+B4 -> 243.3
A6: Per Unit | B6: =+B4/300 -> 0.47766667
D7: Per Unit | E7: =+E4/300 -> 0.811
A13: CUSTOM PROTOCOL
B15: Frequency of Injection | C15: mcg | D15: Units per Injections | E15: # of Injections | F15: Units Needed | J15: COST | K15: Reg Price | P15: =204.9-195.1 -> 9.8
A16: Week | B16: Every Other Day | D16: 15 | E16: 3 | F16: =+D16*E16 -> 45 | H16: =ROUNDUP(F20,0) -> 210 | I16: Units | J16: =+B6*F20 -> 100.31 | K16: =+F20*E7 -> 170.31
A17: Week | B17: Every Other Day | D17: 15 | E17: 4 | F17: =+D17*E17 -> 60 | H17: =E20 -> 14 | I17: Syringe | J17: =+H17*0.24 -> 3.36
A18: Week | B18: Every Other Day | D18: 15 | E18: 3 | F18: =+D18*E18 -> 45 | H18: =E20 -> 14 | I18: Alochol Prep | J18: =0.05*H18 -> 0.7 | M18: Profit | N18: =+K20-J20 -> 66.63
A19: Week | B19: Every Other Day | D19: 15 | E19: 4 | F19: =+D19*E19 -> 60 | H19: 0 | I19: Case | J19: =H19*3.65 -> 0
E20: =SUM(E16:E19) -> 14 | F20: =SUM(F16:F19) -> 210 | J20: =SUM(J16:J19) -> 104.37 | K20: =ROUNDUP(SUM(K16:K19),0) -> 171
F21: =+F20/300 -> 0.7 | I21: Per Unit | J21: =+J20/H16 -> 0.497 | K21: =+K20/H16 -> 0.81428571
A27: Month 1 | B27: Frequency of Injection | C27: mcg | D27: Units per Injections | E27: # of Injections | F27: Units Needed
A28: 1st Injection | B28: Once | C28: 350mcg | D28: 5 | E28: 1 | F28: =+D28*E28 -> 5 | J28: COST | K28: Reg Price | Q28: week 1 | R28: 10 | T28: 0.7mg =700mcg 14 20mg/ml = 10 units
A29: 2nd 3-4 days | B29: Once | C29: 350mcg | D29: 5 | E29: 1 | F29: =+D29*E29 -> 5 | H29: =ROUNDUP(F33,0) -> 40 | I29: Units | J29: =+B6*F33 -> 19.106667 | K29: =F33*E7 -> 32.44 | Q29: week 2 | R29: 10
A30: Week 2 | B30: Weekly | C30: 700mcg | D30: 10 | E30: =IF(B30="Daily",7, IF(B30="Weekly",1, IF(B30="Every Other Day",4,""))) -> 1 | F30: =+D30*E30 -> 10 | H30: =E33 -> 5 | I30: Syringe | J30: =H30*0.24 -> 1.2 | Q30: week 3 | R30: 20
A31: Week 3 | B31: Weekly | C31: 700mcg | D31: 10 | E31: =IF(B31="Daily",7, IF(B31="Weekly",1, IF(B31="Every Other Day",4,""))) -> 1 | F31: =+D31*E31 -> 10 | H31: =H30 -> 5 | I31: Alochol Prep | J31: =+H31*0.05 -> 0.25 | Q31: week 4 | R31: 20
A32: Week 4 | B32: Weekly | C32: 700mcg | D32: 10 | E32: =IF(B32="Daily",7, IF(B32="Weekly",1, IF(B32="Every Other Day",4,""))) -> 1 | F32: =+D32*E32 -> 10 | H32: 1 | I32: Case | J32: =H32*3.65 -> 3.65 | M32: Profit | N32: =+K33-J33 -> 325.79333
E33: =SUM(E28:E32) -> 5 | F33: =SUM(F28:F32) -> 40 | J33: =SUM(J29:J32) -> 24.206667 | K33: 350
E34: Number of vials = | F34: =+F33/300 -> 0.13333333 | I34: Per Unit | J34: =+J33/H29 -> 0.60516667 | K34: =+K33/H29 -> 8.75
A38: Month 2 | B38: Frequency of Injection | C38: mcg | D38: Units per Injections | E38: # of Injections | F38: Units Needed | J38: COST | K38: Reg Price
A39: Week 5 | B39: Weekly | C39: 1350 | D39: 20 | E39: =IF(B39="Daily",7, IF(B39="Weekly",1, IF(B39="Every Other Day",4,""))) -> 1 | F39: =+D39*E39 -> 20 | H39: =ROUNDUP(F43,0) -> 80 | I39: Units | J39: =+B6*F43 -> 38.213333 | K39: =+F43*E7 -> 64.88
A40: Week 6 | B40: Weekly | C40: 1350 | D40: 20 | E40: =IF(B40="Daily",7, IF(B40="Weekly",1, IF(B40="Every Other Day",4,""))) -> 1 | F40: =+D40*E40 -> 20 | H40: =E43 -> 4 | I40: Syringe | J40: =H40*0.24 -> 0.96
A41: Week 7 | B41: Weekly | C41: 1350 | D41: 20 | E41: =IF(B41="Daily",7, IF(B41="Weekly",1, IF(B41="Every Other Day",4,""))) -> 1 | F41: =+D41*E41 -> 20 | H41: =E43 -> 4 | I41: Alochol Prep | J41: =+H41*0.05 -> 0.2
A42: Week 8 | B42: Weekly | C42: 1350 | D42: 20 | E42: =IF(B42="Daily",7, IF(B42="Weekly",1, IF(B42="Every Other Day",4,""))) -> 1 | F42: =+D42*E42 -> 20 | H42: 0 | I42: Case | J42: =H42*3.65 -> 0
E43: =SUM(E39:E42) -> 4 | F43: =SUM(F39:F42) -> 80 | J43: =SUM(J39:J42) -> 39.373333 | K43: =K33 -> 350 | M43: Profit | N43: =+K43-J43 -> 310.62667
E44: Number of vials = | F44: =+F43/300 -> 0.26666667 | I44: Per Unit | J44: =+J43/H39 -> 0.49216667 | K44: =+K43/H39 -> 4.375
A50: Month 3 | B50: Frequency of Injection | C50: mcg | D50: Units per Injections | E50: # of Injections | F50: Units Needed | J50: COST | K50: Reg Price | S50: =30*0.85 -> 25.5
A51: Week 9 | B51: Weekly | C51: 2000 | D51: 30 | E51: =IF(B51="Daily",7, IF(B51="Weekly",1, IF(B51="Every Other Day",4,""))) -> 1 | F51: =+D51*E51 -> 30 | H51: =ROUNDUP(F55,0) -> 120 | I51: Units | J51: =+B6*F55 -> 57.32 | K51: =+F55*E7 -> 97.32
A52: week 10 | B52: Weekly | C52: 2000 | D52: 30 | E52: =IF(B52="Daily",7, IF(B52="Weekly",1, IF(B52="Every Other Day",4,""))) -> 1 | F52: =+D52*E52 -> 30 | H52: =E55 -> 4 | I52: Syringe | J52: =+H52*0.24 -> 0.96
A53: Week 11 | B53: Weekly | C53: 2000 | D53: 30 | E53: =IF(B53="Daily",7, IF(B53="Weekly",1, IF(B53="Every Other Day",4,""))) -> 1 | F53: =+D53*E53 -> 30 | H53: =E55 -> 4 | I53: Alochol Prep | J53: =H53*0.05 -> 0.2
A54: Week 12 | B54: Weekly | C54: 2000 | D54: 30 | E54: =IF(B54="Daily",7, IF(B54="Weekly",1, IF(B54="Every Other Day",4,""))) -> 1 | F54: =+D54*E54 -> 30 | H54: 0 | I54: Case | J54: =H54*3.65 -> 0
E55: =SUM(E51:E54) -> 4 | F55: =SUM(F51:F54) -> 120 | J55: =SUM(J51:J54) -> 58.48 | K55: =K33 -> 350 | M55: Profit | N55: =+K55-J55 -> 291.52
E56: Number of vials = | F56: =+F55/300 -> 0.4 | I56: Per Unit | J56: =+J55/H51 -> 0.48733333 | K56: =+K55/H51 -> 2.9166667
A60: Month 4 | B60: Frequency of Injection | C60: mcg | D60: Units per Injections | E60: # of Injections | F60: Units Needed | J60: COST | K60: Reg Price | P60: =0.2+0.27+0.33+0.4 -> 1.2
A61: Week 13 | B61: Weekly | C61: 2650 | D61: 40 | E61: =IF(B61="Daily",7, IF(B61="Weekly",1, IF(B61="Every Other Day",4,""))) -> 1 | F61: =+D61*E61 -> 40 | H61: =ROUNDUP(F65,0) -> 160 | I61: Units | J61: =F65*B6 -> 76.426667 | K61: =+F65*E7 -> 129.76
A62: Week 14 | B62: Weekly | C62: 2650 | D62: 40 | E62: =IF(B62="Daily",7, IF(B62="Weekly",1, IF(B62="Every Other Day",4,""))) -> 1 | F62: =+D62*E62 -> 40 | H62: =E65 -> 4 | I62: Syringe | J62: =+H62*0.24 -> 0.96
A63: Week 15 | B63: Weekly | C63: 2650 | D63: 40 | E63: =IF(B63="Daily",7, IF(B63="Weekly",1, IF(B63="Every Other Day",4,""))) -> 1 | F63: =+D63*E63 -> 40 | H63: =E65 -> 4 | I63: Alochol Prep | J63: =H63*0.05 -> 0.2
A64: Week 16 | B64: Weekly | C64: 2650 | D64: 40 | E64: =IF(B64="Daily",7, IF(B64="Weekly",1, IF(B64="Every Other Day",4,""))) -> 1 | F64: =+D64*E64 -> 40 | H64: 0 | I64: Case | J64: =H64*3.65 -> 0
E65: =SUM(E61:E64) -> 4 | F65: =SUM(F61:F64) -> 160 | J65: =SUM(J61:J64) -> 77.586667 | K65: =K33 -> 350 | M65: Profit | N65: =+K65-J65 -> 272.41333
E66: Number of vials = | F66: =+F65/300 -> 0.53333333 | I66: Per Unit | J66: =+J65/H61 -> 0.48491667 | K66: =+K65/H61 -> 2.1875
A70: Month 5 | B70: Frequency of Injection | C70: mcg | D70: Units per Injections | E70: # of Injections | F70: Units Needed | J70: COST | K70: Reg Price
A71: Week 17 | B71: Weekly | C71: 3300 | D71: 50 | E71: =IF(B71="Daily",7, IF(B71="Weekly",1, IF(B71="Every Other Day",4,""))) -> 1 | F71: =+D71*E71 -> 50 | H71: =ROUNDUP(F75,0) -> 200 | I71: Units | J71: =F75*B6 -> 95.533333 | K71: =+F75*E7 -> 162.2
A72: Week 18 | B72: Weekly | C72: 3300 | D72: 50 | E72: =IF(B72="Daily",7, IF(B72="Weekly",1, IF(B72="Every Other Day",4,""))) -> 1 | F72: =+D72*E72 -> 50 | H72: =E75 -> 4 | I72: Syringe | J72: =+H72*0.24 -> 0.96
A73: Week 19 | B73: Weekly | C73: 3300 | D73: 50 | E73: =IF(B73="Daily",7, IF(B73="Weekly",1, IF(B73="Every Other Day",4,""))) -> 1 | F73: =+D73*E73 -> 50 | H73: =E75 -> 4 | I73: Alochol Prep | J73: =H73*0.05 -> 0.2
A74: Week 20 | B74: Weekly | C74: 3300 | D74: 50 | E74: =IF(B74="Daily",7, IF(B74="Weekly",1, IF(B74="Every Other Day",4,""))) -> 1 | F74: =+D74*E74 -> 50 | H74: 0 | I74: Case | J74: =H74*3.65 -> 0
E75: =SUM(E71:E74) -> 4 | F75: =SUM(F71:F74) -> 200 | J75: =SUM(J71:J74) -> 96.693333 | K75: 350 | M75: Profit | N75: =+K75-J75 -> 253.30667
E76: Number of vials = | F76: =+F75/300 -> 0.66666667 | I76: Per Unit | J76: =+J75/H71 -> 0.48346667 | K76: =+K75/H71 -> 1.75
A80: Month 6 | B80: Frequency of Injection | C80: mcg | D80: Units per Injections | E80: # of Injections | F80: Units Needed | J80: COST | K80: Reg Price
A81: Week 21 | B81: Weekly | C81: 4000 | D81: 60 | E81: =IF(B81="Daily",7, IF(B81="Weekly",1, IF(B81="Every Other Day",4,""))) -> 1 | F81: =+D81*E81 -> 60 | H81: =ROUNDUP(F85,0) -> 240 | I81: Units | J81: =F85*B6 -> 114.64 | K81: =+F85*E7 -> 194.64
A82: Week 22 | B82: Weekly | C82: 4000 | D82: 60 | E82: =IF(B82="Daily",7, IF(B82="Weekly",1, IF(B82="Every Other Day",4,""))) -> 1 | F82: =+D82*E82 -> 60 | H82: =E85 -> 4 | I82: Syringe | J82: =+H82*0.24 -> 0.96
A83: Week 23 | B83: Weekly | C83: 4000 | D83: 60 | E83: =IF(B83="Daily",7, IF(B83="Weekly",1, IF(B83="Every Other Day",4,""))) -> 1 | F83: =+D83*E83 -> 60 | H83: =E85 -> 4 | I83: Alochol Prep | J83: =H83*0.05 -> 0.2
A84: Week 24 | B84: Weekly | C84: 4000 | D84: 60 | E84: =IF(B84="Daily",7, IF(B84="Weekly",1, IF(B84="Every Other Day",4,""))) -> 1 | F84: =+D84*E84 -> 60 | H84: 0 | I84: Case | J84: =H84*3.65 -> 0
E85: =SUM(E81:E84) -> 4 | F85: =SUM(F81:F84) -> 240 | J85: =SUM(J81:J84) -> 115.8 | K85: 350 | M85: Profit | N85: =+K85-J85 -> 234.2
E86: Number of vials = | F86: =+F85/300 -> 0.8 | I86: Per Unit | J86: =+J85/H81 -> 0.4825 | K86: =+K85/H81 -> 1.4583333
A90: Month 7 | B90: Frequency of Injection | C90: mcg | D90: Units per Injections | E90: # of Injections | F90: Units Needed | J90: COST | K90: Reg Price
A91: Week 25 | B91: Weekly | C91: 4600 | D91: 70 | E91: =IF(B91="Daily",7, IF(B91="Weekly",1, IF(B91="Every Other Day",4,""))) -> 1 | F91: =+D91*E91 -> 70 | H91: =ROUNDUP(F95,0) -> 280 | I91: Units | J91: =F95*B6 -> 133.74667 | K91: =+F95*E7 -> 227.08
A92: Week 26 | B92: Weekly | C92: 4600 | D92: 70 | E92: =IF(B92="Daily",7, IF(B92="Weekly",1, IF(B92="Every Other Day",4,""))) -> 1 | F92: =+D92*E92 -> 70 | H92: =E95 -> 4 | I92: Syringe | J92: =+H92*0.24 -> 0.96
A93: Week 27 | B93: Weekly | C93: 4600 | D93: 70 | E93: =IF(B93="Daily",7, IF(B93="Weekly",1, IF(B93="Every Other Day",4,""))) -> 1 | F93: =+D93*E93 -> 70 | H93: =E95 -> 4 | I93: Alochol Prep | J93: =H93*0.05 -> 0.2
A94: Week 28 | B94: Weekly | C94: 4600 | D94: 70 | E94: =IF(B94="Daily",7, IF(B94="Weekly",1, IF(B94="Every Other Day",4,""))) -> 1 | F94: =+D94*E94 -> 70 | H94: 0 | I94: Case | J94: =H94*3.65 -> 0
E95: =SUM(E91:E94) -> 4 | F95: =SUM(F91:F94) -> 280 | J95: =SUM(J91:J94) -> 134.90667 | K95: 350 | M95: Profit | N95: =+K95-J95 -> 215.09333
E96: Number of vials = | F96: =+F95/300 -> 0.93333333 | I96: Per Unit | J96: =+J95/H91 -> 0.48180952 | K96: =+K95/H91 -> 1.25
A100: Month 8 | B100: Frequency of Injection | C100: mcg | D100: Units per Injections | E100: # of Injections | F100: Units Needed | J100: COST | K100: Reg Price
A101: Week 29 | B101: Weekly | C101: 5250 | D101: 80 | E101: =IF(B101="Daily",7, IF(B101="Weekly",1, IF(B101="Every Other Day",4,""))) -> 1 | F101: =+D101*E101 -> 80 | H101: =ROUNDUP(F105,0) -> 320 | I101: Units | J101: =F105*B6 -> 152.85333 | K101: =+F105*E7 -> 259.52
A102: Week 30 | B102: Weekly | C102: 5250 | D102: 80 | E102: =IF(B102="Daily",7, IF(B102="Weekly",1, IF(B102="Every Other Day",4,""))) -> 1 | F102: =+D102*E102 -> 80 | H102: =E105 -> 4 | I102: Syringe | J102: =+H102*0.24 -> 0.96
A103: Week 31 | B103: Weekly | C103: 5250 | D103: 80 | E103: =IF(B103="Daily",7, IF(B103="Weekly",1, IF(B103="Every Other Day",4,""))) -> 1 | F103: =+D103*E103 -> 80 | H103: =E105 -> 4 | I103: Alochol Prep | J103: =H103*0.05 -> 0.2
A104: Week 32 | B104: Weekly | C104: 5250 | D104: 80 | E104: =IF(B104="Daily",7, IF(B104="Weekly",1, IF(B104="Every Other Day",4,""))) -> 1 | F104: =+D104*E104 -> 80 | H104: 0 | I104: Case | J104: =H104*3.65 -> 0
E105: =SUM(E101:E104) -> 4 | F105: =SUM(F101:F104) -> 320 | J105: =SUM(J101:J104) -> 154.01333 | K105: 350 | M105: Profit | N105: =+K105-J105 -> 195.98667
E106: Number of vials = | F106: =+F105/300 -> 1.0666667 | I106: Per Unit | J106: =+J105/H101 -> 0.48129167 | K106: =+K105/H101 -> 1.09375
A110: Month 9 | B110: Frequency of Injection | C110: mcg | D110: Units per Injections | E110: # of Injections | F110: Units Needed | J110: COST | K110: Reg Price
A111: Week 32 | B111: Weekly | C111: 5900 | D111: 90 | E111: =IF(B111="Daily",7, IF(B111="Weekly",1, IF(B111="Every Other Day",4,""))) -> 1 | F111: =+D111*E111 -> 90 | H111: =ROUNDUP(F115,0) -> 360 | I111: Units | J111: =F115*B6 -> 171.96 | K111: =+F115*E7 -> 291.96
A112: Week 33 | B112: Weekly | C112: 5900 | D112: 90 | E112: =IF(B112="Daily",7, IF(B112="Weekly",1, IF(B112="Every Other Day",4,""))) -> 1 | F112: =+D112*E112 -> 90 | H112: =E115 -> 4 | I112: Syringe | J112: =+H112*0.24 -> 0.96
A113: Week 34 | B113: Weekly | C113: 5900 | D113: 90 | E113: =IF(B113="Daily",7, IF(B113="Weekly",1, IF(B113="Every Other Day",4,""))) -> 1 | F113: =+D113*E113 -> 90 | H113: =E115 -> 4 | I113: Alochol Prep | J113: =H113*0.05 -> 0.2
A114: Week 35 | B114: Weekly | C114: 5900 | D114: 90 | E114: =IF(B114="Daily",7, IF(B114="Weekly",1, IF(B114="Every Other Day",4,""))) -> 1 | F114: =+D114*E114 -> 90 | H114: 0 | I114: Case | J114: =H114*3.65 -> 0
E115: =SUM(E111:E114) -> 4 | F115: =SUM(F111:F114) -> 360 | J115: =SUM(J111:J114) -> 173.12 | K115: 350 | M115: Profit | N115: =+K115-J115 -> 176.88
E116: Number of vials = | F116: =+F115/300 -> 1.2 | I116: Per Unit | J116: =+J115/H111 -> 0.48088889 | K116: =+K115/H111 -> 0.97222222
A120: Month 10 | B120: Frequency of Injection | C120: mcg | D120: Units per Injections | E120: # of Injections | F120: Units Needed | J120: COST | K120: Reg Price
A121: Week 36 | B121: Weekly | C121: 6600 | D121: 100 | E121: =IF(B121="Daily",7, IF(B121="Weekly",1, IF(B121="Every Other Day",4,""))) -> 1 | F121: =+D121*E121 -> 100 | H121: =ROUNDUP(F125,0) -> 400 | I121: Units | J121: =F125*B6 -> 191.06667 | K121: =+F125*E7 -> 324.4
A122: Week 37 | B122: Weekly | C122: 6600 | D122: 100 | E122: =IF(B122="Daily",7, IF(B122="Weekly",1, IF(B122="Every Other Day",4,""))) -> 1 | F122: =+D122*E122 -> 100 | H122: =E125 -> 4 | I122: Syringe | J122: =+H122*0.24 -> 0.96
A123: Week 38 | B123: Weekly | C123: 6600 | D123: 100 | E123: =IF(B123="Daily",7, IF(B123="Weekly",1, IF(B123="Every Other Day",4,""))) -> 1 | F123: =+D123*E123 -> 100 | H123: =E125 -> 4 | I123: Alochol Prep | J123: =H123*0.05 -> 0.2 | Q123: =13220.93-794 -> 12426.93
A124: Week 39 | B124: Weekly | C124: 6600 | D124: 100 | E124: =IF(B124="Daily",7, IF(B124="Weekly",1, IF(B124="Every Other Day",4,""))) -> 1 | F124: =+D124*E124 -> 100 | H124: 0 | I124: Case | J124: =H124*3.65 -> 0
E125: =SUM(E121:E124) -> 4 | F125: =SUM(F121:F124) -> 400 | J125: =SUM(J121:J124) -> 192.22667 | K125: 350 | M125: Profit | N125: =+K125-J125 -> 157.77333
E126: Number of vials = | F126: =+F125/300 -> 1.3333333 | I126: Per Unit | J126: =+J125/H121 -> 0.48056667 | K126: =+K125/H121 -> 0.875
A130: Month 11 | B130: Frequency of Injection | C130: mcg | D130: Units per Injections | E130: # of Injections | F130: Units Needed | J130: COST | K130: Reg Price
A131: Week 40 | B131: Weekly | C131: 7300 | D131: 110 | E131: =IF(B131="Daily",7, IF(B131="Weekly",1, IF(B131="Every Other Day",4,""))) -> 1 | F131: =+D131*E131 -> 110 | H131: =ROUNDUP(F135,0) -> 440 | I131: Units | J131: =F135*B6 -> 210.17333 | K131: =+F135*E7 -> 356.84
A132: Week 41 | B132: Weekly | C132: 7300 | D132: 110 | E132: =IF(B132="Daily",7, IF(B132="Weekly",1, IF(B132="Every Other Day",4,""))) -> 1 | F132: =+D132*E132 -> 110 | H132: =E135 -> 4 | I132: Syringe | J132: =+H132*0.24 -> 0.96
A133: Week 42 | B133: Weekly | C133: 7300 | D133: 110 | E133: =IF(B133="Daily",7, IF(B133="Weekly",1, IF(B133="Every Other Day",4,""))) -> 1 | F133: =+D133*E133 -> 110 | H133: =E135 -> 4 | I133: Alochol Prep | J133: =H133*0.05 -> 0.2
A134: Week 43 | B134: Weekly | C134: 7300 | D134: 110 | E134: =IF(B134="Daily",7, IF(B134="Weekly",1, IF(B134="Every Other Day",4,""))) -> 1 | F134: =+D134*E134 -> 110 | H134: 0 | I134: Case | J134: =H134*3.65 -> 0
E135: =SUM(E131:E134) -> 4 | F135: =SUM(F131:F134) -> 440 | J135: =SUM(J131:J134) -> 211.33333 | K135: 350 | M135: Profit | N135: =+K135-J135 -> 138.66667
E136: Number of vials = | F136: =+F135/300 -> 1.4666667 | I136: Per Unit | J136: =+J135/H131 -> 0.48030303 | K136: =+K135/H131 -> 0.79545455
A140: Month 12 | B140: Frequency of Injection | C140: mcg | D140: Units per Injections | E140: # of Injections | F140: Units Needed | J140: COST | K140: Reg Price
A141: Week 44 | B141: Weekly | C141: 8000 | D141: 120 | E141: =IF(B141="Daily",7, IF(B141="Weekly",1, IF(B141="Every Other Day",4,""))) -> 1 | F141: =+D141*E141 -> 120 | H141: =ROUNDUP(F145,0) -> 480 | I141: Units | J141: =F145*B6 -> 229.28 | K141: =+F145*E7 -> 389.28
A142: Week 45 | B142: Weekly | C142: 8000 | D142: 120 | E142: =IF(B142="Daily",7, IF(B142="Weekly",1, IF(B142="Every Other Day",4,""))) -> 1 | F142: =+D142*E142 -> 120 | H142: =E145 -> 4 | I142: Syringe | J142: =+H142*0.24 -> 0.96
A143: Week 46 | B143: Weekly | C143: 8000 | D143: 120 | E143: =IF(B143="Daily",7, IF(B143="Weekly",1, IF(B143="Every Other Day",4,""))) -> 1 | F143: =+D143*E143 -> 120 | H143: =E145 -> 4 | I143: Alochol Prep | J143: =H143*0.05 -> 0.2
A144: Week 47 | B144: Weekly | C144: 8000 | D144: 120 | E144: =IF(B144="Daily",7, IF(B144="Weekly",1, IF(B144="Every Other Day",4,""))) -> 1 | F144: =+D144*E144 -> 120 | H144: 0 | I144: Case | J144: =H144*3.65 -> 0
E145: =SUM(E141:E144) -> 4 | F145: =SUM(F141:F144) -> 480 | J145: =SUM(J141:J144) -> 230.44 | K145: 350 | M145: Profit | N145: =+K145-J145 -> 119.56
E146: Number of vials = | F146: =+F145/300 -> 1.6 | I146: Per Unit | J146: =+J145/H141 -> 0.48008333 | K146: =+K145/H141 -> 0.72916667
A153: Over 10 months
...

Sheet BPC+TB500
A1: BPC157 + TB500 20mg | N1: Daily
B2: ='Pep Costs'!B11 -> 150 | C2: cost | N2: Every Other Day
B3: 3.3 | C3: BAC | N3: Weekly
B4: 15 | C4: (30) Pen Needles, up to 3 Cartridges, (30)Alcohol Prep | F4: ADD per vial | G4: Reg Price | N4: Monthly
B5: =SUM(B2:B4) -> 168.3 | F5: 100 | G5: =+F5+B5 -> 268.3
A7: Per Unit | B7: =+B5/300 -> 0.561 | F7: Per Unit | G7: =+G5/300 -> 0.89433333
A13: CUSTOM PROTOCOL | K13: Reg Price
H14: =ROUNDUP(F20,0) -> 240 | I14: Units | J14: =+B7*F20 -> 134.64 | K14: =+F20*G7 -> 214.64
B15: Frequency of Injection | C15: mcg | D15: Units per Injections | E15: # of Injections | F15: Units Needed | H15: 0 | I15: Pen | J15: =+H15*45 -> 0
A16: Week | B16: Every Other Day | C16: 1000 | D16: 15 | E16: =IF(B16="Daily",7, IF(B16="Weekly",1, IF(B16="Every Other Day",4,""))) -> 4 | F16: =+D16*E16 -> 60 | H16: =IF(E20>=25, E20+2, E20+1) -> 17 | I16: Pen Needles
A17: Week | B17: Every Other Day | C17: 1000 | D17: 15 | E17: =IF(B17="Daily",7, IF(B17="Weekly",1, IF(B17="Every Other Day",4,""))) -> 4 | F17: =+D17*E17 -> 60 | H17: =ROUNDUP(F21,0) -> 1 | I17: Cartridges
A18: Week | B18: Every Other Day | C18: 1000 | D18: 15 | E18: =IF(B18="Daily",7, IF(B18="Weekly",1, IF(B18="Every Other Day",4,""))) -> 4 | F18: =+D18*E18 -> 60 | H18: =H16 -> 17 | I18: Alochol Prep
A19: Week | B19: Every Other Day | C19: 1000 | D19: 15 | E19: =IF(B19="Daily",7, IF(B19="Weekly",1, IF(B19="Every Other Day",4,""))) -> 4 | F19: =+D19*E19 -> 60 | H19: 0 | I19: Case | J19: =H19*3.65 -> 0
E20: =SUM(E16:E19) -> 16 | F20: =SUM(F16:F19) -> 240 | J20: =SUM(J14:J19) -> 134.64 | K20: =ROUNDUP(SUM(K14:K19),0) -> 215 | M20: Profit | N20: =+K20-J20 -> 80.36
E21: Number of Cartridges needed | F21: =+F20/300 -> 0.8 | I21: Per Unit | J21: =+J20/H14 -> 0.561 | K21: =+K20/H14 -> 0.89583333
J30: COST | K30: Reg Price
H31: =ROUNDUP(F37,0) -> 238 | I31: Units | J31: =F37*B7 -> 133.518 | K31: =+F37*G7 -> 212.85133
A32: Month 1 | B32: Frequency of Injection | C32: mcg | D32: Units per Injections | E32: # of Injections | F32: Units Needed | H32: 1 | I32: Pen | J32: =+H32*45 -> 45 | K32: =H32*85 -> 85
A33: Week 1 | B33: Daily | C33: 500 | D33: 7 | E33: =IF(B33="Daily",7, IF(B33="Weekly",1, IF(B33="Every Other Day",4,""))) -> 7 | F33: =+D33*E33 -> 49 | H33: =IF(E37>=25, E37+2, E37+1) -> 30 | I33: Pen Needles
A34: Week 2 | B34: Daily | C34: 500 | D34: 7 | E34: =IF(B34="Daily",7, IF(B34="Weekly",1, IF(B34="Every Other Day",4,""))) -> 7 | F34: =+D34*E34 -> 49 | H34: =ROUNDUP(F38,0) -> 1 | I34: Cartridges
A35: Week 3 | B35: Daily | C35: 666 | D35: 10 | E35: =IF(B35="Daily",7, IF(B35="Weekly",1, IF(B35="Every Other Day",4,""))) -> 7 | F35: =+D35*E35 -> 70 | H35: =H33 -> 30 | I35: Alochol Prep
A36: Week 4 | B36: Daily | C36: 666 | D36: 10 | E36: =IF(B36="Daily",7, IF(B36="Weekly",1, IF(B36="Every Other Day",4,""))) -> 7 | F36: =+D36*E36 -> 70 | H36: 1 | I36: Case | J36: =H36*3.65 -> 3.65
E37: =SUM(E33:E36) -> 28 | F37: =SUM(F33:F36) -> 238 | J37: =SUM(J31:J36) -> 182.168 | K37: =ROUNDUP(SUM(K31:K36),0) -> 298 | M37: Profit | N37: =+K37-J37 -> 115.832
E38: Number of Cartridges needed | F38: =+F37/300 -> 0.79333333 | I38: Per Unit | J38: =+J37/H31 -> 0.76541176 | K38: =+K37/H31 -> 1.2521008
J43: COST | K43: Reg Price
H44: =ROUNDUP(F50,0) -> 420 | I44: Units | J44: =+B7*F50 -> 235.62 | K44: =+F50*G7 -> 375.62
A45: Month 2 | B45: Frequency of Injection | C45: mcg | D45: Units per Injections | E45: # of Injections | F45: Units Needed | H45: 0 | I45: Pen | J45: =+H45*45 -> 0 | K45: =+H45*85 -> 0
A46: Week 5 | B46: Daily | C46: 1000 | D46: 15 | E46: =IF(B46="Daily",7, IF(B46="Weekly",1, IF(B46="Every Other Day",4,""))) -> 7 | F46: =+D46*E46 -> 105 | H46: =IF(E50>=25, E50+2, E50+1) -> 30 | I46: Pen Needles
A47: Week 6 | B47: Daily | C47: 1000 | D47: 15 | E47: =IF(B47="Daily",7, IF(B47="Weekly",1, IF(B47="Every Other Day",4,""))) -> 7 | F47: =+D47*E47 -> 105 | H47: =ROUNDUP(F51,0) -> 2 | I47: Cartridges
A48: Week 7 | B48: Daily | C48: 1000 | D48: 15 | E48: =IF(B48="Daily",7, IF(B48="Weekly",1, IF(B48="Every Other Day",4,""))) -> 7 | F48: =+D48*E48 -> 105 | H48: =H46 -> 30 | I48: Alochol Prep
A49: Week 8 | B49: Daily | C49: 1000 | D49: 15 | E49: =IF(B49="Daily",7, IF(B49="Weekly",1, IF(B49="Every Other Day",4,""))) -> 7 | F49: =+D49*E49 -> 105 | H49: 0 | I49: Case | J49: =H49*3.65 -> 0
E50: =SUM(E46:E49) -> 28 | F50: =SUM(F46:F49) -> 420 | J50: =SUM(J44:J49) -> 235.62 | K50: =ROUNDUP(SUM(K44:K49),0) -> 376 | M50: Profit | N50: =+K50-J50 -> 140.38
E51: Number of Cartridges needed | F51: =+F50/300 -> 1.4 | I51: Per Unit | J51: =+J50/H44 -> 0.561 | K51: =+K50/H44 -> 0.8952381
J55: COST | K55: Reg Price
H56: =ROUNDUP(F62,0) -> 420 | I56: Units | J56: =+B7*F62 -> 235.62 | K56: =+F62*G7 -> 375.62
A57: Month 3 | B57: Frequency of Injection | C57: mcg | D57: Units per Injections | E57: # of Injections | F57: Units Needed | H57: 0 | I57: Pen | J57: =+H57*45 -> 0 | K57: =+H57*85 -> 0
A58: Week 9 | B58: Daily | C58: 1000 | D58: 15 | E58: =IF(B58="Daily",7, IF(B58="Weekly",1, IF(B58="Every Other Day",4,""))) -> 7 | F58: =+D58*E58 -> 105 | H58: =IF(E62>=25, E62+2, E62+1) -> 30 | I58: Pen Needles
A59: Week 10 | B59: Daily | C59: 1000 | D59: 15 | E59: =IF(B59="Daily",7, IF(B59="Weekly",1, IF(B59="Every Other Day",4,""))) -> 7 | F59: =+D59*E59 -> 105 | H59: =ROUNDUP(F63,0) -> 2 | I59: Cartridges
A60: Week 11 | B60: Daily | C60: 1000 | D60: 15 | E60: =IF(B60="Daily",7, IF(B60="Weekly",1, IF(B60="Every Other Day",4,""))) -> 7 | F60: =+D60*E60 -> 105 | H60: =H58 -> 30 | I60: Alochol Prep
A61: Week 12 | B61: Daily | C61: 1000 | D61: 15 | E61: =IF(B61="Daily",7, IF(B61="Weekly",1, IF(B61="Every Other Day",4,""))) -> 7 | F61: =+D61*E61 -> 105 | H61: 0 | I61: Case | J61: =H61*3.65 -> 0
E62: =SUM(E58:E61) -> 28 | F62: =SUM(F58:F61) -> 420 | J62: =SUM(J56:J61) -> 235.62 | K62: =ROUNDUP(SUM(K56:K61),0) -> 376 | M62: Profit | N62: =+K62-J62 -> 140.38
E63: Number of Cartridges needed | F63: =+F62/300 -> 1.4 | I63: Per Unit | J63: =+J62/H56 -> 0.561 | K63: =+K62/H56 -> 0.8952381
A67: Month 4
A68: Week 13-16 | B68: The patient needs to have a conversation with Unruh as they will most likely take this month OFF.
B69: When the patient returns they may continue to match Week 9-12 or go on a custome protocol
A76: Over 10 months
D77: Sell the bottle?
A78: If we sell exactly what the need: | D78: how many vials do you need for 10 months?
A79: based on Week 9-12 | E79: Units per month | F79: =F62 -> 420
A80: Monthly Profit | B80: =N62 -> 140.38 | E80: Months | F80: 10
F81: =+F80*F79 -> 4200 | G81: Unts needed
E82: Number of vials (div by 300) | F82: =+F81/300 -> 14
E83: $100 per vial | F83: =+F82*100 -> 1400
E85: Average montly profit | F85: =+F83/10 -> 140
A93: What is the largest disocunt/Sale we can offer on Peptides? | G93: What is the largest disocunt/Sale we can offer on Peptides?
A94: Based on highest dosage: | G94: Based on FIRSTS MONTH
B96: Pt Price | C96: Cost | D96: Profit | H96: Pt Price | I96: Cost | J96: Profit
A97: 0 | B97: =K62 -> 376 | C97: =J62 -> 235.62 | D97: =+B97-C97 -> 140.38 | G97: 0 | H97: =K37 -> 298 | I97: =J37 -> 182.168 | J97: =+H97-I97 -> 115.832
A98: 0.1 | B98: =0.9*B97 -> 338.4 | C98: =C97 -> 235.62 | D98: =+B98-C98 -> 102.78 | G98: 0.1 | H98: =0.9*H97 -> 268.2 | I98: =I97 -> 182.168 | J98: =+H98-I98 -> 86.032
A99: 0.15 | B99: =+B97*0.85 -> 319.6 | C99: =C98 -> 235.62 | D99: =+B99-C99 -> 83.98 | G99: 0.15 | H99: =+H97*0.85 -> 253.3 | I99: =I98 -> 182.168 | J99: =+H99-I99 -> 71.132
A100: 0.2 | B100: =0.8*B97 -> 300.8 | C100: =C99 -> 235.62 | D100: =+B100-C100 -> 65.18 | G100: 0.2 | H100: =0.8*H97 -> 238.4 | I100: =I99 -> 182.168 | J100: =+H100-I100 -> 56.232
A101: 0.25 | B101: =0.75*B97 -> 282 | C101: =C100 -> 235.62 | D101: =+B101-C101 -> 46.38 | G101: 0.25 | H101: =0.755*H97 -> 224.99 | I101: =I100 -> 182.168 | J101: =+H101-I101 -> 42.822

Sheet Wolv Slow Tit
A1: BPC157 + TB500 20mg (Slow Titration) | N1: Daily
B2: ='Pep Costs'!B11 -> 150 | C2: cost | F2: Add per vial | G2: Reg Price | N2: Every Other Day
B3: 3.3 | C3: BAC | F3: 100 | G3: =+F3+B5 -> 268.3 | N3: Weekly
B4: 15 | C4: (30) Pen Needles, Cartridges, Alcohol Prep
B5: =SUM(B2:B4) -> 168.3
F6: Per Unit | G6: =+G3/300 -> 0.89433333
A7: Per Unit | B7: =+B5/300 -> 0.561
K11: Reg Price
H12: =ROUNDUP(F18,0) -> 136 | I12: Units | J12: =F18*B7 -> 76.296 | K12: =+F18*G6 -> 121.62933
A13: Month 1 | B13: Frequency of Injection | C13: mcg | D13: Units per Injections | E13: # of Injections | F13: Units Needed | H13: 0 | I13: Pen | J13: =+H13*45 -> 0 | K13: =H13*85 -> 0
A14: Week 1 | B14: Every Other Day | C14: 500 | D14: 7 | E14: =IF(B14="Daily",7, IF(B14="Weekly",1, IF(B14="Every Other Day",4,""))) -> 4 | F14: =+D14*E14 -> 28 | H14: =IF(E18>=25, E18+2, E18+1) -> 17 | I14: Pen Needles
A15: Week 2 | B15: Every Other Day | C15: 500 | D15: 7 | E15: =IF(B15="Daily",7, IF(B15="Weekly",1, IF(B15="Every Other Day",4,""))) -> 4 | F15: =+D15*E15 -> 28 | H15: =ROUNDUP(F19,0) -> 1 | I15: Cartridges
A16: Week 3 | B16: Every Other Day | C16: 666 | D16: 10 | E16: =IF(B16="Daily",7, IF(B16="Weekly",1, IF(B16="Every Other Day",4,""))) -> 4 | F16: =+D16*E16 -> 40 | H16: =H14 -> 17 | I16: Alochol Prep
A17: Week 4 | B17: Every Other Day | C17: 666 | D17: 10 | E17: =IF(B17="Daily",7, IF(B17="Weekly",1, IF(B17="Every Other Day",4,""))) -> 4 | F17: =+D17*E17 -> 40 | H17: 1 | I17: Case | J17: =H17*3.65 -> 3.65
E18: =SUM(E14:E17) -> 16 | F18: =SUM(F14:F17) -> 136 | J18: =SUM(J12:J17) -> 79.946 | K18: =ROUNDUP(SUM(K12:K17),0) -> 122 | M18: Profit | N18: =+K18-J18 -> 42.054
E19: Number of Cartridges needed | F19: =+F18/300 -> 0.45333333 | I19: Per Unit | J19: =+J18/H12 -> 0.58783824 | K19: =+K18/H12 -> 0.89705882
K23: Reg Price
H24: =ROUNDUP(F30,0) -> 240 | I24: Units | J24: =+B7*F30 -> 134.64 | K24: =+F30*G6 -> 214.64
A25: Month 2 | B25: Frequency of Injection | C25: mcg | D25: Units per Injections | E25: # of Injections | F25: Units Needed | H25: 0 | I25: Pen | J25: =+H25*45 -> 0 | K25: =+H25*85 -> 0
A26: Week 5 | B26: Every Other Day | C26: 1000 | D26: 15 | E26: =IF(B26="Daily",7, IF(B26="Weekly",1, IF(B26="Every Other Day",4,""))) -> 4 | F26: =+D26*E26 -> 60 | H26: =IF(E30>=25, E30+2, E30+1) -> 17 | I26: Pen Needles
A27: Week 6 | B27: Every Other Day | C27: 1000 | D27: 15 | E27: =IF(B27="Daily",7, IF(B27="Weekly",1, IF(B27="Every Other Day",4,""))) -> 4 | F27: =+D27*E27 -> 60 | H27: =ROUNDUP(F31,0) -> 1 | I27: Cartridges
A28: Week 7 | B28: Every Other Day | C28: 1000 | D28: 15 | E28: =IF(B28="Daily",7, IF(B28="Weekly",1, IF(B28="Every Other Day",4,""))) -> 4 | F28: =+D28*E28 -> 60 | H28: =H26 -> 17 | I28: Alochol Prep
A29: Week 8 | B29: Every Other Day | C29: 1000 | D29: 15 | E29: =IF(B29="Daily",7, IF(B29="Weekly",1, IF(B29="Every Other Day",4,""))) -> 4 | F29: =+D29*E29 -> 60 | H29: 0 | I29: Case | J29: =H29*3.65 -> 0
E30: =SUM(E26:E29) -> 16 | F30: =SUM(F26:F29) -> 240 | J30: =SUM(J24:J29) -> 134.64 | K30: =ROUNDUP(SUM(K24:K29),0) -> 215 | M30: Profit | N30: =+K30-J30 -> 80.36
E31: Number of Cartridges needed | F31: =+F30/300 -> 0.8 | I31: Per Unit | J31: =+J30/H24 -> 0.561 | K31: =+K30/H24 -> 0.89583333
K35: Reg Price
H36: =ROUNDUP(F42,0) -> 240 | I36: Units | J36: =+B7*F42 -> 134.64 | K36: =+F42*G6 -> 214.64
A37: Month 3 | B37: Frequency of Injection | C37: mcg | D37: Units per Injections | E37: # of Injections | F37: Units Needed | H37: 0 | I37: Pen | J37: =+H37*45 -> 0 | K37: =+H37*85 -> 0
A38: Week 9 | B38: Every Other Day | C38: 1000 | D38: 15 | E38: =IF(B38="Daily",7, IF(B38="Weekly",1, IF(B38="Every Other Day",4,""))) -> 4 | F38: =+D38*E38 -> 60 | H38: =IF(E42>=25, E42+2, E42+1) -> 17 | I38: Pen Needles
A39: Week 10 | B39: Every Other Day | C39: 1000 | D39: 15 | E39: =IF(B39="Daily",7, IF(B39="Weekly",1, IF(B39="Every Other Day",4,""))) -> 4 | F39: =+D39*E39 -> 60 | H39: =ROUNDUP(F43,0) -> 1 | I39: Cartridges
A40: Week 11 | B40: Every Other Day | C40: 1000 | D40: 15 | E40: =IF(B40="Daily",7, IF(B40="Weekly",1, IF(B40="Every Other Day",4,""))) -> 4 | F40: =+D40*E40 -> 60 | H40: =H38 -> 17 | I40: Alochol Prep
A41: Week 12 | B41: Every Other Day | C41: 1000 | D41: 15 | E41: =IF(B41="Daily",7, IF(B41="Weekly",1, IF(B41="Every Other Day",4,""))) -> 4 | F41: =+D41*E41 -> 60 | H41: 0 | I41: Case | J41: =H41*3.65 -> 0
E42: =SUM(E38:E41) -> 16 | F42: =SUM(F38:F41) -> 240 | J42: =SUM(J36:J41) -> 134.64 | K42: =ROUNDUP(SUM(K36:K41),0) -> 215 | M42: Profit | N42: =+K42-J42 -> 80.36
E43: Number of Cartridges needed | F43: =+F42/300 -> 0.8 | I43: Per Unit | J43: =+J42/H36 -> 0.561 | K43: =+K42/H36 -> 0.89583333
A47: Month 4
A48: Week 13-16 | B48: The patient needs to have a conversation with Unruh as they will most likely take this month OFF.
B49: When the patient returns they may continue to match Week 9-12 or go on a custome protocol
A56: Over 10 months
D57: Sell the bottle?
A58: If we sell exactly what the need: | D58: how many vials do you need for 10 months?
A59: based on Week 9-12 | E59: Units per month | F59: =F42 -> 240
A60: Monthly Profit | B60: =N42 -> 80.36 | E60: Months | F60: 10
F61: =+F60*F59 -> 2400 | G61: Unts needed
E62: Number of vials (div by 300) | F62: =+F61/300 -> 8
E63: $100 per vial | F63: =+F62*100 -> 800
E65: Average montly profit | F65: =+F63/10 -> 80
A73: What is the largest disocunt/Sale we can offer on Peptides? | G73: What is the largest disocunt/Sale we can offer on Peptides?
A74: Based on highest dosage: | G74: Based on FIRSTS MONTH
B76: Pt Price | C76: Cost | D76: Profit | H76: Pt Price | I76: Cost | J76: Profit
A77: 0 | B77: =K42 -> 215 | C77: =J42 -> 134.64 | D77: =+B77-C77 -> 80.36 | G77: 0 | H77: =K18 -> 122 | I77: =J18 -> 79.946 | J77: =+H77-I77 -> 42.054
A78: 0.1 | B78: =0.9*B77 -> 193.5 | C78: =C77 -> 134.64 | D78: =+B78-C78 -> 58.86 | G78: 0.1 | H78: =0.9*H77 -> 109.8 | I78: =I77 -> 79.946 | J78: =+H78-I78 -> 29.854
A79: 0.15 | B79: =+B77*0.85 -> 182.75 | C79: =C78 -> 134.64 | D79: =+B79-C79 -> 48.11 | G79: 0.15 | H79: =+H77*0.85 -> 103.7 | I79: =I78 -> 79.946 | J79: =+H79-I79 -> 23.754
A80: 0.2 | B80: =0.8*B77 -> 172 | C80: =C79 -> 134.64 | D80: =+B80-C80 -> 37.36 | G80: 0.2 | H80: =0.8*H77 -> 97.6 | I80: =I79 -> 79.946 | J80: =+H80-I80 -> 17.654
A81: 0.25 | B81: =0.75*B77 -> 161.25 | C81: =C80 -> 134.64 | D81: =+B81-C81 -> 26.61 | G81: 0.25 | H81: =0.755*H77 -> 92.11 | I81: =I80 -> 79.946 | J81: =+H81-I81 -> 12.164

Sheet Wolv Maintenance
A1: BPC157 + TB500 20mg (Maintenance) | N1: Daily
B2: ='Pep Costs'!B11 -> 150 | C2: cost | N2: Every Other Day
B3: 3.3 | C3: BAC | N3: Weekly
B4: 15 | C4: (30) Pen Needles, Cartridges, Alcohol Prep | F4: Add per vial | G4: Reg Price
B5: =SUM(B2:B4) -> 168.3 | F5: 100 | G5: =SUM(B5:F5) -> 268.3
A7: Per Unit | B7: =+B5/300 -> 0.561 | F7: Per Unit | G7: =+G5/300 -> 0.89433333
K11: Reg Price
H12: =ROUNDUP(F18,0) -> 128 | I12: Units | J12: =F18*B7 -> 71.808 | K12: =+F18*G7 -> 114.47467
A13: Month 1 | B13: Frequency of Injection | C13: mcg | D13: Units per Injections | E13: # of Injections | F13: Units Needed | H13: 0 | I13: Pen | J13: =+H13*45 -> 0 | K13: =+H13*85 -> 0
A14: Week 1 | B14: Every Other Day | C14: 500 | D14: 8 | E14: =IF(B14="Daily",7, IF(B14="Weekly",1, IF(B14="Every Other Day",4,""))) -> 4 | F14: =+D14*E14 -> 32 | H14: =IF(E18>=25, E18+2, E18+1) -> 17 | I14: Pen Needles
A15: Week 2 | B15: Every Other Day | C15: 500 | D15: 8 | E15: =IF(B15="Daily",7, IF(B15="Weekly",1, IF(B15="Every Other Day",4,""))) -> 4 | F15: =+D15*E15 -> 32 | H15: =ROUNDUP(F19,0) -> 1 | I15: Cartridges
A16: Week 3 | B16: Every Other Day | C16: 500 | D16: 8 | E16: =IF(B16="Daily",7, IF(B16="Weekly",1, IF(B16="Every Other Day",4,""))) -> 4 | F16: =+D16*E16 -> 32 | H16: =H14 -> 17 | I16: Alochol Prep
A17: Week 4 | B17: Every Other Day | C17: 500 | D17: 8 | E17: =IF(B17="Daily",7, IF(B17="Weekly",1, IF(B17="Every Other Day",4,""))) -> 4 | F17: =+D17*E17 -> 32 | H17: 1 | I17: Case | J17: =H17*3.65 -> 3.65
E18: =SUM(E14:E17) -> 16 | F18: =SUM(F14:F17) -> 128 | J18: =SUM(J12:J17) -> 75.458 | K18: 150 | M18: Profit | N18: =+K18-J18 -> 74.542
E19: Number of Cartridges needed | F19: =+F18/300 -> 0.42666667 | I19: Per Unit | J19: =+J18/H12 -> 0.58951563 | K19: =+K18/H12 -> 1.171875
A26: Over 10 months
D27: Sell the bottle?
A28: If we sell exactly what the need: | D28: how many vials do you need for 10 months?
A29: based on Week 1-4 | E29: Units per month | F29: =F18 -> 128
A30: Monthly Profit | B30: =N18 -> 74.542 | E30: Months | F30: 10
F31: =+F30*F29 -> 1280 | G31: Unts needed
E32: Number of vials (div by 300) | F32: =ROUNDUP((F31/300),0) -> 5
E33: $100 per vial | F33: =+F32*100 -> 500
E35: Average montly profit | F35: =+F33/10 -> 50
A44: What is the largest disocunt/Sale we can offer on Peptides? | G44: What is the largest disocunt/Sale we can offer on Peptides?
A45: Based on highest dosage: | G45: Based on FIRSTS MONTH
B47: Pt Price | C47: Cost | D47: Profit | H47: Pt Price | I47: Cost | J47: Profit
A48: 0 | B48: =K18 -> 150 | C48: =J18 -> 75.458 | D48: =+B48-C48 -> 74.542 | G48: 0 | H48: =K18 -> 150 | I48: =J18 -> 75.458 | J48: =+H48-I48 -> 74.542
A49: 0.1 | B49: =0.9*B48 -> 135 | C49: =C48 -> 75.458 | D49: =+B49-C49 -> 59.542 | G49: 0.1 | H49: =0.9*H48 -> 135 | I49: =I48 -> 75.458 | J49: =+H49-I49 -> 59.542
A50: 0.15 | B50: =+B48*0.85 -> 127.5 | C50: =C49 -> 75.458 | D50: =+B50-C50 -> 52.042 | G50: 0.15 | H50: =+H48*0.85 -> 127.5 | I50: =I49 -> 75.458 | J50: =+H50-I50 -> 52.042
A51: 0.2 | B51: =0.8*B48 -> 120 | C51: =C50 -> 75.458 | D51: =+B51-C51 -> 44.542 | G51: 0.2 | H51: =0.8*H48 -> 120 | I51: =I50 -> 75.458 | J51: =+H51-I51 -> 44.542
A52: 0.25 | B52: =0.75*B48 -> 112.5 | C52: =C51 -> 75.458 | D52: =+B52-C52 -> 37.042 | G52: 0.25 | H52: =0.755*H48 -> 113.25 | I52: =I51 -> 75.458 | J52: =+H52-I52 -> 37.792

Sheet ARA290
A1: ARA-290 10mg | O1: Daily
B2: 59.26 | C2: cost | O2: Every Other Day
B3: 3.3 | C3: BAC | O3: Weekly
B4: 15 | C4: (30) Pen Needles, Cartridges, Alcohol Prep | F4: Add per vial | G4: Reg Price
B5: =SUM(B2:B4) -> 77.56 | F5: 35 | G5: =+F5+B5 -> 112.56
A7: Per Unit | B7: =+B5/300 -> 0.25853333 | F7: Per Unit | G7: =+G5/300 -> 0.3752
A13: CUSTOM PROTOCOL | K13: Reg Price
H14: =ROUNDUP(F20,0) -> 285 | I14: Units | J14: =+B7*F20 -> 73.682 | K14: =+F20*G7 -> 106.932
B15: Frequency of Injection | C15: mcg | D15: Units per Injections | E15: # of Injections | F15: Units Needed | H15: 1 | I15: Pen | J15: =+H15*45 -> 45 | K15: =+H15*85 -> 85
A16: Week | B16: Daily | C16: 500 | D16: 15 | E16: =IF(B16="Daily",7, IF(B16="Weekly",1, IF(B16="Every Other Day",4,""))) -> 7 | F16: =+D16*E16 -> 105 | H16: =IF(E20>=25, E20+2, E20+1) -> 20 | I16: Pen Needles
A17: Week | B17: Every Other Day | C17: 500 | D17: 15 | E17: =IF(B17="Daily",7, IF(B17="Weekly",1, IF(B17="Every Other Day",4,""))) -> 4 | F17: =+D17*E17 -> 60 | H17: =ROUNDUP(F21,0) -> 1 | I17: Cartridges
A18: Week | B18: Daily | C18: 500 | D18: 15 | E18: =IF(B18="Daily",7, IF(B18="Weekly",1, IF(B18="Every Other Day",4,""))) -> 7 | F18: =+D18*E18 -> 105 | H18: =H16 -> 20 | I18: Alochol Prep
A19: Week | B19: Weekly | C19: 500 | D19: 15 | E19: =IF(B19="Daily",7, IF(B19="Weekly",1, IF(B19="Every Other Day",4,""))) -> 1 | F19: =+D19*E19 -> 15 | H19: 0 | I19: Case | J19: =H19*3.65 -> 0
E20: =SUM(E16:E19) -> 19 | F20: =SUM(F16:F19) -> 285 | J20: =SUM(J14:J19) -> 118.682 | K20: =ROUNDUP(SUM(K14:K19),0) -> 192 | M20: Profit | N20: =+K20-J20 -> 73.318
E21: Number of Cartridges needed | F21: =+F20/300 -> 0.95 | I21: Per Unit | J21: =+J20/H14 -> 0.41642807 | K21: =+K20/H14 -> 0.67368421
K26: Reg Price
H27: =ROUNDUP(F33,0) -> 1838 | I27: Units | J27: =F33*B7 -> 475.055 | K27: =+F33*G7 -> 689.43
A28: Month 1 | B28: Frequency of Injection | C28: mcg | D28: Units per Injections | E28: # of Injections | F28: Units Needed | H28: 0 | I28: Pen | J28: =+H28*45 -> 0 | K28: =H28*85 -> 0
A29: Week 1 | B29: Daily | C29: 2000 | D29: 37.5 | E29: =IF(B29="Daily",7, IF(B29="Weekly",1, IF(B29="Every Other Day",4,""))) -> 7 | F29: =+D29*E29 -> 262.5 | H29: =IF(E33>=25, E33+2, E33+1) -> 30 | I29: Pen Needles
A30: Week 2 | B30: Daily | C30: 4000 | D30: 75 | E30: =IF(B30="Daily",7, IF(B30="Weekly",1, IF(B30="Every Other Day",4,""))) -> 7 | F30: =+D30*E30 -> 525 | H30: =ROUNDUP(F34,0) -> 7 | I30: Cartridges | J30: =(H30-2)*0.6 -> 3 | K30: =(H30-2) -> 5
A31: Week 3 | B31: Daily | C31: 4000 | D31: 75 | E31: =IF(B31="Daily",7, IF(B31="Weekly",1, IF(B31="Every Other Day",4,""))) -> 7 | F31: =+D31*E31 -> 525 | H31: =H29 -> 30 | I31: Alochol Prep
A32: Week 4 | B32: Daily | C32: 4000 | D32: 75 | E32: =IF(B32="Daily",7, IF(B32="Weekly",1, IF(B32="Every Other Day",4,""))) -> 7 | F32: =+D32*E32 -> 525 | H32: 1 | I32: Case | J32: =H32*3.65 -> 3.65
E33: =SUM(E29:E32) -> 28 | F33: =SUM(F29:F32) -> 1837.5 | J33: =SUM(J27:J32) -> 481.705 | K33: =ROUNDUP(SUM(K27:K32),0) -> 695 | M33: Profit | N33: =+K33-J33 -> 213.295
E34: Number of Cartridges needed | F34: =+F33/300 -> 6.125 | I34: Per Unit | J34: =+J33/H27 -> 0.26208107 | K34: =+K33/H27 -> 0.3781284
K38: Reg Price
H39: =ROUNDUP(F45,0) -> 2100 | I39: Units | J39: =+B7*F45 -> 542.92 | K39: =+F45*G7 -> 787.92
A40: Month 2 | B40: Frequency of Injection | C40: mcg | D40: Units per Injections | E40: # of Injections | F40: Units Needed | H40: 0 | I40: Pen | J40: =+H40*45 -> 0 | K40: =+H40*85 -> 0
A41: Week 5 | B41: Daily | C41: 4000 | D41: 75 | E41: =IF(B41="Daily",7, IF(B41="Weekly",1, IF(B41="Every Other Day",4,""))) -> 7 | F41: =+D41*E41 -> 525 | H41: =IF(E45>=25, E45+2, E45+1) -> 30 | I41: Pen Needles
A42: Week 6 | B42: Daily | C42: 4000 | D42: 75 | E42: =IF(B42="Daily",7, IF(B42="Weekly",1, IF(B42="Every Other Day",4,""))) -> 7 | F42: =+D42*E42 -> 525 | H42: =ROUNDUP(F46,0) -> 7 | I42: Cartridges | J42: =H42*0.6 -> 4.2 | K42: =+H42 -> 7
A43: Week 7 | B43: Daily | C43: 4000 | D43: 75 | E43: =IF(B43="Daily",7, IF(B43="Weekly",1, IF(B43="Every Other Day",4,""))) -> 7 | F43: =+D43*E43 -> 525 | H43: =H41 -> 30 | I43: Alochol Prep
A44: Week 8 | B44: Daily | C44: 4000 | D44: 75 | E44: =IF(B44="Daily",7, IF(B44="Weekly",1, IF(B44="Every Other Day",4,""))) -> 7 | F44: =+D44*E44 -> 525 | H44: 0 | I44: Case | J44: =H44*3.65 -> 0
E45: =SUM(E41:E44) -> 28 | F45: =SUM(F41:F44) -> 2100 | J45: =SUM(J39:J44) -> 547.12 | K45: =ROUNDUP(SUM(K39:K44),0) -> 795 | M45: Profit | N45: =+K45-J45 -> 247.88
E46: Number of Cartridges needed | F46: =+F45/300 -> 7 | I46: Per Unit | J46: =+J45/H39 -> 0.26053333 | K46: =+K45/H39 -> 0.37857143
K50: Reg Price
H51: =ROUNDUP(F57,0) -> 2100 | I51: Units | J51: =+B7*F57 -> 542.92 | K51: =+F57*G7 -> 787.92
A52: Month 3 | B52: Frequency of Injection | C52: mcg | D52: Units per Injections | E52: # of Injections | F52: Units Needed | H52: 0 | I52: Pen | J52: =+H52*45 -> 0 | K52: =+H52*85 -> 0
A53: Week 9 | B53: Daily | C53: 4000 | D53: 75 | E53: =IF(B53="Daily",7, IF(B53="Weekly",1, IF(B53="Every Other Day",4,""))) -> 7 | F53: =+D53*E53 -> 525 | H53: =IF(E57>=25, E57+2, E57+1) -> 30 | I53: Pen Needles
A54: Week 10 | B54: Daily | C54: 4000 | D54: 75 | E54: =IF(B54="Daily",7, IF(B54="Weekly",1, IF(B54="Every Other Day",4,""))) -> 7 | F54: =+D54*E54 -> 525 | H54: =ROUNDUP(F58,0) -> 7 | I54: Cartridges | J54: =H54*0.6 -> 4.2 | K54: =+H54 -> 7
A55: Week 11 | B55: Daily | C55: 4000 | D55: 75 | E55: =IF(B55="Daily",7, IF(B55="Weekly",1, IF(B55="Every Other Day",4,""))) -> 7 | F55: =+D55*E55 -> 525 | H55: =H53 -> 30 | I55: Alochol Prep
A56: Week 12 | B56: Daily | C56: 4000 | D56: 75 | E56: =IF(B56="Daily",7, IF(B56="Weekly",1, IF(B56="Every Other Day",4,""))) -> 7 | F56: =+D56*E56 -> 525 | H56: 0 | I56: Case | J56: =H56*3.65 -> 0
E57: =SUM(E53:E56) -> 28 | F57: =SUM(F53:F56) -> 2100 | J57: =SUM(J51:J56) -> 547.12 | K57: =ROUNDUP(SUM(K51:K56),0) -> 795 | M57: Profit | N57: =+K57-J57 -> 247.88
E58: Number of Cartridges needed | F58: =+F57/300 -> 7 | I58: Per Unit | J58: =+J57/H51 -> 0.26053333 | K58: =+K57/H51 -> 0.37857143
K62: Reg Price
H63: =ROUNDUP(F69,0) -> 2100 | I63: Units | J63: =+B7*F69 -> 542.92 | K63: =+F69*G7 -> 787.92
A64: Month 4 | B64: Frequency of Injection | C64: mcg | D64: Units per Injections | E64: # of Injections | F64: Units Needed | H64: 0 | I64: Pen | J64: =+H64*45 -> 0 | K64: =+H64*85 -> 0
A65: Week 13 | B65: Daily | C65: 4000 | D65: 75 | E65: =IF(B65="Daily",7, IF(B65="Weekly",1, IF(B65="Every Other Day",4,""))) -> 7 | F65: =+D65*E65 -> 525 | H65: =IF(E69>=25, E69+2, E69+1) -> 30 | I65: Pen Needles
A66: Week 14 | B66: Daily | C66: 4000 | D66: 75 | E66: =IF(B66="Daily",7, IF(B66="Weekly",1, IF(B66="Every Other Day",4,""))) -> 7 | F66: =+D66*E66 -> 525 | H66: =ROUNDUP(F70,0) -> 7 | I66: Cartridges | J66: =H66*0.6 -> 4.2 | K66: =+H66 -> 7
A67: Week 15 | B67: Daily | C67: 4000 | D67: 75 | E67: =IF(B67="Daily",7, IF(B67="Weekly",1, IF(B67="Every Other Day",4,""))) -> 7 | F67: =+D67*E67 -> 525 | H67: =H65 -> 30 | I67: Alochol Prep
A68: Week 16 | B68: Daily | C68: 4000 | D68: 75 | E68: =IF(B68="Daily",7, IF(B68="Weekly",1, IF(B68="Every Other Day",4,""))) -> 7 | F68: =+D68*E68 -> 525 | H68: 0 | I68: Case | J68: =H68*3.65 -> 0
E69: =SUM(E65:E68) -> 28 | F69: =SUM(F65:F68) -> 2100 | J69: =SUM(J63:J68) -> 547.12 | K69: =ROUNDUP(SUM(K63:K68),0) -> 795 | M69: Profit | N69: =+K69-J69 -> 247.88
E70: Number of Cartridges needed | F70: =+F69/300 -> 7 | I70: Per Unit | J70: =+J69/H63 -> 0.26053333 | K70: =+K69/H63 -> 0.37857143
A77: Over 10 months
D78: Sell the bottle?
A79: If we sell exactly what the need: | D79: how many vials do you need for 10 months?
E80: Units per month | F80: =F45 -> 2100
A81: Monthly Profit | B81: =N45 -> 247.88 | E81: Months | F81: 10
F82: =+F81*F80 -> 21000 | G82: Unts needed
E83: Number of vials (div by 300) | F83: =ROUNDUP((F82/300),0) -> 70
E84: $100 per vial | F84: =+F5*F83 -> 2450
E86: Average montly profit | F86: =+F84/10 -> 245
A95: What is the largest disocunt/Sale we can offer on Peptides? | H95: What is the largest disocunt/Sale we can offer on Peptides?
A96: Based on highest dosage: | H96: Based on FIRSTS MONTH
B98: Pt Price | C98: Cost | D98: Profit | I98: Pt Price | J98: Cost | K98: Profit
A99: 0 | B99: =K45 -> 795 | C99: =J45 -> 547.12 | D99: =+B99-C99 -> 247.88 | H99: 0 | I99: =K33 -> 695 | J99: =J33 -> 481.705 | K99: =+I99-J99 -> 213.295
A100: 0.1 | B100: =0.9*B99 -> 715.5 | C100: =C99 -> 547.12 | D100: =+B100-C100 -> 168.38 | H100: 0.1 | I100: =0.9*I99 -> 625.5 | J100: =J99 -> 481.705 | K100: =+I100-J100 -> 143.795
A101: 0.15 | B101: =+B99*0.85 -> 675.75 | C101: =C100 -> 547.12 | D101: =+B101-C101 -> 128.63 | H101: 0.15 | I101: =+I99*0.85 -> 590.75 | J101: =J100 -> 481.705 | K101: =+I101-J101 -> 109.045
A102: 0.2 | B102: =0.8*B99 -> 636 | C102: =C101 -> 547.12 | D102: =+B102-C102 -> 88.88 | H102: 0.2 | I102: =0.8*I99 -> 556 | J102: =J101 -> 481.705 | K102: =+I102-J102 -> 74.295
A103: 0.25 | B103: =0.75*B99 -> 596.25 | C103: =C102 -> 547.12 | D103: =+B103-C103 -> 49.13 | H103: 0.25 | I103: =0.755*I99 -> 524.725 | J103: =J102 -> 481.705 | K103: =+I103-J103 -> 43.02

Sheet BPC157
A1: BPC-157 10mg | O1: Daily
B2: 48 | C2: cost | O2: Every Other Day
B3: 3.3 | C3: BAC | O3: Weekly
B4: 15 | C4: (30) Pen Needles, Cartridges, Alcohol Prep | F4: Add per vial | G4: Reg Price
B5: =SUM(B2:B4) -> 66.3 | F5: 100 | G5: =+F5+B5 -> 166.3
A7: Per Unit | B7: =+B5/300 -> 0.221 | F7: Per Unit | G7: =+G5/300 -> 0.55433333
A13: CUSTOM PROTOCOL | K13: Reg Price
H14: =ROUNDUP(F20,0) -> 285 | I14: Units | J14: =+B7*F20 -> 62.985 | K14: =+F20*G7 -> 157.985
B15: Frequency of Injection | C15: mcg | D15: Units per Injections | E15: # of Injections | F15: Units Needed | H15: 1 | I15: Pen | J15: =+H15*45 -> 45 | K15: =+H15*85 -> 85
A16: Week | B16: Daily | C16: 500 | D16: 15 | E16: =IF(B16="Daily",7, IF(B16="Weekly",1, IF(B16="Every Other Day",4,""))) -> 7 | F16: =+D16*E16 -> 105 | H16: =IF(E20>=25, E20+2, E20+1) -> 20 | I16: Pen Needles
A17: Week | B17: Every Other Day | C17: 500 | D17: 15 | E17: =IF(B17="Daily",7, IF(B17="Weekly",1, IF(B17="Every Other Day",4,""))) -> 4 | F17: =+D17*E17 -> 60 | H17: =ROUNDUP(F21,0) -> 1 | I17: Cartridges
A18: Week | B18: Daily | C18: 500 | D18: 15 | E18: =IF(B18="Daily",7, IF(B18="Weekly",1, IF(B18="Every Other Day",4,""))) -> 7 | F18: =+D18*E18 -> 105 | H18: =H16 -> 20 | I18: Alochol Prep
A19: Week | B19: Weekly | C19: 500 | D19: 15 | E19: =IF(B19="Daily",7, IF(B19="Weekly",1, IF(B19="Every Other Day",4,""))) -> 1 | F19: =+D19*E19 -> 15 | H19: 0 | I19: Case | J19: =H19*3.65 -> 0
E20: =SUM(E16:E19) -> 19 | F20: =SUM(F16:F19) -> 285 | J20: =SUM(J14:J19) -> 107.985 | K20: =ROUNDUP(SUM(K14:K19),0) -> 243 | M20: Profit | N20: =+K20-J20 -> 135.015
E21: Number of Cartridges needed | F21: =+F20/300 -> 0.95 | I21: Per Unit | J21: =+J20/H14 -> 0.37889474 | K21: =+K20/H14 -> 0.85263158
K26: Reg Price
H27: =ROUNDUP(F33,0) -> 252 | I27: Units | J27: =F33*B7 -> 55.692 | K27: =+F33*G7 -> 139.692
A28: Month 1 | B28: Frequency of Injection | C28: mcg | D28: Units per Injections | E28: # of Injections | F28: Units Needed | H28: 1 | I28: Pen | J28: =+H28*45 -> 45 | K28: =H28*85 -> 85
A29: Week 1 | B29: Daily | C29: 200 | D29: 6 | E29: =IF(B29="Daily",7, IF(B29="Weekly",1, IF(B29="Every Other Day",4,""))) -> 7 | F29: =+D29*E29 -> 42 | H29: =IF(E33>=25, E33+2, E33+1) -> 30 | I29: Pen Needles
A30: Week 2 | B30: Daily | C30: 200 | D30: 6 | E30: =IF(B30="Daily",7, IF(B30="Weekly",1, IF(B30="Every Other Day",4,""))) -> 7 | F30: =+D30*E30 -> 42 | H30: =ROUNDUP(F34,0) -> 1 | I30: Cartridges
A31: Week 3 | B31: Daily | C31: 400 | D31: 12 | E31: =IF(B31="Daily",7, IF(B31="Weekly",1, IF(B31="Every Other Day",4,""))) -> 7 | F31: =+D31*E31 -> 84 | H31: =H29 -> 30 | I31: Alochol Prep
A32: Week 4 | B32: Daily | C32: 400 | D32: 12 | E32: =IF(B32="Daily",7, IF(B32="Weekly",1, IF(B32="Every Other Day",4,""))) -> 7 | F32: =+D32*E32 -> 84 | H32: 1 | I32: Case | J32: =H32*3.65 -> 3.65
E33: =SUM(E29:E32) -> 28 | F33: =SUM(F29:F32) -> 252 | J33: =SUM(J27:J32) -> 104.342 | K33: =ROUNDUP(SUM(K27:K32),0) -> 225 | M33: Profit | N33: =+K33-J33 -> 120.658
E34: Number of Cartridges needed | F34: =+F33/300 -> 0.84 | I34: Per Unit | J34: =+J33/H27 -> 0.41405556 | K34: =+K33/H27 -> 0.89285714
K38: Reg Price
H39: =ROUNDUP(F45,0) -> 504 | I39: Units | J39: =+B7*F45 -> 111.384 | K39: =+F45*G7 -> 279.384
A40: Month 2 | B40: Frequency of Injection | C40: mcg | D40: Units per Injections | E40: # of Injections | F40: Units Needed | H40: 0 | I40: Pen | J40: =+H40*45 -> 0 | K40: =+H40*85 -> 0
A41: Week 5 | B41: Daily | C41: 600 | D41: 18 | E41: =IF(B41="Daily",7, IF(B41="Weekly",1, IF(B41="Every Other Day",4,""))) -> 7 | F41: =+D41*E41 -> 126 | H41: =IF(E45>=25, E45+2, E45+1) -> 30 | I41: Pen Needles
A42: Week 6 | B42: Daily | C42: 600 | D42: 18 | E42: =IF(B42="Daily",7, IF(B42="Weekly",1, IF(B42="Every Other Day",4,""))) -> 7 | F42: =+D42*E42 -> 126 | H42: =ROUNDUP(F46,0) -> 2 | I42: Cartridges
A43: Week 7 | B43: Daily | C43: 600 | D43: 18 | E43: =IF(B43="Daily",7, IF(B43="Weekly",1, IF(B43="Every Other Day",4,""))) -> 7 | F43: =+D43*E43 -> 126 | H43: =H41 -> 30 | I43: Alochol Prep
A44: Week 8 | B44: Daily | C44: 600 | D44: 18 | E44: =IF(B44="Daily",7, IF(B44="Weekly",1, IF(B44="Every Other Day",4,""))) -> 7 | F44: =+D44*E44 -> 126 | H44: 0 | I44: Case | J44: =H44*3.65 -> 0
E45: =SUM(E41:E44) -> 28 | F45: =SUM(F41:F44) -> 504 | J45: =SUM(J39:J44) -> 111.384 | K45: =ROUNDUP(SUM(K39:K44),0) -> 280 | M45: Profit | N45: =+K45-J45 -> 168.616
E46: Number of Cartridges needed | F46: =+F45/300 -> 1.68 | I46: Per Unit | J46: =+J45/H39 -> 0.221 | K46: =+K45/H39 -> 0.55555556
K50: Reg Price
H51: =ROUNDUP(F57,0) -> 504 | I51: Units | J51: =+F57*B7 -> 111.384 | K51: =+F57*G7 -> 279.384
A52: Month 3 | B52: Frequency of Injection | C52: mcg | D52: Units per Injections | E52: # of Injections | F52: Units Needed | H52: 0 | I52: Pen | J52: =+H52*45 -> 0 | K52: =+H52*85 -> 0
A53: Week 9 | B53: Daily | C53: 600 | D53: 18 | E53: =IF(B53="Daily",7, IF(B53="Weekly",1, IF(B53="Every Other Day",4,""))) -> 7 | F53: =+D53*E53 -> 126 | H53: =IF(E57>=25, E57+2, E57+1) -> 30 | I53: Pen Needles
A54: Week 10 | B54: Daily | C54: 600 | D54: 18 | E54: =IF(B54="Daily",7, IF(B54="Weekly",1, IF(B54="Every Other Day",4,""))) -> 7 | F54: =+D54*E54 -> 126 | H54: =ROUNDUP(F58,0) -> 2 | I54: Cartridges
A55: Week 11 | B55: Daily | C55: 600 | D55: 18 | E55: =IF(B55="Daily",7, IF(B55="Weekly",1, IF(B55="Every Other Day",4,""))) -> 7 | F55: =+D55*E55 -> 126 | H55: =H53 -> 30 | I55: Alochol Prep
A56: Week 12 | B56: Daily | C56: 600 | D56: 18 | E56: =IF(B56="Daily",7, IF(B56="Weekly",1, IF(B56="Every Other Day",4,""))) -> 7 | F56: =+D56*E56 -> 126 | H56: 0 | I56: Case | J56: =H56*3.65 -> 0
E57: =SUM(E53:E56) -> 28 | F57: =SUM(F53:F56) -> 504 | J57: =SUM(J51:J56) -> 111.384 | K57: =ROUNDUP(SUM(K51:K56),0) -> 280 | M57: Profit | N57: =+K57-J57 -> 168.616
E58: Number of Cartridges needed | F58: =+F57/300 -> 1.68 | I58: Per Unit | J58: =+J57/H51 -> 0.221 | K58: =+K57/H51 -> 0.55555556
A62: Month 4 | B62: The patient needs to have a conversation with Unruh as they will most likely take this month OFF.
A70: Over 10 months
D71: Sell the bottle?
A72: If we sell exactly what the need: | D72: how many vials do you need for 10 months?
E73: Units per month | F73: =F45 -> 504
A74: Monthly Profit | B74: =N45 -> 168.616 | E74: Months | F74: 10
F75: =+F74*F73 -> 5040 | G75: Unts needed
E76: Number of vials (div by 300) | F76: =ROUNDUP((F75/300),0) -> 17
E77: $100 per vial | F77: =+F76*100 -> 1700
E79: Average montly profit | F79: =+F77/10 -> 170
A88: What is the largest disocunt/Sale we can offer on Peptides? | G88: What is the largest disocunt/Sale we can offer on Peptides?
A89: Based on highest dosage: | G89: Based on FIRSTS MONTH
B91: Pt Price | C91: Cost | D91: Profit | H91: Pt Price | I91: Cost | J91: Profit
A92: 0 | B92: =K45 -> 280 | C92: =J45 -> 111.384 | D92: =+B92-C92 -> 168.616 | G92: 0 | H92: =K33 -> 225 | I92: =J33 -> 104.342 | J92: =+H92-I92 -> 120.658
A93: 0.1 | B93: =0.9*B92 -> 252 | C93: =C92 -> 111.384 | D93: =+B93-C93 -> 140.616 | G93: 0.1 | H93: =0.9*H92 -> 202.5 | I93: =I92 -> 104.342 | J93: =+H93-I93 -> 98.158
A94: 0.15 | B94: =+B92*0.85 -> 238 | C94: =C93 -> 111.384 | D94: =+B94-C94 -> 126.616 | G94: 0.15 | H94: =+H92*0.85 -> 191.25 | I94: =I93 -> 104.342 | J94: =+H94-I94 -> 86.908
A95: 0.2 | B95: =0.8*B92 -> 224 | C95: =C94 -> 111.384 | D95: =+B95-C95 -> 112.616 | G95: 0.2 | H95: =0.8*H92 -> 180 | I95: =I94 -> 104.342 | J95: =+H95-I95 -> 75.658
A96: 0.25 | B96: =0.75*B92 -> 210 | C96: =C95 -> 111.384 | D96: =+B96-C96 -> 98.616 | G96: 0.25 | H96: =0.755*H92 -> 169.875 | I96: =I95 -> 104.342 | J96: =+H96-I96 -> 65.533

Sheet DSIP 5mg
A1: DSIP 5mg | N1: Daily
B2: ='Pep Costs'!B16 -> 37 | C2: cost | N2: Every Other Day
B3: 3.3 | C3: BAC | N3: Weekly
B4: 15 | C4: (30) Pen Needles, Cartridges, Alcohol Prep | E4: Add per vial | F4: Reg Price
B5: =SUM(B2:B4) -> 55.3 | E5: 100 | F5: =+E5+B5 -> 155.3
A7: Per Unit | B7: =+B5/300 -> 0.18433333 | E7: Per Unit | F7: =+F5/300 -> 0.51766667
A12: CUSTOM PROTOCOL
K14: Reg Price
H15: =ROUNDUP(F21,0) -> 285 | I15: Units | J15: =+B7*F21 -> 52.535 | K15: =+F21*F7 -> 147.535
B16: Frequency of Injection | C16: mcg | D16: Units per Injections | E16: # of Injections | F16: Units Needed | H16: 0 | I16: Pen | J16: =+H16*45 -> 0 | K16: =+H16*85 -> 0
A17: Week | B17: Daily | C17: 1000 | D17: 15 | E17: =IF(B17="Daily",7, IF(B17="Weekly",1, IF(B17="Every Other Day",4,""))) -> 7 | F17: =+D17*E17 -> 105 | H17: =IF(E21>=25, E21+2, E21+1) -> 20 | I17: Pen Needles
A18: Week | B18: Every Other Day | C18: 1000 | D18: 15 | E18: =IF(B18="Daily",7, IF(B18="Weekly",1, IF(B18="Every Other Day",4,""))) -> 4 | F18: =+D18*E18 -> 60 | H18: =ROUNDUP(F22,0) -> 1 | I18: Cartridges
A19: Week | B19: Weekly | C19: 1000 | D19: 15 | E19: =IF(B19="Daily",7, IF(B19="Weekly",1, IF(B19="Every Other Day",4,""))) -> 1 | F19: =+D19*E19 -> 15 | H19: =H17 -> 20 | I19: Alochol Prep
A20: Week | B20: Daily | C20: 1000 | D20: 15 | E20: =IF(B20="Daily",7, IF(B20="Weekly",1, IF(B20="Every Other Day",4,""))) -> 7 | F20: =+D20*E20 -> 105 | H20: 0 | I20: Case | J20: =H20*3.65 -> 0
E21: =SUM(E17:E20) -> 19 | F21: =SUM(F17:F20) -> 285 | J21: =SUM(J15:J20) -> 52.535 | K21: =ROUNDUP(SUM(K15:K20),0) -> 148 | M21: Profit | N21: =+K21-J21 -> 95.465
E22: Number of Cartridges needed | F22: =+F21/300 -> 0.95 | I22: Per Unit | J22: =+J21/H15 -> 0.18433333 | K22: =+K21/H15 -> 0.51929825
K28: Reg Price
H29: =ROUNDUP(F35,0) -> 294 | I29: Units | J29: =F35*B7 -> 54.194 | K29: =+F35*F7 -> 152.194
A30: Month 1 | B30: Frequency of Injection | C30: mcg | D30: Units per Injections | E30: # of Injections | F30: Units Needed | H30: 0 | I30: Pen | J30: =+H30*45 -> 0 | K30: =H30*85 -> 0
A31: Week 1 | B31: Daily | C31: 100 | D31: 6 | E31: =IF(B31="Daily",7, IF(B31="Weekly",1, IF(B31="Every Other Day",4,""))) -> 7 | F31: =+D31*E31 -> 42 | H31: =IF(E35>=25, E35+2, E35+1) -> 30 | I31: Pen Needles
A32: Week 2 | B32: Daily | C32: 150 | D32: 9 | E32: =IF(B32="Daily",7, IF(B32="Weekly",1, IF(B32="Every Other Day",4,""))) -> 7 | F32: =+D32*E32 -> 63 | H32: =ROUNDUP(F36,0) -> 1 | I32: Cartridges
A33: Week 3 | B33: Daily | C33: 200 | D33: 12 | E33: =IF(B33="Daily",7, IF(B33="Weekly",1, IF(B33="Every Other Day",4,""))) -> 7 | F33: =+D33*E33 -> 84 | H33: =H31 -> 30 | I33: Alochol Prep
A34: Week 4 | B34: Daily | C34: 250 | D34: 15 | E34: =IF(B34="Daily",7, IF(B34="Weekly",1, IF(B34="Every Other Day",4,""))) -> 7 | F34: =+D34*E34 -> 105 | H34: 1 | I34: Case | J34: =H34*3.65 -> 3.65
E35: =SUM(E31:E34) -> 28 | F35: =SUM(F31:F34) -> 294 | J35: =SUM(J29:J34) -> 57.844 | K35: =ROUNDUP(SUM(K29:K34),0) -> 153 | M35: Profit | N35: =+K35-J35 -> 95.156
E36: Number of Cartridges needed | F36: =+F35/300 -> 0.98 | I36: Per Unit | J36: =+J35/H29 -> 0.1967483 | K36: =+K35/H29 -> 0.52040816
K40: Reg Price
H41: =ROUNDUP(F47,0) -> 483 | I41: Units | J41: =+B7*F47 -> 89.033 | K41: =+F47*F7 -> 250.033
A42: Month 2 | B42: Frequency of Injection | C42: mcg | D42: Units per Injections | E42: # of Injections | F42: Units Needed | H42: 0 | I42: Pen | J42: =+H42*45 -> 0 | K42: =+H42*85 -> 0
A43: Week 5 | B43: Daily | C43: 250 | D43: 15 | E43: =IF(B43="Daily",7, IF(B43="Weekly",1, IF(B43="Every Other Day",4,""))) -> 7 | F43: =+D43*E43 -> 105 | H43: =IF(E47>=25, E47+2, E47+1) -> 30 | I43: Pen Needles
A44: Week 6 | B44: Daily | C44: 300 | D44: 18 | E44: =IF(B44="Daily",7, IF(B44="Weekly",1, IF(B44="Every Other Day",4,""))) -> 7 | F44: =+D44*E44 -> 126 | H44: =ROUNDUP(F48,0) -> 2 | I44: Cartridges
A45: Week 7 | B45: Daily | C45: 300 | D45: 18 | E45: =IF(B45="Daily",7, IF(B45="Weekly",1, IF(B45="Every Other Day",4,""))) -> 7 | F45: =+D45*E45 -> 126 | H45: =H43 -> 30 | I45: Alochol Prep
A46: Week 8 | B46: Daily | C46: 300 | D46: 18 | E46: =IF(B46="Daily",7, IF(B46="Weekly",1, IF(B46="Every Other Day",4,""))) -> 7 | F46: =+D46*E46 -> 126 | H46: 0 | I46: Case | J46: =H46*3.65 -> 0
E47: =SUM(E43:E46) -> 28 | F47: =SUM(F43:F46) -> 483 | J47: =SUM(J41:J46) -> 89.033 | K47: =ROUNDUP(SUM(K41:K46),0) -> 251
E48: Number of Cartridges needed | F48: =+F47/300 -> 1.61 | I48: Per Unit | J48: =+J47/H41 -> 0.18433333 | K48: =+K47/H41 -> 0.51966874 | M48: Profit | N48: =+K47-J47 -> 161.967
A52: Weeks 9-12: see below OR…..
B53: The patient needs to have a conversation with Unruh as they will most likely take this month OFF.
B54: When the patient returns they may continue to match Week 9-12 or go on a custome protocol
K58: Reg Price
H59: =ROUNDUP(F65,0) -> 546 | I59: Units | J59: =+B7*F65 -> 100.646 | K59: =+F65*F7 -> 282.646
A60: Month 3 | B60: Frequency of Injection | C60: mcg | D60: Units per Injections | E60: # of Injections | F60: Units Needed | H60: 0 | I60: Pen | J60: =+H60*45 -> 0 | K60: =+H60*85 -> 0
A61: Week 9 | B61: Daily | C61: 300 | D61: 18 | E61: =IF(B61="Daily",7, IF(B61="Weekly",1, IF(B61="Every Other Day",4,""))) -> 7 | F61: =+D61*E61 -> 126 | H61: =IF(E65>=25, E65+2, E65+1) -> 30 | I61: Pen Needles
A62: Week 10 | B62: Daily | C62: 300 | D62: 18 | E62: =IF(B62="Daily",7, IF(B62="Weekly",1, IF(B62="Every Other Day",4,""))) -> 7 | F62: =+D62*E62 -> 126 | H62: =ROUNDUP(F66,0) -> 2 | I62: Cartridges | J62: =H62*0.6 -> 1.2 | K62: =+H62 -> 2
A63: Week 11 | B63: Daily | C63: 350 | D63: 21 | E63: =IF(B63="Daily",7, IF(B63="Weekly",1, IF(B63="Every Other Day",4,""))) -> 7 | F63: =+D63*E63 -> 147 | H63: =H61 -> 30 | I63: Alochol Prep
A64: Week 12 | B64: Daily | C64: 350 | D64: 21 | E64: =IF(B64="Daily",7, IF(B64="Weekly",1, IF(B64="Every Other Day",4,""))) -> 7 | F64: =+D64*E64 -> 147 | H64: 0 | I64: Case | J64: =H64*3.65 -> 0
E65: =SUM(E61:E64) -> 28 | F65: =SUM(F61:F64) -> 546 | J65: =SUM(J59:J64) -> 101.846 | K65: =ROUNDUP(SUM(K59:K64),0) -> 285 | M65: Profit | N65: =+K65-J65 -> 183.154
E66: Number of Cartridges needed | F66: =+F65/300 -> 1.82 | I66: Per Unit | J66: =+J65/H59 -> 0.18653114 | K66: =+K65/H59 -> 0.52197802
K70: Reg Price
H71: =ROUNDUP(F77,0) -> 651 | I71: Units | J71: =+B7*F77 -> 120.001 | K71: =+F77*F7 -> 337.001
A72: Month 4 | B72: Frequency of Injection | C72: mcg | D72: Units per Injections | E72: # of Injections | F72: Units Needed | H72: 0 | I72: Pen | J72: =+H72*45 -> 0 | K72: =+H72*85 -> 0
A73: Week 13 | B73: Daily | C73: 350 | D73: 21 | E73: =IF(B73="Daily",7, IF(B73="Weekly",1, IF(B73="Every Other Day",4,""))) -> 7 | F73: =+D73*E73 -> 147 | H73: =IF(E77>=25, E77+2, E77+1) -> 30 | I73: Pen Needles
A74: Week 14 | B74: Daily | C74: 400 | D74: 24 | E74: =IF(B74="Daily",7, IF(B74="Weekly",1, IF(B74="Every Other Day",4,""))) -> 7 | F74: =+D74*E74 -> 168 | H74: =ROUNDUP(F78,0) -> 3 | I74: Cartridges | J74: =H74*0.6 -> 1.8 | K74: =H74 -> 3
A75: Week 15 | B75: Daily | C75: 400 | D75: 24 | E75: =IF(B75="Daily",7, IF(B75="Weekly",1, IF(B75="Every Other Day",4,""))) -> 7 | F75: =+D75*E75 -> 168 | H75: =H73 -> 30 | I75: Alochol Prep
A76: Week 16 | B76: Daily | C76: 400 | D76: 24 | E76: =IF(B76="Daily",7, IF(B76="Weekly",1, IF(B76="Every Other Day",4,""))) -> 7 | F76: =+D76*E76 -> 168 | H76: 0 | I76: Case | J76: =H76*3.65 -> 0
E77: =SUM(E73:E76) -> 28 | F77: =SUM(F73:F76) -> 651 | J77: =SUM(J71:J76) -> 121.801 | K77: =ROUNDUP(SUM(K71:K76),0) -> 341 | M77: Profit | N77: =+K77-J77 -> 219.199
E78: Number of Cartridges needed | F78: =+F77/300 -> 2.17 | I78: Per Unit | J78: =+J77/H71 -> 0.18709831 | K78: =+K77/H71 -> 0.52380952
K82: Reg Price
H83: =ROUNDUP(F89,0) -> 777 | I83: Units | J83: =+B7*F89 -> 143.227 | K83: =+F89*F7 -> 402.227
A84: Month 5 | B84: Frequency of Injection | C84: mcg | D84: Units per Injections | E84: # of Injections | F84: Units Needed | H84: 0 | I84: Pen | J84: =+H84*45 -> 0 | K84: =+H84*85 -> 0
A85: Week 17 | B85: Daily | C85: 450 | D85: 27 | E85: =IF(B85="Daily",7, IF(B85="Weekly",1, IF(B85="Every Other Day",4,""))) -> 7 | F85: =+D85*E85 -> 189 | H85: =IF(E89>=25, E89+2, E89+1) -> 30 | I85: Pen Needles
A86: Week 18 | B86: Daily | C86: 450 | D86: 27 | E86: =IF(B86="Daily",7, IF(B86="Weekly",1, IF(B86="Every Other Day",4,""))) -> 7 | F86: =+D86*E86 -> 189 | H86: =ROUNDUP(F90,0) -> 3 | I86: Cartridges | J86: =H86*0.6 -> 1.8 | K86: =H86 -> 3
A87: Week 19 | B87: Daily | C87: 450 | D87: 27 | E87: =IF(B87="Daily",7, IF(B87="Weekly",1, IF(B87="Every Other Day",4,""))) -> 7 | F87: =+D87*E87 -> 189 | H87: =H85 -> 30 | I87: Alochol Prep
A88: Week 20 | B88: Daily | C88: 500 | D88: 30 | E88: =IF(B88="Daily",7, IF(B88="Weekly",1, IF(B88="Every Other Day",4,""))) -> 7 | F88: =+D88*E88 -> 210 | H88: 0 | I88: Case | J88: =H88*3.65 -> 0
E89: =SUM(E85:E88) -> 28 | F89: =SUM(F85:F88) -> 777 | J89: =SUM(J83:J88) -> 145.027 | K89: =ROUNDUP(SUM(K83:K88),0) -> 406 | M89: Profit | N89: =+K89-J89 -> 260.973
E90: Number of Cartridges needed | F90: =+F89/300 -> 2.59 | I90: Per Unit | J90: =+J89/H83 -> 0.18664994 | K90: =+K89/H83 -> 0.52252252
K94: Reg Price
H95: =ROUNDUP(F101,0) -> 840 | I95: Units | J95: =+B7*F101 -> 154.84 | K95: =+F101*F7 -> 434.84
A96: Month 6 | B96: Frequency of Injection | C96: mcg | D96: Units per Injections | E96: # of Injections | F96: Units Needed | H96: 0 | I96: Pen | J96: =+H96*45 -> 0 | K96: =+H96*85 -> 0
A97: Week 17 | B97: Daily | C97: 500 | D97: 30 | E97: =IF(B97="Daily",7, IF(B97="Weekly",1, IF(B97="Every Other Day",4,""))) -> 7 | F97: =+D97*E97 -> 210 | H97: =IF(E101>=25, E101+2, E101+1) -> 30 | I97: Pen Needles
A98: Week 18 | B98: Daily | C98: 500 | D98: 30 | E98: =IF(B98="Daily",7, IF(B98="Weekly",1, IF(B98="Every Other Day",4,""))) -> 7 | F98: =+D98*E98 -> 210 | H98: =ROUNDUP(F102,0) -> 3 | I98: Cartridges | J98: =H98*0.6 -> 1.8 | K98: =H98 -> 3
A99: Week 19 | B99: Daily | C99: 500 | D99: 30 | E99: =IF(B99="Daily",7, IF(B99="Weekly",1, IF(B99="Every Other Day",4,""))) -> 7 | F99: =+D99*E99 -> 210 | H99: =H97 -> 30 | I99: Alochol Prep
A100: Week 20 | B100: Daily | C100: 500 | D100: 30 | E100: =IF(B100="Daily",7, IF(B100="Weekly",1, IF(B100="Every Other Day",4,""))) -> 7 | F100: =+D100*E100 -> 210 | H100: 0 | I100: Case | J100: =H100*3.65 -> 0
E101: =SUM(E97:E100) -> 28 | F101: =SUM(F97:F100) -> 840 | J101: =SUM(J95:J100) -> 156.64 | K101: =ROUNDUP(SUM(K95:K100),0) -> 438 | M101: Profit | N101: =+K101-J101 -> 281.36
E102: Number of Cartridges needed | F102: =+F101/300 -> 2.8 | I102: Per Unit | J102: =+J101/H95 -> 0.18647619 | K102: =+K101/H95 -> 0.52142857
A109: Over 10 months
D110: Sell the bottle?
A111: If we sell exactly what the need: | D111: how many vials do you need for 10 months?
A112: based on Week 17-20 | E112: Units per month | F112: =F101 -> 840
A113: Monthly Profit | B113: =N101 -> 281.36 | E113: Months | F113: 10
F114: =+F113*F112 -> 8400 | G114: Unts needed
E115: Number of vials (div by 300) | F115: =ROUNDUP((F114/300),0) -> 28
E116: $100 per vial | F116: =+F115*E5 -> 2800
E118: Average montly profit | F118: =+F116/10 -> 280
A126: What is the largest disocunt/Sale we can offer on Peptides? | G126: What is the largest disocunt/Sale we can offer on Peptides?
A127: Based on highest dosage: | G127: Based on FIRSTS MONTH
B129: Pt Price | C129: Cost | D129: Profit | H129: Pt Price | I129: Cost | J129: Profit
A130: 0 | B130: =K101 -> 438 | C130: =J101 -> 156.64 | D130: =+B130-C130 -> 281.36 | G130: 0 | H130: =K35 -> 153 | I130: =J35 -> 57.844 | J130: =+H130-I130 -> 95.156
A131: 0.1 | B131: =0.9*B130 -> 394.2 | C131: =C130 -> 156.64 | D131: =+B131-C131 -> 237.56 | G131: 0.1 | H131: =0.9*H130 -> 137.7 | I131: =I130 -> 57.844 | J131: =+H131-I131 -> 79.856
A132: 0.15 | B132: =+B130*0.85 -> 372.3 | C132: =C131 -> 156.64 | D132: =+B132-C132 -> 215.66 | G132: 0.15 | H132: =+H130*0.85 -> 130.05 | I132: =I131 -> 57.844 | J132: =+H132-I132 -> 72.206
A133: 0.2 | B133: =0.8*B130 -> 350.4 | C133: =C132 -> 156.64 | D133: =+B133-C133 -> 193.76 | G133: 0.2 | H133: =0.8*H130 -> 122.4 | I133: =I132 -> 57.844 | J133: =+H133-I133 -> 64.556
A134: 0.25 | B134: =0.75*B130 -> 328.5 | C134: =C133 -> 156.64 | D134: =+B134-C134 -> 171.86 | G134: 0.25 | H134: =0.755*H130 -> 115.515 | I134: =I133 -> 57.844 | J134: =+H134-I134 -> 57.671

Sheet DSIP 10mg
A1: DSIP 10mg | N1: Daily
B2: ='Pep Costs'!B17 -> 47 | C2: cost | N2: Every Other Day
B3: 3.3 | C3: BAC | N3: Weekly
B4: 15 | C4: (30) Pen Needles, Cartridges, Alcohol Prep | F4: Add per vial | G4: Reg Price
B5: =SUM(B2:B4) -> 65.3 | F5: 100 | G5: =+F5+B5 -> 165.3
A7: Per Unit | B7: =+B5/300 -> 0.21766667 | F7: Per Unit | G7: =+G5/300 -> 0.551
A13: CUSTOM PROTOCOL | K13: Reg Price
H14: =ROUNDUP(F20,0) -> 57 | I14: Units | J14: =+B7*F20 -> 12.407 | K14: =+F20*G7 -> 31.407
B15: Frequency of Injection | C15: mcg | D15: Units per Injections | E15: # of Injections | F15: Units Needed | H15: 0 | I15: Pen | J15: =+H15*45 -> 0 | K15: =+H15*85 -> 0
A16: Week | B16: Every Other Day | C16: 100 | D16: 3 | E16: =IF(B16="Daily",7, IF(B16="Weekly",1, IF(B16="Every Other Day",4,""))) -> 4 | F16: =+D16*E16 -> 12 | H16: =IF(E20>=25, E20+2, E20+1) -> 20 | I16: Pen Needles
A17: Week | B17: Daily | C17: 100 | D17: 3 | E17: =IF(B17="Daily",7, IF(B17="Weekly",1, IF(B17="Every Other Day",4,""))) -> 7 | F17: =+D17*E17 -> 21 | H17: =ROUNDUP(F21,0) -> 1 | I17: Cartridges
A18: Week | B18: Weekly | C18: 100 | D18: 3 | E18: =IF(B18="Daily",7, IF(B18="Weekly",1, IF(B18="Every Other Day",4,""))) -> 1 | F18: =+D18*E18 -> 3 | H18: =H16 -> 20 | I18: Alochol Prep
A19: Week | B19: Daily | C19: 10 | D19: 3 | E19: =IF(B19="Daily",7, IF(B19="Weekly",1, IF(B19="Every Other Day",4,""))) -> 7 | F19: =+D19*E19 -> 21 | H19: 0 | I19: Case | J19: =H19*3.65 -> 0
E20: =SUM(E16:E19) -> 19 | F20: =SUM(F16:F19) -> 57 | J20: =SUM(J14:J19) -> 12.407 | K20: =ROUNDUP(SUM(K14:K19),0) -> 32 | M20: Profit | N20: =+K20-J20 -> 19.593
E21: Number of Cartridges needed | F21: =+F20/300 -> 0.19 | I21: Per Unit | J21: =+J20/H14 -> 0.21766667 | K21: =+K20/H14 -> 0.56140351
K27: Reg Price
H28: =ROUNDUP(F34,0) -> 154 | I28: Units | J28: =F34*B7 -> 33.520667 | K28: =+F34*G7 -> 84.854
A29: Month 1 | B29: Frequency of Injection | C29: mcg | D29: Units per Injections | E29: # of Injections | F29: Units Needed | H29: 0 | I29: Pen | J29: =+H29*45 -> 0 | K29: =H29*85 -> 0
A30: Week 1 | B30: Daily | C30: 100 | D30: 3 | E30: =IF(B30="Daily",7, IF(B30="Weekly",1, IF(B30="Every Other Day",4,""))) -> 7 | F30: =+D30*E30 -> 21 | H30: =IF(E34>=25, E34+2, E34+1) -> 30 | I30: Pen Needles
A31: Week 2 | B31: Daily | C31: 150 | D31: 5 | E31: =IF(B31="Daily",7, IF(B31="Weekly",1, IF(B31="Every Other Day",4,""))) -> 7 | F31: =+D31*E31 -> 35 | H31: =ROUNDUP(F35,0) -> 1 | I31: Cartridges
A32: Week 3 | B32: Daily | C32: 200 | D32: 6 | E32: =IF(B32="Daily",7, IF(B32="Weekly",1, IF(B32="Every Other Day",4,""))) -> 7 | F32: =+D32*E32 -> 42 | H32: =H30 -> 30 | I32: Alochol Prep
A33: Week 4 | B33: Daily | C33: 250 | D33: 8 | E33: =IF(B33="Daily",7, IF(B33="Weekly",1, IF(B33="Every Other Day",4,""))) -> 7 | F33: =+D33*E33 -> 56 | H33: 1 | I33: Case | J33: =H33*3.65 -> 3.65
E34: =SUM(E30:E33) -> 28 | F34: =SUM(F30:F33) -> 154 | J34: =SUM(J28:J33) -> 37.170667 | K34: =ROUNDUP(SUM(K28:K33),0) -> 85 | M34: Profit | N34: =+K34-J34 -> 47.829333
E35: Number of Cartridges needed | F35: =+F34/300 -> 0.51333333 | I35: Per Unit | J35: =+J34/H28 -> 0.24136797 | K35: =+K34/H28 -> 0.55194805
K39: Reg Price
H40: =ROUNDUP(F46,0) -> 252 | I40: Units | J40: =+B7*F46 -> 54.852 | K40: =+F46*G7 -> 138.852
A41: Month 2 | B41: Frequency of Injection | C41: mcg | D41: Units per Injections | E41: # of Injections | F41: Units Needed | H41: 0 | I41: Pen | J41: =+H41*45 -> 0 | K41: =+H41*85 -> 0
A42: Week 5 | B42: Daily | C42: 300 | D42: 9 | E42: =IF(B42="Daily",7, IF(B42="Weekly",1, IF(B42="Every Other Day",4,""))) -> 7 | F42: =+D42*E42 -> 63 | H42: =IF(E46>=25, E46+2, E46+1) -> 30 | I42: Pen Needles
A43: Week 6 | B43: Daily | C43: 300 | D43: 9 | E43: =IF(B43="Daily",7, IF(B43="Weekly",1, IF(B43="Every Other Day",4,""))) -> 7 | F43: =+D43*E43 -> 63 | H43: =ROUNDUP(F47,0) -> 1 | I43: Cartridges
A44: Week 7 | B44: Daily | C44: 300 | D44: 9 | E44: =IF(B44="Daily",7, IF(B44="Weekly",1, IF(B44="Every Other Day",4,""))) -> 7 | F44: =+D44*E44 -> 63 | H44: =H42 -> 30 | I44: Alochol Prep
A45: Week 8 | B45: Daily | C45: 300 | D45: 9 | E45: =IF(B45="Daily",7, IF(B45="Weekly",1, IF(B45="Every Other Day",4,""))) -> 7 | F45: =+D45*E45 -> 63 | H45: 0 | I45: Case | J45: =H45*3.65 -> 0
E46: =SUM(E42:E45) -> 28 | F46: =SUM(F42:F45) -> 252 | J46: =SUM(J40:J45) -> 54.852 | K46: =ROUNDUP(SUM(K40:K45),0) -> 139
E47: Number of Cartridges needed | F47: =+F46/300 -> 0.84 | I47: Per Unit | J47: =+J46/H40 -> 0.21766667 | K47: =+K46/H40 -> 0.5515873 | M47: Profit | N47: =+K46-J46 -> 84.148
K51: Reg Price
H52: =ROUNDUP(F58,0) -> 252 | I52: Units | J52: =+B19*F58 -> #VALUE! | K52: =+F58*G19 -> 0
A53: Month 3 | B53: Frequency of Injection | C53: mcg | D53: Units per Injections | E53: # of Injections | F53: Units Needed | H53: 0 | I53: Pen | J53: =+H53*45 -> 0 | K53: =+H53*85 -> 0
A54: Week 9 | B54: Daily | C54: 300 | D54: 9 | E54: =IF(B54="Daily",7, IF(B54="Weekly",1, IF(B54="Every Other Day",4,""))) -> 7 | F54: =+D54*E54 -> 63 | H54: =IF(E58>=25, E58+2, E58+1) -> 30 | I54: Pen Needles
A55: Week 10 | B55: Daily | C55: 300 | D55: 9 | E55: =IF(B55="Daily",7, IF(B55="Weekly",1, IF(B55="Every Other Day",4,""))) -> 7 | F55: =+D55*E55 -> 63 | H55: =ROUNDUP(F59,0) -> 1 | I55: Cartridges
A56: Week 11 | B56: Daily | C56: 300 | D56: 9 | E56: =IF(B56="Daily",7, IF(B56="Weekly",1, IF(B56="Every Other Day",4,""))) -> 7 | F56: =+D56*E56 -> 63 | H56: =H54 -> 30 | I56: Alochol Prep
A57: Week 12 | B57: Daily | C57: 300 | D57: 9 | E57: =IF(B57="Daily",7, IF(B57="Weekly",1, IF(B57="Every Other Day",4,""))) -> 7 | F57: =+D57*E57 -> 63 | H57: 0 | I57: Case | J57: =H57*3.65 -> 0
E58: =SUM(E54:E57) -> 28 | F58: =SUM(F54:F57) -> 252 | J58: =SUM(J52:J57) -> #VALUE! | K58: =ROUNDUP(SUM(K52:K57),0) -> 0
E59: Number of Cartridges needed | F59: =+F58/300 -> 0.84 | I59: Per Unit | J59: =+J58/H52 -> #VALUE! | K59: =+K58/H52 -> 0 | M59: Profit | N59: =+K58-J58 -> #VALUE!
A63: Month 4 | B63: The patient needs to have a conversation with Unruh as they will most likely take this month OFF.
A64: Week 13-16
A70: Over 10 months
D71: Sell the bottle?
A72: If we sell exactly what the need: | D72: how many vials do you need for 10 months?
A73: based on Week 1-4 | E73: Units per month | F73: =F46 -> 252
A74: Monthly Profit | B74: =N47 -> 84.148 | E74: Months | F74: 10
F75: =+F74*F73 -> 2520 | G75: Unts needed
E76: Number of vials (div by 300) | F76: =ROUNDUP((F75/300),0) -> 9
E77: $100 per vial | F77: =+F76*100 -> 900
E79: Average montly profit | F79: =+F77/10 -> 90
A87: What is the largest disocunt/Sale we can offer on Peptides? | G87: What is the largest disocunt/Sale we can offer on Peptides?
A88: Based on highest dosage: | G88: Based on FIRSTS MONTH
B90: Pt Price | C90: Cost | D90: Profit | H90: Pt Price | I90: Cost | J90: Profit
A91: 0 | B91: =K46 -> 139 | C91: =J46 -> 54.852 | D91: =+B91-C91 -> 84.148 | G91: 0 | H91: =K34 -> 85 | I91: =J34 -> 37.170667 | J91: =+H91-I91 -> 47.829333
A92: 0.1 | B92: =0.9*B91 -> 125.1 | C92: =C91 -> 54.852 | D92: =+B92-C92 -> 70.248 | G92: 0.1 | H92: =0.9*H91 -> 76.5 | I92: =I91 -> 37.170667 | J92: =+H92-I92 -> 39.329333
A93: 0.15 | B93: =+B91*0.85 -> 118.15 | C93: =C92 -> 54.852 | D93: =+B93-C93 -> 63.298 | G93: 0.15 | H93: =+H91*0.85 -> 72.25 | I93: =I92 -> 37.170667 | J93: =+H93-I93 -> 35.079333
A94: 0.2 | B94: =0.8*B91 -> 111.2 | C94: =C93 -> 54.852 | D94: =+B94-C94 -> 56.348 | G94: 0.2 | H94: =0.8*H91 -> 68 | I94: =I93 -> 37.170667 | J94: =+H94-I94 -> 30.829333
A95: 0.25 | B95: =0.75*B91 -> 104.25 | C95: =C94 -> 54.852 | D95: =+B95-C95 -> 49.398 | G95: 0.25 | H95: =0.755*H91 -> 64.175 | I95: =I94 -> 37.170667 | J95: =+H95-I95 -> 27.004333

Sheet Epithalon
A1: Epithalon 10mg | M1: Daily
B2: 75 | C2: cost | M2: Every Other Day
B3: 3.3 | C3: BAC | M3: Weekly
B4: 15 | C4: (30) Pen Needles, Cartridges, Alcohol Prep | F4: Add per vial | G4: Reg Price
B5: =SUM(B2:B4) -> 93.3 | F5: 40 | G5: =+F5+B5 -> 133.3
A7: Per Unit | B7: =+B5/300 -> 0.311 | F7: Per Unit | G7: =+G5/300 -> 0.44433333
A13: CUSTOM PROTOCOL | K13: Reg Price
H14: =ROUNDUP(F20,0) -> 285 | I14: Units | J14: =+B7*F20 -> 88.635 | K14: =+F20*G7 -> 126.635
B15: Frequency of Injection | C15: mcg | D15: Units per Injections | E15: # of Injections | F15: Units Needed | H15: 1 | I15: Pen | J15: =+H15*45 -> 45 | K15: =+H15*85 -> 85
A16: Week | B16: Daily | C16: 500 | D16: 15 | E16: =IF(B16="Daily",7, IF(B16="Weekly",1, IF(B16="Every Other Day",4,""))) -> 7 | F16: =+D16*E16 -> 105 | H16: =IF(E20>=25, E20+2, E20+1) -> 20 | I16: Pen Needles
A17: Week | B17: Every Other Day | C17: 500 | D17: 15 | E17: =IF(B17="Daily",7, IF(B17="Weekly",1, IF(B17="Every Other Day",4,""))) -> 4 | F17: =+D17*E17 -> 60 | H17: =ROUNDUP(F21,0) -> 1 | I17: Cartridges
A18: Week | B18: Daily | C18: 500 | D18: 15 | E18: =IF(B18="Daily",7, IF(B18="Weekly",1, IF(B18="Every Other Day",4,""))) -> 7 | F18: =+D18*E18 -> 105 | H18: =H16 -> 20 | I18: Alochol Prep
A19: Week | B19: Weekly | C19: 500 | D19: 15 | E19: =IF(B19="Daily",7, IF(B19="Weekly",1, IF(B19="Every Other Day",4,""))) -> 1 | F19: =+D19*E19 -> 15 | H19: 0 | I19: Case | J19: =H19*3.65 -> 0
E20: =SUM(E16:E19) -> 19 | F20: =SUM(F16:F19) -> 285 | J20: =SUM(J14:J19) -> 133.635 | K20: =ROUNDUP(SUM(K14:K19),0) -> 212 | M20: Profit | N20: =+K20-J20 -> 78.365
E21: Number of Cartridges needed | F21: =+F20/300 -> 0.95 | I21: Per Unit | J21: =+J20/H14 -> 0.46889474 | K21: =+K20/H14 -> 0.74385965
K26: Reg Price
H27: =ROUNDUP(F33,0) -> 3150 | I27: Units | J27: =F33*B7 -> 979.65 | K27: =+F33*G7 -> 1399.65
A28: Month 1 | B28: Frequency of Injection | C28: mcg | D28: Units per Injections | E28: # of Injections | F28: Units Needed | H28: 0 | I28: Pen | J28: =+H28*45 -> 0 | K28: =H28*85 -> 0
A29: Week 1 | B29: Daily | C29: 5000 | D29: 150 | E29: =IF(B29="Daily",7, IF(B29="Weekly",1, IF(B29="Every Other Day",4,""))) -> 7 | F29: =+D29*E29 -> 1050 | H29: =IF(E33>=25, E33+2, E33+1) -> 30 | I29: Pen Needles
A30: Week 2 | B30: Daily | C30: 5000 | D30: 150 | E30: =IF(B30="Daily",7, IF(B30="Weekly",1, IF(B30="Every Other Day",4,""))) -> 7 | F30: =+D30*E30 -> 1050 | H30: =ROUNDUP(F34,0) -> 11 | I30: Cartridges
A31: Week 3 | B31: Daily | C31: 5000 | D31: 150 | E31: =IF(B31="Daily",7, IF(B31="Weekly",1, IF(B31="Every Other Day",4,""))) -> 7 | F31: =+D31*E31 -> 1050 | H31: =H29 -> 30 | I31: Alochol Prep
A32: Week 4 | B32: Daily | C32: 0 | D32: 0 | E32: =IF(B32="Daily",7, IF(B32="Weekly",1, IF(B32="Every Other Day",4,""))) -> 7 | F32: =+D32*E32 -> 0 | H32: 1 | I32: Case | J32: =H32*3.65 -> 3.65
E33: =SUM(E29:E32) -> 28 | F33: =SUM(F29:F32) -> 3150 | J33: =SUM(J27:J32) -> 983.3 | K33: =ROUNDUP(SUM(K27:K32),0) -> 1400 | M33: Profit | N33: =+K33-J33 -> 416.7
E34: Number of Cartridges needed | F34: =+F33/300 -> 10.5 | I34: Per Unit | J34: =+J33/H27 -> 0.31215873 | K34: =+K33/H27 -> 0.44444444
A38: Peptidedosages.com only has a THREE week protocol
A46: Over 10 months
D47: Sell the bottle?
A48: If we sell exactly what the need: | D48: how many vials do you need for 10 months?
E49: Units per month | F49: =F33 -> 3150
A50: Monthly Profit | B50: =N33 -> 416.7 | E50: Months | F50: 10
F51: =+F50*F49 -> 31500 | G51: Unts needed
E52: Number of vials (div by 300) | F52: =ROUNDUP((F51/300),0) -> 105
E53: $100 per vial | F53: =+F52*100 -> 10500
E55: Average montly profit | F55: =+F53/10 -> 1050
A63: What is the largest disocunt/Sale we can offer on Peptides? | G63: What is the largest disocunt/Sale we can offer on Peptides?
A64: Based on highest dosage: | G64: Based on FIRSTS MONTH
B66: Pt Price | C66: Cost | D66: Profit | H66: Pt Price | I66: Cost | J66: Profit
A67: 0 | B67: =K33 -> 1400 | C67: =J33 -> 983.3 | D67: =+B67-C67 -> 416.7 | G67: 0 | H67: =K33 -> 1400 | I67: =J27 -> 979.65 | J67: =+H67-I67 -> 420.35
A68: 0.1 | B68: =0.9*B67 -> 1260 | C68: =C67 -> 983.3 | D68: =+B68-C68 -> 276.7 | G68: 0.1 | H68: =0.9*H67 -> 1260 | I68: =I67 -> 979.65 | J68: =+H68-I68 -> 280.35
A69: 0.15 | B69: =+B67*0.85 -> 1190 | C69: =C68 -> 983.3 | D69: =+B69-C69 -> 206.7 | G69: 0.15 | H69: =+H67*0.85 -> 1190 | I69: =I68 -> 979.65 | J69: =+H69-I69 -> 210.35
A70: 0.2 | B70: =0.8*B67 -> 1120 | C70: =C69 -> 983.3 | D70: =+B70-C70 -> 136.7 | G70: 0.2 | H70: =0.8*H67 -> 1120 | I70: =I69 -> 979.65 | J70: =+H70-I70 -> 140.35
A71: 0.25 | B71: =0.75*B67 -> 1050 | C71: =C70 -> 983.3 | D71: =+B71-C71 -> 66.7 | G71: 0.25 | H71: =0.755*H67 -> 1057 | I71: =I70 -> 979.65 | J71: =+H71-I71 -> 77.35

Sheet GHK-CU 50
A1: GHK-CU 50mg | O1: Daily
B2: ='Pep Costs'!B21 -> 45 | C2: cost | O2: Every Other Day
B3: 3.3 | C3: BAC | O3: Weekly
B4: 15 | C4: (30) Pen Needles, Cartridges, Alcohol Prep | F4: Add per vial | G4: Reg Price
B5: =SUM(B2:B4) -> 63.3 | F5: 100 | G5: =+F5+B5 -> 163.3
A7: Per Unit | B7: =+B5/300 -> 0.211 | F7: Per Unit | G7: =+G5/300 -> 0.54433333
A13: CUSTOM PROTOCOL | K13: Reg Price
H14: =ROUNDUP(F20,0) -> 114 | I14: Units | J14: =+B7*F20 -> 24.054 | K14: =+F20*G7 -> 62.054
B15: Frequency of Injection | C15: mcg | D15: Units per Injections | E15: # of Injections | F15: Units Needed | H15: 0 | I15: Pen | J15: =+H15*45 -> 0 | K15: =+H15*85 -> 0
A16: Week | B16: Every Other Day | C16: 1000 | D16: 6 | E16: =IF(B16="Daily",7, IF(B16="Weekly",1, IF(B16="Every Other Day",4,""))) -> 4 | F16: =+D16*E16 -> 24 | H16: =IF(E20>=25, E20+2, E20+1) -> 20 | I16: Pen Needles
A17: Week | B17: Daily | C17: 1000 | D17: 6 | E17: =IF(B17="Daily",7, IF(B17="Weekly",1, IF(B17="Every Other Day",4,""))) -> 7 | F17: =+D17*E17 -> 42 | H17: =ROUNDUP(F21,0) -> 1 | I17: Cartridges
A18: Week | B18: Weekly | C18: 1000 | D18: 6 | E18: =IF(B18="Daily",7, IF(B18="Weekly",1, IF(B18="Every Other Day",4,""))) -> 1 | F18: =+D18*E18 -> 6 | H18: =H16 -> 20 | I18: Alochol Prep
A19: Week | B19: Daily | C19: 1000 | D19: 6 | E19: =IF(B19="Daily",7, IF(B19="Weekly",1, IF(B19="Every Other Day",4,""))) -> 7 | F19: =+D19*E19 -> 42 | H19: 0 | I19: Case | J19: =H19*3.65 -> 0
E20: =SUM(E16:E19) -> 19 | F20: =SUM(F16:F19) -> 114 | J20: =SUM(J14:J19) -> 24.054 | K20: =ROUNDUP(SUM(K14:K19),0) -> 63 | M20: Profit | N20: =+K20-J20 -> 38.946
E21: Number of Cartridges needed | F21: =+F20/300 -> 0.38 | I21: Per Unit | J21: =+J20/H14 -> 0.211 | K21: =+K20/H14 -> 0.55263158
K27: Reg Price
H28: =ROUNDUP(F34,0) -> 168 | I28: Units | J28: =F34*B7 -> 35.448 | K28: =+F34*G7 -> 91.448
A29: Month 1 | B29: Frequency of Injection | C29: mcg | D29: Units per Injections | E29: # of Injections | F29: Units Needed | H29: 0 | I29: Pen | J29: =+H29*45 -> 0 | K29: =H29*85 -> 0
A30: Week 1 | B30: Daily | C30: 1000 | D30: 6 | E30: =IF(B30="Daily",7, IF(B30="Weekly",1, IF(B30="Every Other Day",4,""))) -> 7 | F30: =+D30*E30 -> 42 | H30: =IF(E34>=25, E34+2, E34+1) -> 30 | I30: Pen Needles
A31: Week 2 | B31: Daily | C31: 1000 | D31: 6 | E31: =IF(B31="Daily",7, IF(B31="Weekly",1, IF(B31="Every Other Day",4,""))) -> 7 | F31: =+D31*E31 -> 42 | H31: =ROUNDUP(F35,0) -> 1 | I31: Cartridges
A32: Week 3 | B32: Daily | C32: 1000 | D32: 6 | E32: =IF(B32="Daily",7, IF(B32="Weekly",1, IF(B32="Every Other Day",4,""))) -> 7 | F32: =+D32*E32 -> 42 | H32: =H30 -> 30 | I32: Alochol Prep
A33: Week 4 | B33: Daily | C33: 1000 | D33: 6 | E33: =IF(B33="Daily",7, IF(B33="Weekly",1, IF(B33="Every Other Day",4,""))) -> 7 | F33: =+D33*E33 -> 42 | H33: 1 | I33: Case | J33: =H33*3.65 -> 3.65
E34: =SUM(E30:E33) -> 28 | F34: =SUM(F30:F33) -> 168 | J34: =SUM(J28:J33) -> 39.098 | K34: =ROUNDUP(SUM(K28:K33),0) -> 92 | M34: Profit | N34: =+K34-J34 -> 52.902
E35: Number of Cartridges needed | F35: =+F34/300 -> 0.56 | I35: Per Unit | J35: =+J34/H28 -> 0.23272619 | K35: =+K34/H28 -> 0.54761905
K39: Reg Price
H40: =ROUNDUP(F46,0) -> 252 | I40: Units | J40: =+B7*F46 -> 53.172 | K40: =+F46*G7 -> 137.172
A41: Month 2 | B41: Frequency of Injection | C41: mcg | D41: Units per Injections | E41: # of Injections | F41: Units Needed | H41: 0 | I41: Pen | J41: =+H41*45 -> 0 | K41: =+H41*85 -> 0
A42: Week 5 | B42: Daily | C42: 1500 | D42: 9 | E42: =IF(B42="Daily",7, IF(B42="Weekly",1, IF(B42="Every Other Day",4,""))) -> 7 | F42: =+D42*E42 -> 63 | H42: =IF(E46>=25, E46+2, E46+1) -> 30 | I42: Pen Needles
A43: Week 6 | B43: Daily | C43: 1500 | D43: 9 | E43: =IF(B43="Daily",7, IF(B43="Weekly",1, IF(B43="Every Other Day",4,""))) -> 7 | F43: =+D43*E43 -> 63 | G43: =+F34+F42+F43 -> 294 | H43: =ROUNDUP(F47,0) -> 1 | I43: Cartridges
A44: Week 7 | B44: Daily | C44: 1500 | D44: 9 | E44: =IF(B44="Daily",7, IF(B44="Weekly",1, IF(B44="Every Other Day",4,""))) -> 7 | F44: =+D44*E44 -> 63 | H44: =H42 -> 30 | I44: Alochol Prep
A45: Week 8 | B45: Daily | C45: 1500 | D45: 9 | E45: =IF(B45="Daily",7, IF(B45="Weekly",1, IF(B45="Every Other Day",4,""))) -> 7 | F45: =+D45*E45 -> 63 | H45: 0 | I45: Case | J45: =H45*3.65 -> 0
E46: =SUM(E42:E45) -> 28 | F46: =SUM(F42:F45) -> 252 | J46: =SUM(J40:J45) -> 53.172 | K46: =ROUNDUP(SUM(K40:K45),0) -> 138 | M46: Profit | N46: =+K46-J46 -> 84.828
E47: Number of Cartridges needed | F47: =+F46/300 -> 0.84 | I47: Per Unit | J47: =+J46/H40 -> 0.211 | K47: =+K46/H40 -> 0.54761905
K51: Reg Price
H52: =ROUNDUP(F58,0) -> 336 | I52: Units | J52: =+B7*F58 -> 70.896 | K52: =+F58*G7 -> 182.896
A53: Month 3 | B53: Frequency of Injection | C53: mcg | D53: Units per Injections | E53: # of Injections | F53: Units Needed | H53: 0 | I53: Pen | J53: =+H53*45 -> 0 | K53: =+H53*85 -> 0
A54: Week 9 | B54: Daily | C54: 2000 | D54: 12 | E54: =IF(B54="Daily",7, IF(B54="Weekly",1, IF(B54="Every Other Day",4,""))) -> 7 | F54: =+D54*E54 -> 84 | H54: =IF(E58>=25, E58+2, E58+1) -> 30 | I54: Pen Needles
A55: Week 10 | B55: Daily | C55: 2000 | D55: 12 | E55: =IF(B55="Daily",7, IF(B55="Weekly",1, IF(B55="Every Other Day",4,""))) -> 7 | F55: =+D55*E55 -> 84 | H55: =ROUNDUP(F59,0) -> 2 | I55: Cartridges
A56: Week 11 | B56: Daily | C56: 2000 | D56: 12 | E56: =IF(B56="Daily",7, IF(B56="Weekly",1, IF(B56="Every Other Day",4,""))) -> 7 | F56: =+D56*E56 -> 84 | H56: =H54 -> 30 | I56: Alochol Prep
A57: Week 12 | B57: Daily | C57: 2000 | D57: 12 | E57: =IF(B57="Daily",7, IF(B57="Weekly",1, IF(B57="Every Other Day",4,""))) -> 7 | F57: =+D57*E57 -> 84 | H57: 0 | I57: Case | J57: =H57*3.65 -> 0
E58: =SUM(E54:E57) -> 28 | F58: =SUM(F54:F57) -> 336 | J58: =SUM(J52:J57) -> 70.896 | K58: =ROUNDUP(SUM(K52:K57),0) -> 183 | M58: Profit | N58: =+K58-J58 -> 112.104
E59: Number of Cartridges needed | F59: =+F58/300 -> 1.12 | I59: Per Unit | J59: =+J58/H52 -> 0.211 | K59: =+K58/H52 -> 0.54464286
A63: Month 4 | B63: The patient needs to have a conversation with Unruh as they will most likely take this month OFF.
A64: Week 13-16
A70: Over 10 months
D71: Sell the bottle?
A72: If we sell exactly what the need: | D72: how many vials do you need for 10 months?
A73: based on Week 1-4 | E73: Units per month | F73: =F58 -> 336
A74: Monthly Profit | B74: =N58 -> 112.104 | E74: Months | F74: 10
F75: =+F74*F73 -> 3360 | G75: Unts needed
E76: Number of vials (div by 300) | F76: =ROUNDUP((F75/300),0) -> 12
E77: $100 per vial | F77: =+F76*100 -> 1200
E79: Average montly profit | F79: =+F77/10 -> 120
A87: What is the largest disocunt/Sale we can offer on Peptides? | G87: What is the largest disocunt/Sale we can offer on Peptides?
A88: Based on highest dosage: | G88: Based on FIRSTS MONTH
B90: Pt Price | C90: Cost | D90: Profit | H90: Pt Price | I90: Cost | J90: Profit
A91: 0 | B91: =K58 -> 183 | C91: =J58 -> 70.896 | D91: =+B91-C91 -> 112.104 | G91: 0 | H91: =K34 -> 92 | I91: =J34 -> 39.098 | J91: =+H91-I91 -> 52.902
A92: 0.1 | B92: =0.9*B91 -> 164.7 | C92: =C91 -> 70.896 | D92: =+B92-C92 -> 93.804 | G92: 0.1 | H92: =0.9*H91 -> 82.8 | I92: =I91 -> 39.098 | J92: =+H92-I92 -> 43.702
A93: 0.15 | B93: =+B91*0.85 -> 155.55 | C93: =C92 -> 70.896 | D93: =+B93-C93 -> 84.654 | G93: 0.15 | H93: =+H91*0.85 -> 78.2 | I93: =I92 -> 39.098 | J93: =+H93-I93 -> 39.102
A94: 0.2 | B94: =0.8*B91 -> 146.4 | C94: =C93 -> 70.896 | D94: =+B94-C94 -> 75.504 | G94: 0.2 | H94: =0.8*H91 -> 73.6 | I94: =I93 -> 39.098 | J94: =+H94-I94 -> 34.502
A95: 0.25 | B95: =0.75*B91 -> 137.25 | C95: =C94 -> 70.896 | D95: =+B95-C95 -> 66.354 | G95: 0.25 | H95: =0.755*H91 -> 69.46 | I95: =I94 -> 39.098 | J95: =+H95-I95 -> 30.362

Sheet Glow 70
A1: GLOW 70 | O1: Daily
B2: ='Pep Costs'!B24 -> 105 | C2: cost | O2: Every Other Day
B3: 3.3 | C3: BAC | O3: Weekly
B4: 15 | C4: (30) Pen Needles, Cartridges, Alcohol Prep | F4: Add per vial | G4: Reg Price
B5: =SUM(B2:B4) -> 123.3 | F5: 100 | G5: =+F5+B5 -> 223.3
A7: Per Unit | B7: =+B5/300 -> 0.411 | F7: Per Unit | G7: =+G5/300 -> 0.74433333
A14: CUSTOM PROTOCOL | K14: Reg Price
H15: =ROUNDUP(F21,0) -> 80 | I15: Units | J15: =B7*H15 -> 32.88 | K15: =G7*H15 -> 59.546667
B16: Frequency of Injection | C16: mcg | D16: Units per Injections | E16: # of Injections | F16: Units Needed | H16: 0 | I16: Pen | J16: =+H16*45 -> 0 | K16: =+H16*85 -> 0
A17: Week | B17: Every Other Day | D17: 5 | E17: =IF(B17="Daily",7, IF(B17="Weekly",1, IF(B17="Every Other Day",4,""))) -> 4 | F17: =+D17*E17 -> 20 | H17: =IF(E21>=25, E21+2, E21+1) -> 17 | I17: Pen Needles
A18: Week | B18: Weekly | D18: 5 | E18: =IF(B18="Daily",7, IF(B18="Weekly",1, IF(B18="Every Other Day",4,""))) -> 1 | F18: =+D18*E18 -> 5 | H18: =ROUNDUP(F22,0) -> 1 | I18: Cartridges
A19: Week | B19: Daily | D19: 5 | E19: =IF(B19="Daily",7, IF(B19="Weekly",1, IF(B19="Every Other Day",4,""))) -> 7 | F19: =+D19*E19 -> 35 | H19: =H17 -> 17 | I19: Alochol Prep
A20: Week | B20: Every Other Day | D20: 5 | E20: =IF(B20="Daily",7, IF(B20="Weekly",1, IF(B20="Every Other Day",4,""))) -> 4 | F20: =+D20*E20 -> 20 | H20: 0 | I20: Case | J20: =H20*3.65 -> 0
E21: =SUM(E17:E20) -> 16 | F21: =SUM(F17:F20) -> 80 | J21: =SUM(J15:J20) -> 32.88 | K21: =ROUNDUP(SUM(K15:K20),0) -> 60 | M21: Profit | N21: =+K21-J21 -> 27.12
E22: Number of Cartridges needed | F22: =+F21/300 -> 0.26666667 | I22: Per Unit | J22: =+J21/H15 -> 0.411 | K22: =+K21/H15 -> 0.75
K29: Reg Price
H30: =ROUNDUP(F36,0) -> 280 | I30: Units | J30: =F36*B7 -> 115.08 | K30: =+F36*G7 -> 208.41333
A31: Month 1 | B31: Frequency of Injection | C31: mcg | D31: Units per Injections | E31: # of Injections | F31: Units Needed | H31: 0 | I31: Pen | J31: =+H31*45 -> 0 | K31: =H31*85 -> 0
A32: Week 1 | B32: Daily | C32: 2330 | D32: 10 | E32: =IF(B32="Daily",7, IF(B32="Weekly",1, IF(B32="Every Other Day",4,""))) -> 7 | F32: =+D32*E32 -> 70 | H32: =IF(E36>=25, E36+2, E36+1) -> 30 | I32: Pen Needles
A33: Week 2 | B33: Daily | C33: 2330 | D33: 10 | E33: =IF(B33="Daily",7, IF(B33="Weekly",1, IF(B33="Every Other Day",4,""))) -> 7 | F33: =+D33*E33 -> 70 | H33: =ROUNDUP(F37,0) -> 1 | I33: Cartridges
A34: Week 3 | B34: Daily | C34: 2330 | D34: 10 | E34: =IF(B34="Daily",7, IF(B34="Weekly",1, IF(B34="Every Other Day",4,""))) -> 7 | F34: =+D34*E34 -> 70 | H34: =H32 -> 30 | I34: Alochol Prep
A35: Week 4 | B35: Daily | C35: 2330 | D35: 10 | E35: =IF(B35="Daily",7, IF(B35="Weekly",1, IF(B35="Every Other Day",4,""))) -> 7 | F35: =+D35*E35 -> 70 | H35: 1 | I35: Case | J35: =H35*3.65 -> 3.65
E36: =SUM(E32:E35) -> 28 | F36: =SUM(F32:F35) -> 280 | J36: =SUM(J30:J35) -> 118.73 | K36: =ROUNDUP(SUM(K30:K35),0) -> 209 | M36: Profit | N36: =+K36-J36 -> 90.27
E37: Number of Cartridges needed | F37: =+F36/300 -> 0.93333333 | I37: Per Unit | J37: =+J36/H30 -> 0.42403571 | K37: =+K36/H30 -> 0.74642857
A42: Peptide Dosages only have a 4 week protocol
A49: Over 10 months
D50: Sell the bottle?
A51: If we sell exactly what the need: | D51: how many vials do you need for 10 months?
A52: based on Week 1-4 | E52: Units per month | F52: =F36 -> 280
A53: Monthly Profit | B53: =N36 -> 90.27 | E53: Months | F53: 10
F54: =+F53*F52 -> 2800 | G54: Unts needed
E55: Number of vials (div by 300) | F55: =ROUNDUP((F54/300),0) -> 10
E56: $100 per vial | F56: =+F55*100 -> 1000
E58: Average montly profit | F58: =+F56/10 -> 100
A67: What is the largest disocunt/Sale we can offer on Peptides? | G67: What is the largest disocunt/Sale we can offer on Peptides?
A68: Based on highest dosage: | G68: Based on FIRSTS MONTH
B70: Pt Price | C70: Cost | D70: Profit | H70: Pt Price | I70: Cost | J70: Profit
A71: 0 | B71: =K36 -> 209 | C71: =J36 -> 118.73 | D71: =+B71-C71 -> 90.27 | G71: 0 | H71: =K36 -> 209 | I71: =J36 -> 118.73 | J71: =+H71-I71 -> 90.27
A72: 0.1 | B72: =0.9*B71 -> 188.1 | C72: =C71 -> 118.73 | D72: =+B72-C72 -> 69.37 | G72: 0.1 | H72: =0.9*H71 -> 188.1 | I72: =I71 -> 118.73 | J72: =+H72-I72 -> 69.37
A73: 0.15 | B73: =+B71*0.85 -> 177.65 | C73: =C72 -> 118.73 | D73: =+B73-C73 -> 58.92 | G73: 0.15 | H73: =+H71*0.85 -> 177.65 | I73: =I72 -> 118.73 | J73: =+H73-I73 -> 58.92
A74: 0.2 | B74: =0.8*B71 -> 167.2 | C74: =C73 -> 118.73 | D74: =+B74-C74 -> 48.47 | G74: 0.2 | H74: =0.8*H71 -> 167.2 | I74: =I73 -> 118.73 | J74: =+H74-I74 -> 48.47
A75: 0.25 | B75: =0.75*B71 -> 156.75 | C75: =C74 -> 118.73 | D75: =+B75-C75 -> 38.02 | G75: 0.25 | H75: =0.755*H71 -> 157.795 | I75: =I74 -> 118.73 | J75: =+H75-I75 -> 39.065

Sheet Kissp
A1: Kisspeptine 10mg | O1: Daily
B2: ='Pep Costs'!B31 -> 50 | C2: cost | O2: Every Other Day
B3: 3.3 | C3: BAC | O3: Weekly
B4: 15 | C4: (30) Pen Needles, Cartridges, Alcohol Prep | F4: Add per vial | G4: Reg Price
B5: =SUM(B2:B4) -> 68.3 | F5: 100 | G5: =+F5+B5 -> 168.3
A7: Per Unit | B7: =+B5/300 -> 0.22766667 | F7: Per Unit | G7: =+G5/300 -> 0.561
A13: CUSTOM PROTOCOL | K13: Reg Price
H14: =ROUNDUP(F20,0) -> 114 | I14: Units | J14: =+B7*F20 -> 25.954 | K14: =+F20*G7 -> 63.954
B15: Frequency of Injection | C15: mcg | D15: Units per Injections | E15: # of Injections | F15: Units Needed | H15: 1 | I15: Pen | J15: =+H15*45 -> 45 | K15: =+H15*85 -> 85
A16: Week | B16: Every Other Day | C16: 200 | D16: 6 | E16: =IF(B16="Daily",7, IF(B16="Weekly",1, IF(B16="Every Other Day",4,""))) -> 4 | F16: =+D16*E16 -> 24 | H16: =IF(E20>=25, E20+2, E20+1) -> 20 | I16: Pen Needles
A17: Week | B17: Daily | C17: 200 | D17: 6 | E17: =IF(B17="Daily",7, IF(B17="Weekly",1, IF(B17="Every Other Day",4,""))) -> 7 | F17: =+D17*E17 -> 42 | H17: =ROUNDUP(F21,0) -> 1 | I17: Cartridges
A18: Week | B18: Weekly | C18: 200 | D18: 6 | E18: =IF(B18="Daily",7, IF(B18="Weekly",1, IF(B18="Every Other Day",4,""))) -> 1 | F18: =+D18*E18 -> 6 | H18: =H16 -> 20 | I18: Alochol Prep
A19: Week | B19: Daily | C19: 200 | D19: 6 | E19: =IF(B19="Daily",7, IF(B19="Weekly",1, IF(B19="Every Other Day",4,""))) -> 7 | F19: =+D19*E19 -> 42 | H19: 0 | I19: Case | J19: =H19*3.65 -> 0
E20: =SUM(E16:E19) -> 19 | F20: =SUM(F16:F19) -> 114 | J20: =SUM(J14:J19) -> 70.954 | K20: =ROUNDUP(SUM(K14:K19),0) -> 149 | M20: Profit | N20: =+K20-J20 -> 78.046
E21: Number of Cartridges needed | F21: =+F20/300 -> 0.38 | I21: Per Unit | J21: =+J20/H14 -> 0.62240351 | K21: =+K20/H14 -> 1.3070175
K26: Reg Price
H27: =ROUNDUP(F33,0) -> 126 | I27: Units | J27: =F33*B7 -> 28.686 | K27: =+F33*G7 -> 70.686
A28: Month 1 | B28: Frequency of Injection | C28: mcg | D28: Units per Injections | E28: # of Injections | F28: Units Needed | H28: 0 | I28: Pen | J28: =+H28*45 -> 0 | K28: =H28*85 -> 0
A29: Week 1 | B29: Daily | C29: 100 | D29: 3 | E29: =IF(B29="Daily",7, IF(B29="Weekly",1, IF(B29="Every Other Day",4,""))) -> 7 | F29: =+D29*E29 -> 21 | H29: =IF(E33>=25, E33+2, E33+1) -> 30 | I29: Pen Needles
A30: Week 2 | B30: Daily | C30: 100 | D30: 3 | E30: =IF(B30="Daily",7, IF(B30="Weekly",1, IF(B30="Every Other Day",4,""))) -> 7 | F30: =+D30*E30 -> 21 | H30: =ROUNDUP(F34,0) -> 1 | I30: Cartridges
A31: Week 3 | B31: Daily | C31: 200 | D31: 6 | E31: =IF(B31="Daily",7, IF(B31="Weekly",1, IF(B31="Every Other Day",4,""))) -> 7 | F31: =+D31*E31 -> 42 | H31: =H29 -> 30 | I31: Alochol Prep
A32: Week 4 | B32: Daily | C32: 200 | D32: 6 | E32: =IF(B32="Daily",7, IF(B32="Weekly",1, IF(B32="Every Other Day",4,""))) -> 7 | F32: =+D32*E32 -> 42 | H32: 1 | I32: Case | J32: =H32*3.65 -> 3.65
E33: =SUM(E29:E32) -> 28 | F33: =SUM(F29:F32) -> 126 | J33: =SUM(J27:J32) -> 32.336 | K33: =ROUNDUP(SUM(K27:K32),0) -> 71 | M33: Profit | N33: =+K33-J33 -> 38.664
E34: Number of Cartridges needed | F34: =+F33/300 -> 0.42 | I34: Per Unit | J34: =+J33/H27 -> 0.25663492 | K34: =+K33/H27 -> 0.56349206
K38: Reg Price
H39: =ROUNDUP(F45,0) -> 168 | I39: Units | J39: =+B7*F45 -> 38.248 | K39: =+F45*G7 -> 94.248
A40: Month 2 | B40: Frequency of Injection | C40: mcg | D40: Units per Injections | E40: # of Injections | F40: Units Needed | H40: 0 | I40: Pen | J40: =+H40*45 -> 0 | K40: =+H40*85 -> 0
A41: Week 5 | B41: Daily | C41: 200 | D41: 6 | E41: =IF(B41="Daily",7, IF(B41="Weekly",1, IF(B41="Every Other Day",4,""))) -> 7 | F41: =+D41*E41 -> 42 | H41: =IF(E45>=25, E45+2, E45+1) -> 30 | I41: Pen Needles
A42: Week 6 | B42: Daily | C42: 200 | D42: 6 | E42: =IF(B42="Daily",7, IF(B42="Weekly",1, IF(B42="Every Other Day",4,""))) -> 7 | F42: =+D42*E42 -> 42 | H42: =ROUNDUP(F46,0) -> 1 | I42: Cartridges
A43: Week 7 | B43: Daily | C43: 200 | D43: 6 | E43: =IF(B43="Daily",7, IF(B43="Weekly",1, IF(B43="Every Other Day",4,""))) -> 7 | F43: =+D43*E43 -> 42 | H43: =H41 -> 30 | I43: Alochol Prep
A44: Week 8 | B44: Daily | C44: 200 | D44: 6 | E44: =IF(B44="Daily",7, IF(B44="Weekly",1, IF(B44="Every Other Day",4,""))) -> 7 | F44: =+D44*E44 -> 42 | H44: 0 | I44: Case | J44: =H44*3.65 -> 0
E45: =SUM(E41:E44) -> 28 | F45: =SUM(F41:F44) -> 168 | J45: =SUM(J39:J44) -> 38.248 | K45: =ROUNDUP(SUM(K39:K44),0) -> 95 | M45: Profit | N45: =+K45-J45 -> 56.752
E46: Number of Cartridges needed | F46: =+F45/300 -> 0.56 | I46: Per Unit | J46: =+J45/H39 -> 0.22766667 | K46: =+K45/H39 -> 0.56547619
K50: Reg Price
H51: =ROUNDUP(F57,0) -> 168 | I51: Units | J51: =+B7*F57 -> 38.248 | K51: =+F57*G7 -> 94.248
A52: Month 3 | B52: Frequency of Injection | C52: mcg | D52: Units per Injections | E52: # of Injections | F52: Units Needed | H52: 0 | I52: Pen | J52: =+H52*45 -> 0 | K52: =+H52*85 -> 0
A53: Week 9 | B53: Daily | C53: 200 | D53: 6 | E53: =IF(B53="Daily",7, IF(B53="Weekly",1, IF(B53="Every Other Day",4,""))) -> 7 | F53: =+D53*E53 -> 42 | H53: =IF(E57>=25, E57+2, E57+1) -> 30 | I53: Pen Needles
A54: Week 10 | B54: Daily | C54: 200 | D54: 6 | E54: =IF(B54="Daily",7, IF(B54="Weekly",1, IF(B54="Every Other Day",4,""))) -> 7 | F54: =+D54*E54 -> 42 | H54: =ROUNDUP(F58,0) -> 1 | I54: Cartridges
A55: Week 11 | B55: Daily | C55: 200 | D55: 6 | E55: =IF(B55="Daily",7, IF(B55="Weekly",1, IF(B55="Every Other Day",4,""))) -> 7 | F55: =+D55*E55 -> 42 | H55: =H53 -> 30 | I55: Alochol Prep
A56: Week 12 | B56: Daily | C56: 200 | D56: 6 | E56: =IF(B56="Daily",7, IF(B56="Weekly",1, IF(B56="Every Other Day",4,""))) -> 7 | F56: =+D56*E56 -> 42 | H56: 0 | I56: Case | J56: =H56*3.65 -> 0
E57: =SUM(E53:E56) -> 28 | F57: =SUM(F53:F56) -> 168 | J57: =SUM(J51:J56) -> 38.248 | K57: =ROUNDUP(SUM(K51:K56),0) -> 95 | M57: Profit | N57: =+K57-J57 -> 56.752
E58: Number of Cartridges needed | F58: =+F57/300 -> 0.56 | I58: Per Unit | J58: =+J57/H51 -> 0.22766667 | K58: =+K57/H51 -> 0.56547619
A62: Month 4 | B62: The patient needs to have a conversation with Unruh as they will most likely take this month OFF.
A63: Week 13-16
A70: Over 10 months
D71: Sell the bottle?
A72: If we sell exactly what the need: | D72: how many vials do you need for 10 months?
E73: Units per month | F73: =F57 -> 168
A74: Monthly Profit | B74: =N57 -> 56.752 | E74: Months | F74: 10
F75: =+F74*F73 -> 1680 | G75: Unts needed
E76: Number of vials (div by 300) | F76: =ROUNDUP((F75/300),0) -> 6
E77: $100 per vial | F77: =+F76*100 -> 600
E79: Average montly profit | F79: =+F77/10 -> 60
A87: What is the largest disocunt/Sale we can offer on Peptides? | G87: What is the largest disocunt/Sale we can offer on Peptides?
A88: Based on highest dosage: | G88: Based on FIRSTS MONTH
B90: Pt Price | C90: Cost | D90: Profit | H90: Pt Price | I90: Cost | J90: Profit
A91: 0 | B91: =K57 -> 95 | C91: =J57 -> 38.248 | D91: =+B91-C91 -> 56.752 | G91: 0 | H91: =K33 -> 71 | I91: =J33 -> 32.336 | J91: =+H91-I91 -> 38.664
A92: 0.1 | B92: =0.9*B91 -> 85.5 | C92: =C91 -> 38.248 | D92: =+B92-C92 -> 47.252 | G92: 0.1 | H92: =0.9*H91 -> 63.9 | I92: =I91 -> 32.336 | J92: =+H92-I92 -> 31.564
A93: 0.15 | B93: =+B91*0.85 -> 80.75 | C93: =C92 -> 38.248 | D93: =+B93-C93 -> 42.502 | G93: 0.15 | H93: =+H91*0.85 -> 60.35 | I93: =I92 -> 32.336 | J93: =+H93-I93 -> 28.014
A94: 0.2 | B94: =0.8*B91 -> 76 | C94: =C93 -> 38.248 | D94: =+B94-C94 -> 37.752 | G94: 0.2 | H94: =0.8*H91 -> 56.8 | I94: =I93 -> 32.336 | J94: =+H94-I94 -> 24.464
A95: 0.25 | B95: =0.75*B91 -> 71.25 | C95: =C94 -> 38.248 | D95: =+B95-C95 -> 33.002 | G95: 0.25 | H95: =0.755*H91 -> 53.605 | I95: =I94 -> 32.336 | J95: =+H95-I95 -> 21.269

Sheet KLOW 80
A1: KLOW 80mg | O1: Daily
B2: ='Pep Costs'!B32 -> 125 | C2: cost | O2: Every Other Day
B3: 3.3 | C3: BAC | O3: Weekly
B4: 15 | C4: (30) Pen Needles, Cartridges, Alcohol Prep | F4: Add per vial | G4: Reg Price
B5: =SUM(B2:B4) -> 143.3 | F5: 100 | G5: =+F5+B5 -> 243.3
A7: Per Unit | B7: =+B5/300 -> 0.47766667 | F7: Per Unit | G7: =+G5/300 -> 0.811
A13: CUSTOM PROTOCOL | K13: Reg Price
H14: =ROUNDUP(F20,0) -> 308 | I14: Units | J14: =+B7*F20 -> 147.12133 | K14: =+F20*G7 -> 249.788
B15: Frequency of Injection | C15: mcg | D15: Units per Injections | E15: # of Injections | F15: Units Needed | H15: 1 | I15: Pen | J15: =+H15*45 -> 45 | K15: 45
A16: Week | B16: Daily | D16: 7 | E16: =IF(B16="Daily",7, IF(B16="Weekly",1, IF(B16="Every Other Day",4,""))) -> 7 | F16: =+D16*E16 -> 49 | H16: =IF(E20>=25, E20+2, E20+1) -> 30 | I16: Pen Needles
A17: Week | B17: Daily | D17: 7 | E17: =IF(B17="Daily",7, IF(B17="Weekly",1, IF(B17="Every Other Day",4,""))) -> 7 | F17: =+D17*E17 -> 49 | H17: =ROUNDUP(F21,0) -> 2 | I17: Cartridges
A18: Week | B18: Daily | D18: 15 | E18: =IF(B18="Daily",7, IF(B18="Weekly",1, IF(B18="Every Other Day",4,""))) -> 7 | F18: =+D18*E18 -> 105 | H18: =H16 -> 30 | I18: Alochol Prep
A19: Week | B19: Daily | D19: 15 | E19: =IF(B19="Daily",7, IF(B19="Weekly",1, IF(B19="Every Other Day",4,""))) -> 7 | F19: =+D19*E19 -> 105 | H19: 0 | I19: Case | J19: =H19*3.65 -> 0
E20: =SUM(E16:E19) -> 28 | F20: =SUM(F16:F19) -> 308 | J20: =SUM(J14:J19) -> 192.12133 | K20: =ROUNDUP(SUM(K14:K19),0) -> 295 | M20: Profit | N20: =+K20-J20 -> 102.87867
E21: Number of Cartridges needed | F21: =+F20/300 -> 1.0266667 | I21: Per Unit | J21: =+J20/H14 -> 0.62377056 | K21: =+K20/H14 -> 0.95779221
K26: Reg Price
H27: =ROUNDUP(F33,0) -> 308 | I27: Units | J27: =F33*B7 -> 147.12133 | K27: =+F33*G7 -> 249.788
A28: Month 1 | B28: Frequency of Injection | C28: mcg | D28: Units per Injections | E28: # of Injections | F28: Units Needed | H28: 0 | I28: Pen | J28: =+H28*45 -> 0 | K28: =H28*85 -> 0
A29: Week 1 | B29: Daily | C29: 250 | D29: 7 | E29: =IF(B29="Daily",7, IF(B29="Weekly",1, IF(B29="Every Other Day",4,""))) -> 7 | F29: =+D29*E29 -> 49 | H29: =IF(E33>=25, E33+2, E33+1) -> 30 | I29: Pen Needles
A30: Week 2 | B30: Daily | C30: 250 | D30: 7 | E30: =IF(B30="Daily",7, IF(B30="Weekly",1, IF(B30="Every Other Day",4,""))) -> 7 | F30: =+D30*E30 -> 49 | H30: =ROUNDUP(F34,0) -> 2 | I30: Cartridges
A31: Week 3 | B31: Daily | C31: 500 | D31: 15 | E31: =IF(B31="Daily",7, IF(B31="Weekly",1, IF(B31="Every Other Day",4,""))) -> 7 | F31: =+D31*E31 -> 105 | H31: =H29 -> 30 | I31: Alochol Prep
A32: Week 4 | B32: Daily | C32: 500 | D32: 15 | E32: =IF(B32="Daily",7, IF(B32="Weekly",1, IF(B32="Every Other Day",4,""))) -> 7 | F32: =+D32*E32 -> 105 | H32: 1 | I32: Case | J32: =H32*3.65 -> 3.65
E33: =SUM(E29:E32) -> 28 | F33: =SUM(F29:F32) -> 308 | J33: =SUM(J27:J32) -> 150.77133 | K33: =ROUNDUP(SUM(K27:K32),0) -> 250 | M33: Profit | N33: =+K33-J33 -> 99.228667
E34: Number of Cartridges needed | F34: =+F33/300 -> 1.0266667 | I34: Per Unit | J34: =+J33/H27 -> 0.48951732 | K34: =+K33/H27 -> 0.81168831
K38: Reg Price
H39: =ROUNDUP(F45,0) -> 616 | I39: Units | J39: =+B7*F45 -> 294.24267 | K39: =+F45*G7 -> 499.576
A40: Month 2 | B40: Frequency of Injection | C40: mcg | D40: Units per Injections | E40: # of Injections | F40: Units Needed | H40: 0 | I40: Pen | J40: =+H40*45 -> 0 | K40: =+H40*85 -> 0
A41: Week 5 | B41: Daily | C41: 750 | D41: 22 | E41: =IF(B41="Daily",7, IF(B41="Weekly",1, IF(B41="Every Other Day",4,""))) -> 7 | F41: =+D41*E41 -> 154 | H41: =IF(E45>=25, E45+2, E45+1) -> 30 | I41: Pen Needles
A42: Week 6 | B42: Daily | C42: 750 | D42: 22 | E42: =IF(B42="Daily",7, IF(B42="Weekly",1, IF(B42="Every Other Day",4,""))) -> 7 | F42: =+D42*E42 -> 154 | H42: =ROUNDUP(F46,0) -> 3 | I42: Cartridges
A43: Week 7 | B43: Daily | C43: 750 | D43: 22 | E43: =IF(B43="Daily",7, IF(B43="Weekly",1, IF(B43="Every Other Day",4,""))) -> 7 | F43: =+D43*E43 -> 154 | H43: =H41 -> 30 | I43: Alochol Prep
A44: Week 8 | B44: Daily | C44: 750 | D44: 22 | E44: =IF(B44="Daily",7, IF(B44="Weekly",1, IF(B44="Every Other Day",4,""))) -> 7 | F44: =+D44*E44 -> 154 | H44: 0 | I44: Case | J44: =H44*3.65 -> 0
E45: =SUM(E41:E44) -> 28 | F45: =SUM(F41:F44) -> 616 | J45: =SUM(J39:J44) -> 294.24267 | K45: =ROUNDUP(SUM(K39:K44),0) -> 500 | M45: Profit | N45: =+K45-J45 -> 205.75733
E46: Number of Cartridges needed | F46: =+F45/300 -> 2.0533333 | I46: Per Unit | J46: =+J45/H39 -> 0.47766667 | K46: =+K45/H39 -> 0.81168831
K50: Reg Price
H51: =ROUNDUP(F57,0) -> 420 | I51: Units | J51: =+B7*F57 -> 200.62 | K51: =+F57*G7 -> 340.62
A52: Month 3 | B52: Frequency of Injection | C52: mcg | D52: Units per Injections | E52: # of Injections | F52: Units Needed | H52: 0 | I52: Pen | J52: =+H52*45 -> 0 | K52: =+H52*85 -> 0
A53: Week 9 | B53: Daily | C53: 500 | D53: 15 | E53: =IF(B53="Daily",7, IF(B53="Weekly",1, IF(B53="Every Other Day",4,""))) -> 7 | F53: =+D53*E53 -> 105 | H53: =IF(E57>=25, E57+2, E57+1) -> 30 | I53: Pen Needles
A54: Week 10 | B54: Daily | C54: 500 | D54: 15 | E54: =IF(B54="Daily",7, IF(B54="Weekly",1, IF(B54="Every Other Day",4,""))) -> 7 | F54: =+D54*E54 -> 105 | H54: =ROUNDUP(F58,0) -> 2 | I54: Cartridges
A55: Week 11 | B55: Daily | C55: 500 | D55: 15 | E55: =IF(B55="Daily",7, IF(B55="Weekly",1, IF(B55="Every Other Day",4,""))) -> 7 | F55: =+D55*E55 -> 105 | H55: =H53 -> 30 | I55: Alochol Prep
A56: Week 12 | B56: Daily | C56: 500 | D56: 15 | E56: =IF(B56="Daily",7, IF(B56="Weekly",1, IF(B56="Every Other Day",4,""))) -> 7 | F56: =+D56*E56 -> 105 | H56: 0 | I56: Case | J56: =H56*3.65 -> 0
E57: =SUM(E53:E56) -> 28 | F57: =SUM(F53:F56) -> 420 | J57: =SUM(J51:J56) -> 200.62 | K57: =ROUNDUP(SUM(K51:K56),0) -> 341 | M57: Profit | N57: =+K57-J57 -> 140.38
E58: Number of Cartridges needed | F58: =+F57/300 -> 1.4 | I58: Per Unit | J58: =+J57/H51 -> 0.47766667 | K58: =+K57/H51 -> 0.81190476
A62: Month 4 | B62: The patient needs to have a conversation with Unruh as they will most likely take this month OFF.
A63: Week 13-16
A73: Over 10 months
D74: Sell the bottle?
A75: If we sell exactly what the need: | D75: how many vials do you need for 10 months?
E76: Units per month | F76: =F57 -> 420
A77: Monthly Profit | B77: =N57 -> 140.38 | E77: Months | F77: 10
F78: =+F77*F76 -> 4200 | G78: Unts needed
E79: Number of vials (div by 300) | F79: =ROUNDUP((F78/300),0) -> 14
E80: $100 per vial | F80: =+F79*100 -> 1400
E82: Average montly profit | F82: =+F80/10 -> 140
A90: What is the largest disocunt/Sale we can offer on Peptides? | H90: What is the largest disocunt/Sale we can offer on Peptides?
A91: Based on highest dosage: | H91: Based on FIRSTS MONTH
B93: Pt Price | C93: Cost | D93: Profit | I93: Pt Price | J93: Cost | K93: Profit
A94: 0 | B94: =K57 -> 341 | C94: =J57 -> 200.62 | D94: =+B94-C94 -> 140.38 | H94: 0 | I94: =K33 -> 250 | J94: =J33 -> 150.77133 | K94: =+I94-J94 -> 99.228667
A95: 0.1 | B95: =0.9*B94 -> 306.9 | C95: =C94 -> 200.62 | D95: =+B95-C95 -> 106.28 | H95: 0.1 | I95: =0.9*I94 -> 225 | J95: =J94 -> 150.77133 | K95: =+I95-J95 -> 74.228667
A96: 0.15 | B96: =+B94*0.85 -> 289.85 | C96: =C95 -> 200.62 | D96: =+B96-C96 -> 89.23 | H96: 0.15 | I96: =+I94*0.85 -> 212.5 | J96: =J95 -> 150.77133 | K96: =+I96-J96 -> 61.728667
A97: 0.2 | B97: =0.8*B94 -> 272.8 | C97: =C96 -> 200.62 | D97: =+B97-C97 -> 72.18 | H97: 0.2 | I97: =0.8*I94 -> 200 | J97: =J96 -> 150.77133 | K97: =+I97-J97 -> 49.228667
A98: 0.25 | B98: =0.75*B94 -> 255.75 | C98: =C97 -> 200.62 | D98: =+B98-C98 -> 55.13 | H98: 0.25 | I98: =0.755*I94 -> 188.75 | J98: =J97 -> 150.77133 | K98: =+I98-J98 -> 37.978667

Sheet MotsC 10
A1: MOTS-C 10mg | O1: Daily
B2: ='Pep Costs'!B36 -> 45 | C2: cost | O2: Every Other Day
B3: 3.3 | C3: BAC | O3: Weekly
B4: 15 | C4: (30) Pen Needles, Cartridges, Alcohol Prep | F4: Add per vial | G4: Reg Price
B5: =SUM(B2:B4) -> 63.3 | F5: 100 | G5: =+F5+B5 -> 163.3
A7: Per Unit | B7: =+B5/300 -> 0.211 | F7: Per Unit | G7: =+G5/300 -> 0.54433333
A13: CUSTOM PROTOCOL
K14: Reg Price
H15: =ROUNDUP(F21,0) -> 162 | I15: Units | J15: =+B7*F21 -> 34.182 | K15: =+F21*G7 -> 88.182
B16: Frequency of Injection | C16: mcg | D16: Units per Injections | E16: # of Injections | F16: Units Needed | H16: 0 | I16: Pen | J16: =+H16*45 -> 0 | K16: =+H16*85 -> 0 | L16: <<they probably already have one
A17: Week | B17: Daily | D17: 6 | E17: =IF(B17="Daily",7, IF(B17="Weekly",1, IF(B17="Every Other Day",4,""))) -> 7 | F17: =+D17*E17 -> 42 | H17: =IF(E21>=25, E21+2, E21+1) -> 20 | I17: Pen Needles
A18: Week | B18: Every Other Day | D18: 6 | E18: =IF(B18="Daily",7, IF(B18="Weekly",1, IF(B18="Every Other Day",4,""))) -> 4 | F18: =+D18*E18 -> 24 | H18: =ROUNDUP(F22,0) -> 1 | I18: Cartridges
A19: Week | B19: Daily | D19: 12 | E19: =IF(B19="Daily",7, IF(B19="Weekly",1, IF(B19="Every Other Day",4,""))) -> 7 | F19: =+D19*E19 -> 84 | H19: =H17 -> 20 | I19: Alochol Prep
A20: Week | B20: Weekly | D20: 12 | E20: =IF(B20="Daily",7, IF(B20="Weekly",1, IF(B20="Every Other Day",4,""))) -> 1 | F20: =+D20*E20 -> 12 | H20: 0 | I20: Case | J20: =H20*3.65 -> 0
E21: =SUM(E17:E20) -> 19 | F21: =SUM(F17:F20) -> 162 | J21: =SUM(J15:J20) -> 34.182 | K21: =ROUNDUP(SUM(K15:K20),0) -> 89 | M21: Profit | N21: =+K21-J21 -> 54.818
E22: Number of Cartridges needed | F22: =+F21/300 -> 0.54 | I22: Per Unit | J22: =+J21/H15 -> 0.211 | K22: =+K21/H15 -> 0.54938272
I28: Profit | K28: =+K21-G69 -> 89
K29: Reg Price
H30: =ROUNDUP(F36,0) -> 252 | I30: Units | J30: =F36*B7 -> 53.172 | K30: =+F36*G7 -> 137.172
A31: Month 1 | B31: Frequency of Injection | C31: mcg | D31: Units per Injections | E31: # of Injections | F31: Units Needed | H31: 0 | I31: Pen | J31: =+H31*45 -> 0 | K31: =H31*85 -> 0 | L31: <<they probably already have one
A32: Week 1 | B32: Daily | C32: 200 | D32: 6 | E32: =IF(B32="Daily",7, IF(B32="Weekly",1, IF(B32="Every Other Day",4,""))) -> 7 | F32: =+D32*E32 -> 42 | H32: =IF(E36>=25, E36+2, E36+1) -> 30 | I32: Pen Needles
A33: Week 2 | B33: Daily | C33: 200 | D33: 6 | E33: =IF(B33="Daily",7, IF(B33="Weekly",1, IF(B33="Every Other Day",4,""))) -> 7 | F33: =+D33*E33 -> 42 | H33: =ROUNDUP(F37,0) -> 1 | I33: Cartridges
A34: Week 3 | B34: Daily | C34: 400 | D34: 12 | E34: =IF(B34="Daily",7, IF(B34="Weekly",1, IF(B34="Every Other Day",4,""))) -> 7 | F34: =+D34*E34 -> 84 | H34: =H32 -> 30 | I34: Alochol Prep
A35: Week 4 | B35: Daily | C35: 400 | D35: 12 | E35: =IF(B35="Daily",7, IF(B35="Weekly",1, IF(B35="Every Other Day",4,""))) -> 7 | F35: =+D35*E35 -> 84 | H35: 1 | I35: Case | J35: =H35*3.65 -> 3.65
E36: =SUM(E32:E35) -> 28 | F36: =SUM(F32:F35) -> 252 | J36: =SUM(J30:J35) -> 56.822 | K36: =ROUNDUP(SUM(K30:K35),0) -> 138 | M36: Profit | N36: =+K36-J36 -> 81.178
E37: Number of Cartridges needed | F37: =+F36/300 -> 0.84 | I37: Per Unit | J37: =+J36/H30 -> 0.22548413 | K37: =+K36/H30 -> 0.54761905
K41: Reg Price
H42: =ROUNDUP(F48,0) -> 588 | I42: Units | J42: =+B7*F48 -> 124.068 | K42: =+F48*G7 -> 320.068
A43: Month 2 | B43: Frequency of Injection | C43: mcg | D43: Units per Injections | E43: # of Injections | F43: Units Needed | H43: 0 | I43: Pen | J43: =+H43*45 -> 0 | K43: =+H43*85 -> 0
A44: Week 5 | B44: Daily | C44: 600 | D44: 18 | E44: =IF(B44="Daily",7, IF(B44="Weekly",1, IF(B44="Every Other Day",4,""))) -> 7 | F44: =+D44*E44 -> 126 | H44: =IF(E48>=25, E48+2, E48+1) -> 30 | I44: Pen Needles
A45: Week 6 | B45: Daily | C45: 600 | D45: 18 | E45: =IF(B45="Daily",7, IF(B45="Weekly",1, IF(B45="Every Other Day",4,""))) -> 7 | F45: =+D45*E45 -> 126 | G45: =+F36+F44+F45 -> 504 | H45: =ROUNDUP(F49,0) -> 2 | I45: Cartridges
A46: Week 7 | B46: Daily | C46: 800 | D46: 24 | E46: =IF(B46="Daily",7, IF(B46="Weekly",1, IF(B46="Every Other Day",4,""))) -> 7 | F46: =+D46*E46 -> 168 | G46: =+G45+F46 -> 672 | H46: =H44 -> 30 | I46: Alochol Prep
A47: Week 8 | B47: Daily | C47: 800 | D47: 24 | E47: =IF(B47="Daily",7, IF(B47="Weekly",1, IF(B47="Every Other Day",4,""))) -> 7 | F47: =+D47*E47 -> 168 | H47: 0 | I47: Case | J47: =H47*3.65 -> 0
E48: =SUM(E44:E47) -> 28 | F48: =SUM(F44:F47) -> 588 | J48: =SUM(J42:J47) -> 124.068 | K48: =ROUNDUP(SUM(K42:K47),0) -> 321 | M48: Profit | N48: =+K48-J48 -> 196.932
E49: Number of Cartridges needed | F49: =+F48/300 -> 1.96 | I49: Per Unit | J49: =+J48/H42 -> 0.211 | K49: =+K48/H42 -> 0.54591837
K53: Reg Price
H54: =ROUNDUP(F60,0) -> 840 | I54: Units | J54: =+B7*F60 -> 177.24 | K54: =+F60*G7 -> 457.24
A55: Month 3 | B55: Frequency of Injection | C55: mcg | D55: Units per Injections | E55: # of Injections | F55: Units Needed | H55: 0 | I55: Pen | J55: =+H55*45 -> 0 | K55: =+H55*85 -> 0
A56: Week 9 | B56: Daily | C56: 1000 | D56: 30 | E56: =IF(B56="Daily",7, IF(B56="Weekly",1, IF(B56="Every Other Day",4,""))) -> 7 | F56: =+D56*E56 -> 210 | H56: =IF(E60>=25, E60+2, E60+1) -> 30 | I56: Pen Needles
A57: Week 10 | B57: Daily | C57: 1000 | D57: 30 | E57: =IF(B57="Daily",7, IF(B57="Weekly",1, IF(B57="Every Other Day",4,""))) -> 7 | F57: =+D57*E57 -> 210 | H57: =ROUNDUP(F61,0) -> 3 | I57: Cartridges
A58: Week 11 | B58: Daily | C58: 1000 | D58: 30 | E58: =IF(B58="Daily",7, IF(B58="Weekly",1, IF(B58="Every Other Day",4,""))) -> 7 | F58: =+D58*E58 -> 210 | H58: =H56 -> 30 | I58: Alochol Prep
A59: Week 12 | B59: Daily | C59: 1000 | D59: 30 | E59: =IF(B59="Daily",7, IF(B59="Weekly",1, IF(B59="Every Other Day",4,""))) -> 7 | F59: =+D59*E59 -> 210 | H59: 0 | I59: Case | J59: =H59*3.65 -> 0
E60: =SUM(E56:E59) -> 28 | F60: =SUM(F56:F59) -> 840 | J60: =SUM(J54:J59) -> 177.24 | K60: =ROUNDUP(SUM(K54:K59),0) -> 458 | M60: Profit | N60: =+K60-J60 -> 280.76
E61: Number of Cartridges needed | F61: =+F60/300 -> 2.8 | I61: Per Unit | J61: =+J60/H54 -> 0.211 | K61: =+K60/H54 -> 0.5452381
A65: Month 4 | B65: The patient needs to have a conversation with Unruh as they will most likely take this month OFF.
A66: Week 13-16
A73: Over 10 months
D74: Sell the bottle?
A75: If we sell exactly what the need: | D75: how many vials do you need for 10 months?
E76: Units per month | F76: =F60 -> 840
A77: Monthly Profit | B77: =N60 -> 280.76 | E77: Months | F77: 10
F78: =+F77*F76 -> 8400 | G78: Unts needed
E79: Number of vials (div by 300) | F79: =ROUNDUP((F78/300),0) -> 28
E80: $100 per vial | F80: =+F79*100 -> 2800
E82: Average montly profit | F82: =+F80/10 -> 280
A91: What is the largest disocunt/Sale we can offer on Peptides? | H91: What is the largest disocunt/Sale we can offer on Peptides?
A92: Based on highest dosage: | H92: Based on FIRSTS MONTH
B94: Pt Price | C94: Cost | D94: Profit | I94: Pt Price | J94: Cost | K94: Profit
A95: 0 | B95: =K60 -> 458 | C95: =J60 -> 177.24 | D95: =+B95-C95 -> 280.76 | H95: 0 | I95: =K36 -> 138 | J95: =J36 -> 56.822 | K95: =+I95-J95 -> 81.178
A96: 0.1 | B96: =0.9*B95 -> 412.2 | C96: =C95 -> 177.24 | D96: =+B96-C96 -> 234.96 | H96: 0.1 | I96: =0.9*I95 -> 124.2 | J96: =J95 -> 56.822 | K96: =+I96-J96 -> 67.378
A97: 0.15 | B97: =+B95*0.85 -> 389.3 | C97: =C96 -> 177.24 | D97: =+B97-C97 -> 212.06 | H97: 0.15 | I97: =+I95*0.85 -> 117.3 | J97: =J96 -> 56.822 | K97: =+I97-J97 -> 60.478
A98: 0.2 | B98: =0.8*B95 -> 366.4 | C98: =C97 -> 177.24 | D98: =+B98-C98 -> 189.16 | H98: 0.2 | I98: =0.8*I95 -> 110.4 | J98: =J97 -> 56.822 | K98: =+I98-J98 -> 53.578
A99: 0.25 | B99: =0.75*B95 -> 343.5 | C99: =C98 -> 177.24 | D99: =+B99-C99 -> 166.26 | H99: 0.25 | I99: =0.755*I95 -> 104.19 | J99: =J98 -> 56.822 | K99: =+I99-J99 -> 47.368

Sheet NAD+ Acute
A1: NAD+ 1000mg (Acute) | O1: Daily
B2: ='Pep Costs'!B37 -> 75 | C2: cost | O2: Every Other Day
B3: 3.3 | C3: BAC | O3: Weekly
B4: 15 | C4: (30) Pen Needles, Cartridges, Alcohol Prep | F4: Add per vial | G4: Reg Price
B5: =SUM(B2:B4) -> 93.3 | F5: 100 | G5: =+F5+B5 -> 193.3
A7: Per Unit | B7: =+B5/300 -> 0.311 | F7: Per Unit | G7: =+G5/300 -> 0.64433333
A14: CUSTOM PROTOCOL | K14: Reg Price
H15: =ROUNDUP(F21,0) -> 285 | I15: Units | J15: =+B7*F21 -> 88.635 | K15: =+F21*G7 -> 183.635
B16: Frequency of Injection | C16: mcg | D16: Units per Injections | E16: # of Injections | F16: Units Needed | H16: 1 | I16: Pen | J16: =+H16*45 -> 45 | K16: =+H16*85 -> 85
A17: Week | B17: Daily | D17: 15 | E17: =IF(B17="Daily",7, IF(B17="Weekly",1, IF(B17="Every Other Day",4,""))) -> 7 | F17: =+D17*E17 -> 105 | H17: =IF(E21>=25, E21+2, E21+1) -> 20 | I17: Pen Needles
A18: Week | B18: Weekly | D18: 15 | E18: =IF(B18="Daily",7, IF(B18="Weekly",1, IF(B18="Every Other Day",4,""))) -> 1 | F18: =+D18*E18 -> 15 | H18: =ROUNDUP(F22,0) -> 1 | I18: Cartridges
A19: Week | B19: Every Other Day | D19: 15 | E19: =IF(B19="Daily",7, IF(B19="Weekly",1, IF(B19="Every Other Day",4,""))) -> 4 | F19: =+D19*E19 -> 60 | H19: =H17 -> 20 | I19: Alochol Prep
A20: Week | B20: Daily | D20: 15 | E20: =IF(B20="Daily",7, IF(B20="Weekly",1, IF(B20="Every Other Day",4,""))) -> 7 | F20: =+D20*E20 -> 105 | H20: 0 | I20: Case | J20: =H20*3.65 -> 0
E21: =SUM(E17:E20) -> 19 | F21: =SUM(F17:F20) -> 285 | J21: =SUM(J15:J20) -> 133.635 | K21: =ROUNDUP(SUM(K15:K20),0) -> 269 | M21: Profit | N21: =+K21-J21 -> 135.365
E22: Number of Cartridges needed | F22: =+F21/300 -> 0.95 | I22: Per Unit | J22: =+J21/H15 -> 0.46889474 | K22: =+K21/H15 -> 0.94385965
K29: Reg Price
H30: =ROUNDUP(F36,0) -> 679 | I30: Units | J30: =F36*B7 -> 211.169 | K30: =+F36*G7 -> 437.50233
A31: Month 1 | B31: Frequency of Injection | C31: mcg | D31: Units per Injections | E31: # of Injections | F31: Units Needed | H31: 1 | I31: Pen | J31: =+H31*45 -> 45 | K31: =H31*85 -> 85
A32: Week 1 | B32: Daily | C32: 50 | D32: 15 | E32: =IF(B32="Daily",7, IF(B32="Weekly",1, IF(B32="Every Other Day",4,""))) -> 7 | F32: =+D32*E32 -> 105 | H32: =IF(E36>=25, E36+2, E36+1) -> 30 | I32: Pen Needles
A33: Week 2 | B33: Daily | C33: 75 | D33: 22 | E33: =IF(B33="Daily",7, IF(B33="Weekly",1, IF(B33="Every Other Day",4,""))) -> 7 | F33: =+D33*E33 -> 154 | H33: =ROUNDUP(F37,0) -> 3 | I33: Cartridges
A34: Week 3 | B34: Daily | C34: 100 | D34: 30 | E34: =IF(B34="Daily",7, IF(B34="Weekly",1, IF(B34="Every Other Day",4,""))) -> 7 | F34: =+D34*E34 -> 210 | H34: =H32 -> 30 | I34: Alochol Prep
A35: Week 4 | B35: Daily | C35: 100 | D35: 30 | E35: =IF(B35="Daily",7, IF(B35="Weekly",1, IF(B35="Every Other Day",4,""))) -> 7 | F35: =+D35*E35 -> 210 | H35: 1 | I35: Case | J35: =H35*3.65 -> 3.65
E36: =SUM(E32:E35) -> 28 | F36: =SUM(F32:F35) -> 679 | J36: =SUM(J30:J35) -> 259.819 | K36: =ROUNDUP(SUM(K30:K35),0) -> 523 | M36: Profit | N36: =+K36-J36 -> 263.181
E37: Number of Cartridges needed | F37: =+F36/300 -> 2.2633333 | I37: Per Unit | J37: =+J36/H30 -> 0.38264948 | K37: =+K36/H30 -> 0.77025037
A41: Peptide Dosages only have a 4 week protocol | K41: Reg Price
H42: =ROUNDUP(F48,0) -> 840 | I42: Units | J42: =+B7*F48 -> 261.24 | K42: =+F48*G7 -> 541.24
A43: Month 2 | B43: Frequency of Injection | C43: mcg | D43: Units per Injections | E43: # of Injections | F43: Units Needed | H43: 0 | I43: Pen | J43: =+H43*45 -> 0 | K43: =+H43*85 -> 0
A44: Week 5 | B44: Daily | C44: 100 | D44: 30 | E44: =IF(B44="Daily",7, IF(B44="Weekly",1, IF(B44="Every Other Day",4,""))) -> 7 | F44: =+D44*E44 -> 210 | H44: =IF(E48>=25, E48+2, E48+1) -> 30 | I44: Pen Needles
A45: Week 6 | B45: Daily | C45: 100 | D45: 30 | E45: =IF(B45="Daily",7, IF(B45="Weekly",1, IF(B45="Every Other Day",4,""))) -> 7 | F45: =+D45*E45 -> 210 | H45: =ROUNDUP(F49,0) -> 3 | I45: Cartridges
A46: Week 7 | B46: Daily | C46: 100 | D46: 30 | E46: =IF(B46="Daily",7, IF(B46="Weekly",1, IF(B46="Every Other Day",4,""))) -> 7 | F46: =+D46*E46 -> 210 | H46: =H44 -> 30 | I46: Alochol Prep
A47: Week 8 | B47: Daily | C47: 100 | D47: 30 | E47: =IF(B47="Daily",7, IF(B47="Weekly",1, IF(B47="Every Other Day",4,""))) -> 7 | F47: =+D47*E47 -> 210 | H47: 0 | I47: Case | J47: =H47*3.65 -> 0
E48: =SUM(E44:E47) -> 28 | F48: =SUM(F44:F47) -> 840 | J48: =SUM(J42:J47) -> 261.24 | K48: =ROUNDUP(SUM(K42:K47),0) -> 542 | M48: Profit | N48: =+K48-J48 -> 280.76
E49: Number of Cartridges needed | F49: =+F48/300 -> 2.8 | I49: Per Unit | J49: =+J48/H42 -> 0.311 | K49: =+K48/H42 -> 0.6452381
K53: Reg Price
H54: =ROUNDUP(F60,0) -> 840 | I54: Units | J54: =+B7*F60 -> 261.24 | K54: =+F60*G7 -> 541.24
A55: Month 3 | B55: Frequency of Injection | C55: mcg | D55: Units per Injections | E55: # of Injections | F55: Units Needed | H55: 0 | I55: Pen | J55: =+H55*45 -> 0 | K55: =+H55*85 -> 0
A56: Week 9 | B56: Daily | C56: 100 | D56: 30 | E56: =IF(B56="Daily",7, IF(B56="Weekly",1, IF(B56="Every Other Day",4,""))) -> 7 | F56: =+D56*E56 -> 210 | H56: =IF(E60>=25, E60+2, E60+1) -> 30 | I56: Pen Needles
A57: Week 10 | B57: Daily | C57: 100 | D57: 30 | E57: =IF(B57="Daily",7, IF(B57="Weekly",1, IF(B57="Every Other Day",4,""))) -> 7 | F57: =+D57*E57 -> 210 | H57: =ROUNDUP(F61,0) -> 3 | I57: Cartridges
A58: Week 11 | B58: Daily | C58: 100 | D58: 30 | E58: =IF(B58="Daily",7, IF(B58="Weekly",1, IF(B58="Every Other Day",4,""))) -> 7 | F58: =+D58*E58 -> 210 | H58: =H56 -> 30 | I58: Alochol Prep
A59: Week 12 | B59: Daily | C59: 100 | D59: 30 | E59: =IF(B59="Daily",7, IF(B59="Weekly",1, IF(B59="Every Other Day",4,""))) -> 7 | F59: =+D59*E59 -> 210 | H59: 0 | I59: Case | J59: =H59*3.65 -> 0
E60: =SUM(E56:E59) -> 28 | F60: =SUM(F56:F59) -> 840 | J60: =SUM(J54:J59) -> 261.24 | K60: =ROUNDUP(SUM(K54:K59),0) -> 542 | M60: Profit | N60: =+K60-J60 -> 280.76
E61: Number of Cartridges needed | F61: =+F60/300 -> 2.8 | I61: Per Unit | J61: =+J60/H54 -> 0.311 | K61: =+K60/H54 -> 0.6452381
A65: Month 4 | B65: The patient needs to have a conversation with Unruh as they will most likely take this month OFF.
A66: Week 13-16
A73: Over 10 months
D74: Sell the bottle?
A75: If we sell exactly what the need: | D75: how many vials do you need for 10 months?
E76: Units per month | F76: =F60 -> 840
A77: Monthly Profit | B77: =N60 -> 280.76 | E77: Months | F77: 10
F78: =+F77*F76 -> 8400 | G78: Unts needed
E79: Number of vials (div by 300) | F79: =ROUNDUP((F78/300),0) -> 28
E80: $100 per vial | F80: =+F79*100 -> 2800
E82: Average montly profit | F82: =+F80/10 -> 280
A89: What is the largest disocunt/Sale we can offer on Peptides? | H89: What is the largest disocunt/Sale we can offer on Peptides?
A90: Based on highest dosage: | H90: Based on FIRSTS MONTH
B92: Pt Price | C92: Cost | D92: Profit | I92: Pt Price | J92: Cost | K92: Profit
A93: 0 | B93: =K60 -> 542 | C93: =J60 -> 261.24 | D93: =+B93-C93 -> 280.76 | H93: 0 | I93: =K36 -> 523 | J93: =J36 -> 259.819 | K93: =+I93-J93 -> 263.181
A94: 0.1 | B94: =0.9*B93 -> 487.8 | C94: =C93 -> 261.24 | D94: =+B94-C94 -> 226.56 | H94: 0.1 | I94: =0.9*I93 -> 470.7 | J94: =J93 -> 259.819 | K94: =+I94-J94 -> 210.881
A95: 0.15 | B95: =+B93*0.85 -> 460.7 | C95: =C94 -> 261.24 | D95: =+B95-C95 -> 199.46 | H95: 0.15 | I95: =+I93*0.85 -> 444.55 | J95: =J94 -> 259.819 | K95: =+I95-J95 -> 184.731
A96: 0.2 | B96: =0.8*B93 -> 433.6 | C96: =C95 -> 261.24 | D96: =+B96-C96 -> 172.36 | H96: 0.2 | I96: =0.8*I93 -> 418.4 | J96: =J95 -> 259.819 | K96: =+I96-J96 -> 158.581
A97: 0.25 | B97: =0.75*B93 -> 406.5 | C97: =C96 -> 261.24 | D97: =+B97-C97 -> 145.26 | H97: 0.25 | I97: =0.755*I93 -> 394.865 | J97: =J96 -> 259.819 | K97: =+I97-J97 -> 135.046

Sheet NAD semiAct
A1: NAD+ 1000mg (Semi-Acute) | O1: Daily
B2: ='Pep Costs'!B37 -> 75 | C2: cost | O2: Every Other Day
B3: 3.3 | C3: BAC | E3: Per Vial | O3: Weekly
B4: 15 | C4: (30) Pen Needles, Cartridges, Alcohol Prep | F4: Add per vial | G4: Reg Price
B5: =SUM(B2:B4) -> 93.3 | F5: 100 | G5: =+F5+B5 -> 193.3
A7: Per Unit | B7: =+B5/300 -> 0.311 | F7: Per Unit | G7: =+G5/300 -> 0.64433333
K12: Reg Price
H13: =ROUNDUP(F19,0) -> 390 | I13: Units | J13: =+B7*F19 -> 121.29 | K13: =+F19*G7 -> 251.29
A14: Month 1 | B14: Frequency of Injection | C14: mcg | D14: Units per Injections | E14: # of Injections | F14: Units Needed | H14: 0 | I14: Pen | J14: =+H14*45 -> 0 | K14: =+H14*85 -> 0
A15: Week 1 | B15: Every Other Day | C15: 50 | D15: 15 | E15: =IF(B15="Daily",7, IF(B15="Weekly",1, IF(B15="Every Other Day",4,""))) -> 4 | F15: =+D15*E15 -> 60 | H15: =IF(E19>=25, E19+2, E19+1) -> 17 | I15: Pen Needles | J15: =0.25*H15 -> 4.25
A16: Week 2 | B16: Every Other Day | C16: 75 | D16: 22.5 | E16: =IF(B16="Daily",7, IF(B16="Weekly",1, IF(B16="Every Other Day",4,""))) -> 4 | F16: =+D16*E16 -> 90 | H16: =ROUNDUP(F20,0) -> 2 | I16: Cartridges | J16: =+H16*0.8 -> 1.6
A17: Week 3 | B17: Every Other Day | C17: 100 | D17: 30 | E17: =IF(B17="Daily",7, IF(B17="Weekly",1, IF(B17="Every Other Day",4,""))) -> 4 | F17: =+D17*E17 -> 120 | H17: =H15 -> 17 | I17: Alochol Prep | J17: =(5/100)*H17 -> 0.85
A18: Week 4 | B18: Every Other Day | C18: 100 | D18: 30 | E18: =IF(B18="Daily",7, IF(B18="Weekly",1, IF(B18="Every Other Day",4,""))) -> 4 | F18: =+D18*E18 -> 120 | H18: 1 | I18: Case | J18: =H18*3.65 -> 3.65
E19: =SUM(E15:E18) -> 16 | F19: =SUM(F15:F18) -> 390 | J19: =SUM(J13:J18) -> 131.64 | K19: =ROUNDUP(SUM(K13:K18),0) -> 252 | M19: Profit | N19: =+K19-J19 -> 120.36
E20: Number of Cartridges needed | F20: =+F19/300 -> 1.3 | I20: Per Unit | J20: =+J19/H13 -> 0.33753846 | K20: =+K19/H13 -> 0.64615385
K24: Reg Price
H25: =ROUNDUP(F31,0) -> 480 | I25: Units | J25: =+B7*F31 -> 149.28 | K25: =+F31*G7 -> 309.28
A26: Month 2 | B26: Frequency of Injection | C26: mcg | D26: Units per Injections | E26: # of Injections | F26: Units Needed | H26: 0 | I26: Pen | J26: =+H26*45 -> 0 | K26: =+H26*85 -> 0
A27: Week 5 | B27: Every Other Day | C27: 100 | D27: 30 | E27: =IF(B27="Daily",7, IF(B27="Weekly",1, IF(B27="Every Other Day",4,""))) -> 4 | F27: =+D27*E27 -> 120 | H27: =IF(E31>=25, E31+2, E31+1) -> 17 | I27: Pen Needles | J27: =0.25*H27 -> 4.25
A28: Week 6 | B28: Every Other Day | C28: 100 | D28: 30 | E28: =IF(B28="Daily",7, IF(B28="Weekly",1, IF(B28="Every Other Day",4,""))) -> 4 | F28: =+D28*E28 -> 120 | H28: =ROUNDUP(F32,0) -> 2 | I28: Cartridges | J28: =+H28*0.8 -> 1.6
A29: Week 7 | B29: Every Other Day | C29: 100 | D29: 30 | E29: =IF(B29="Daily",7, IF(B29="Weekly",1, IF(B29="Every Other Day",4,""))) -> 4 | F29: =+D29*E29 -> 120 | H29: =H27 -> 17 | I29: Alochol Prep | J29: =(5/100)*H29 -> 0.85
A30: Week 8 | B30: Every Other Day | C30: 100 | D30: 30 | E30: =IF(B30="Daily",7, IF(B30="Weekly",1, IF(B30="Every Other Day",4,""))) -> 4 | F30: =+D30*E30 -> 120 | H30: 0 | I30: Case | J30: =H30*3.65 -> 0
E31: =SUM(E27:E30) -> 16 | F31: =SUM(F27:F30) -> 480 | J31: =SUM(J25:J30) -> 155.98 | K31: =ROUNDUP(SUM(K25:K30),0) -> 310 | M31: Profit | N31: =+K31-J31 -> 154.02
E32: Number of Cartridges needed | F32: =+F31/300 -> 1.6 | I32: Per Unit | J32: =+J31/H25 -> 0.32495833 | K32: =+K31/H25 -> 0.64583333
K36: Reg Price
H37: =ROUNDUP(F43,0) -> 480 | I37: Units | J37: =+B7*F43 -> 149.28 | K37: =+F43*G7 -> 309.28
A38: Month 3 | B38: Frequency of Injection | C38: mcg | D38: Units per Injections | E38: # of Injections | F38: Units Needed | H38: 0 | I38: Pen | J38: =+H38*45 -> 0 | K38: =+H38*85 -> 0
A39: Week 9 | B39: Every Other Day | C39: 100 | D39: 30 | E39: =IF(B39="Daily",7, IF(B39="Weekly",1, IF(B39="Every Other Day",4,""))) -> 4 | F39: =+D39*E39 -> 120 | H39: =IF(E43>=25, E43+2, E43+1) -> 17 | I39: Pen Needles | J39: =0.25*H39 -> 4.25
A40: Week 10 | B40: Every Other Day | C40: 100 | D40: 30 | E40: =IF(B40="Daily",7, IF(B40="Weekly",1, IF(B40="Every Other Day",4,""))) -> 4 | F40: =+D40*E40 -> 120 | H40: =ROUNDUP(F44,0) -> 2 | I40: Cartridges | J40: =+H40*0.8 -> 1.6
A41: Week 11 | B41: Every Other Day | C41: 100 | D41: 30 | E41: =IF(B41="Daily",7, IF(B41="Weekly",1, IF(B41="Every Other Day",4,""))) -> 4 | F41: =+D41*E41 -> 120 | H41: =H39 -> 17 | I41: Alochol Prep | J41: =(5/100)*H41 -> 0.85
A42: Week 12 | B42: Every Other Day | C42: 100 | D42: 30 | E42: =IF(B42="Daily",7, IF(B42="Weekly",1, IF(B42="Every Other Day",4,""))) -> 4 | F42: =+D42*E42 -> 120 | H42: 0 | I42: Case | J42: =H42*3.65 -> 0
E43: =SUM(E39:E42) -> 16 | F43: =SUM(F39:F42) -> 480 | J43: =SUM(J37:J42) -> 155.98 | K43: =ROUNDUP(SUM(K37:K42),0) -> 310 | M43: Profit | N43: =+K43-J43 -> 154.02
E44: Number of Cartridges needed | F44: =+F43/300 -> 1.6 | I44: Per Unit | J44: =+J43/H37 -> 0.32495833 | K44: =+K43/H37 -> 0.64583333
A48: Month 4 | B48: The patient needs to have a conversation with Unruh as they will most likely take this month OFF.
A49: Week 13-16
A56: Over 10 months
D57: Sell the bottle?
A58: If we sell exactly what the need: | D58: how many vials do you need for 10 months?
E59: Units per month | F59: =F43 -> 480
A60: Monthly Profit | B60: =N43 -> 154.02 | E60: Months | F60: 10
F61: =+F60*F59 -> 4800 | G61: Unts needed
E62: Number of vials (div by 300) | F62: =ROUNDUP((F61/300),0) -> 16
E63: $100 per vial | F63: =+F62*100 -> 1600
E65: Average montly profit | F65: =+F63/10 -> 160
A74: What is the largest disocunt/Sale we can offer on Peptides? | I74: What is the largest disocunt/Sale we can offer on Peptides?
A75: Based on highest dosage: | I75: Based on FIRSTS MONTH
B77: Pt Price | C77: Cost | D77: Profit | J77: Pt Price | K77: Cost | L77: Profit
A78: 0 | B78: =K43 -> 310 | C78: =J43 -> 155.98 | D78: =+B78-C78 -> 154.02 | I78: 0 | J78: =K19 -> 252 | K78: =J19 -> 131.64 | L78: =+J78-K78 -> 120.36
A79: 0.1 | B79: =0.9*B78 -> 279 | C79: =C78 -> 155.98 | D79: =+B79-C79 -> 123.02 | I79: 0.1 | J79: =0.9*J78 -> 226.8 | K79: =K78 -> 131.64 | L79: =+J79-K79 -> 95.16
A80: 0.15 | B80: =+B78*0.85 -> 263.5 | C80: =C79 -> 155.98 | D80: =+B80-C80 -> 107.52 | I80: 0.15 | J80: =+J78*0.85 -> 214.2 | K80: =K79 -> 131.64 | L80: =+J80-K80 -> 82.56
A81: 0.2 | B81: =0.8*B78 -> 248 | C81: =C80 -> 155.98 | D81: =+B81-C81 -> 92.02 | I81: 0.2 | J81: =0.8*J78 -> 201.6 | K81: =K80 -> 131.64 | L81: =+J81-K81 -> 69.96
A82: 0.25 | B82: =0.75*B78 -> 232.5 | C82: =C81 -> 155.98 | D82: =+B82-C82 -> 76.52 | I82: 0.25 | J82: =0.755*J78 -> 190.26 | K82: =K81 -> 131.64 | L82: =+J82-K82 -> 58.62

Sheet PT-141 10mg
A1: PT-141 10mg
B2: 55 | C2: cost
B3: 3.3 | C3: BAC | F3: Add per vial | G3: Reg Price
B4: =SUM(B2:B3) -> 58.3 | F4: 100 | G4: =+F4+B4 -> 158.3
A6: Per Unit | B6: =+B4/300 -> 0.19433333 | F6: Per Unit | G6: =+G4/300 -> 0.52766667
A13: CUSTOM PROTOCOL
K14: Reg Price
B15: Number of Syringes | C15: mcg | D15: Units per Injections | E15: # of Injections | F15: Units Needed | H15: =ROUNDUP(F20,0) -> 75 | I15: Units | J15: =+B6*F20 -> 14.575 | K15: =+F20*G7 -> 0
I16: Pen | J16: n/a | K16: =+H16*85 -> 0
B17: 5 | D17: 15 | E17: =B17 -> 5 | F17: =+D17*E17 -> 75 | H17: =E20 -> 5 | I17: Syringe | J17: =+H17*0.24 -> 1.2
H18: =E20 -> 5 | I18: Alochol Prep | J18: =0.05*H18 -> 0.25
H19: 0 | I19: Case | J19: =H19*3.65 -> 0
E20: =SUM(E16:E19) -> 5 | F20: =SUM(F16:F19) -> 75 | J20: =SUM(J15:J19) -> 16.025 | K20: =ROUNDUP(SUM(K15:K19),0) -> 0 | N20: =+K20-J20 -> -16.025 | O20: Profit per syringe
I21: Per Unit | J21: =+J20/H15 -> 0.21366667 | K21: =+K20/H15 -> 0
A27: Month 1 | B27: Frequency of Injection | C27: mcg | D27: Units per Injections | E27: # of Injections | F27: Units Needed | K27: Reg Price
A28: Week 1-4 | B28: Weekly | C28: 500 | D28: 15 | E28: 1 | F28: =+D28*E28 -> 15 | H28: =ROUNDUP(F32,0) -> 15 | I28: Units | J28: =+B6*F32 -> 2.915 | K28: =+F32*G7 -> 0
H29: =E32 -> 1 | I29: Syringe | J29: =H29*0.24 -> 0.24
H30: =H29 -> 1 | I30: Alochol Prep | J30: =+H30*0.05 -> 0.05
H31: 0 | I31: Case | J31: =H31*3.65 -> 0
E32: =SUM(E28:E31) -> 1 | F32: =SUM(F28:F31) -> 15 | J32: =SUM(J28:J31) -> 3.205 | K32: 10 | L32: PER SYRINGE | N32: =+K32-J32 -> 6.795 | O32: Profit per syringe
I33: Per Unit | J33: =+J32/H28 -> 0.21366667 | K33: =+K32/H28 -> 0.66666667
A37: Month 2 | B37: Frequency of Injection | C37: mcg | D37: Units per Injections | E37: # of Injections | F37: Units Needed | K37: Reg Price
A38: Week 5-8 | B38: Weekly | C38: 500 | D38: 15 | E38: 1 | F38: =+D38*E38 -> 15 | H38: =ROUNDUP(F42,0) -> 15 | I38: Units | J38: =+B16*F42 -> 0 | K38: =+F42*G17 -> 0
H39: =E42 -> 1 | I39: Syringe | J39: =H39*0.24 -> 0.24
H40: =H39 -> 1 | I40: Alochol Prep | J40: =+H40*0.05 -> 0.05
H41: 0 | I41: Case | J41: =H41*3.65 -> 0
E42: =SUM(E38:E41) -> 1 | F42: =SUM(F38:F41) -> 15 | J42: =SUM(J38:J41) -> 0.29 | K42: 10 | L42: PER SYRINGE | N42: =+K42-J42 -> 9.71 | O42: Profit per syringe
I43: Per Unit | J43: =+J42/H38 -> 0.019333333 | K43: =+K42/H38 -> 0.66666667
A47: Month 3 | B47: Frequency of Injection | C47: mcg | D47: Units per Injections | E47: # of Injections | F47: Units Needed | K47: Reg Price
A48: Week 9-12 | B48: Weekly | C48: 1000 | D48: 30 | E48: =IF(B48="Daily",7, IF(B48="Weekly",1, IF(B48="Every Other Day",4,""))) -> 1 | F48: =+D48*E48 -> 30 | H48: =ROUNDUP(F52,0) -> 30 | I48: Units | J48: =+B6*F52 -> 5.83 | K48: =+F52*G7 -> 0
H49: =E52 -> 1 | I49: Syringe | J49: =H49*0.24 -> 0.24
H50: =E52 -> 1 | I50: Alochol Prep | J50: =+H50*0.05 -> 0.05
H51: 0 | I51: Case | J51: =H51*3.65 -> 0
E52: =SUM(E48:E51) -> 1 | F52: =SUM(F48:F51) -> 30 | J52: =SUM(J48:J51) -> 6.12 | K52: =K32*2 -> 20 | L52: PER SYRINGE | N52: =+K52-J52 -> 13.88 | O52: Profit per syringe
I53: Per Unit | J53: =+J52/H48 -> 0.204 | K53: =+K52/H48 -> 0.66666667
A59: Month 4 | B59: Frequency of Injection | C59: mcg | D59: Units per Injections | E59: # of Injections | F59: Units Needed | K59: Reg Price
A60: Week 13-16 | B60: Weekly | C60: 1500 | D60: 45 | E60: =IF(B60="Daily",7, IF(B60="Weekly",1, IF(B60="Every Other Day",4,""))) -> 1 | F60: =+D60*E60 -> 45 | H60: =ROUNDUP(F64,0) -> 45 | I60: Units | J60: =+B6*F64 -> 8.745 | K60: =+F64*G7 -> 0
H61: =ROUNDUP(F65,0) -> 1 | I61: Syringe | J61: =+H61*0.24 -> 0.24 | K61: 2
H62: =E64 -> 1 | I62: Alochol Prep | J62: =H62*0.05 -> 0.05
H63: 0 | I63: Case | J63: =H63*3.65 -> 0
E64: =SUM(E60:E63) -> 1 | F64: =SUM(F60:F63) -> 45 | J64: =SUM(J60:J63) -> 9.035 | K64: =K32*3 -> 30 | L64: PER SYRINGE | N64: =+K64-J64 -> 20.965 | O64: Profit per syringe
E65: Number of Cartridges needed | F65: =+F64/300 -> 0.15 | I65: Per Unit | J65: =+J64/H60 -> 0.20077778 | K65: =+K64/H60 -> 0.66666667
A69: Month 5 | B69: The patient needs to have a conversation with Unruh as they will most likely take this month OFF.
A70: Week 13-16

Sheet Tesam 10
A1: Tesamorelin 10mg | O1: Daily
B2: ='Pep Costs'!B51 -> 75 | C2: cost | O2: Every Other Day
B3: 3.3 | C3: BAC | O3: Weekly
B4: 15 | C4: Needles, cartrdiges, Alcohol Prep | F4: Add per vial | G4: Reg Price
B5: =SUM(B2:B4) -> 93.3 | F5: 40 | G5: =+F5+B5 -> 133.3
A7: Per Unit | B7: =+B5/300 -> 0.311 | F7: Per Unit | G7: =+G5/300 -> 0.44433333
A13: CUSTOM PROTOCOL | K13: Reg Price
H14: =ROUNDUP(F20,0) -> 330 | I14: Units | J14: =+B7*F20 -> 102.63 | K14: =+F20*G7 -> 146.63
B15: Frequency of Injection | C15: mcg | D15: Units per Injections | E15: # of Injections | F15: Units Needed | I15: Pen | J15: =+H15*45 -> 0 | K15: =+H15*85 -> 0
A16: Week 5 | B16: Daily | C16: 500mc | D16: 15 | E16: =IF(B16="Daily",7, IF(B16="Weekly",1, IF(B16="Every Other Day",4,""))) -> 7 | F16: =+D16*E16 -> 105 | H16: =IF(E20>=25, E20+2, E20+1) -> 23 | I16: Pen Needles | J16: =0.25*H16 -> 5.75
A17: Week 5 | B17: Daily | D17: 15 | E17: 4 | F17: =+D17*E17 -> 60 | H17: =ROUNDUP(F21,0) -> 2 | I17: Cartridges | J17: =+H17*0.8 -> 1.6
A18: Week 5 | B18: Daily | D18: 15 | E18: =IF(B18="Daily",7, IF(B18="Weekly",1, IF(B18="Every Other Day",4,""))) -> 7 | F18: =+D18*E18 -> 105 | H18: =H16 -> 23 | I18: Alochol Prep | J18: =(5/100)*H18 -> 1.15
A19: Week 5 | B19: Daily | D19: 15 | E19: 4 | F19: =+D19*E19 -> 60 | H19: 0 | I19: Case | J19: =H19*3.65 -> 0
E20: =SUM(E16:E19) -> 22 | F20: =SUM(F16:F19) -> 330 | J20: =SUM(J14:J19) -> 111.13 | K20: =ROUNDUP(SUM(K14:K19),0) -> 147 | M20: Profit | N20: =+K20-J20 -> 35.87
E21: Number of Cartridges needed | F21: =+F20/300 -> 1.1 | I21: Per Unit | J21: =+J20/H14 -> 0.33675758 | K21: =+K20/H14 -> 0.44545455
K26: Reg Price
H27: =ROUNDUP(F33,0) -> 1260 | I27: Units | J27: =+B7*F33 -> 391.86 | K27: =F33*G7 -> 559.86
A28: Month 1 | B28: Frequency of Injection | C28: mcg | D28: Units per Injections | E28: # of Injections | F28: Units Needed | H28: 0 | I28: Pen | J28: =+H28*45 -> 0 | K28: =+H28*85 -> 0
A29: Week 1 | B29: Daily | C29: 1000 | D29: 30 | E29: =IF(B29="Daily",7, IF(B29="Weekly",1, IF(B29="Every Other Day",4,""))) -> 7 | F29: =+D29*E29 -> 210 | H29: =IF(E33>=25, E33+2, E33+1) -> 30 | I29: Pen Needles | J29: =0.25*H29 -> 7.5
A30: Week 2 | B30: Daily | C30: 1000 | D30: 30 | E30: =IF(B30="Daily",7, IF(B30="Weekly",1, IF(B30="Every Other Day",4,""))) -> 7 | F30: =+D30*E30 -> 210 | H30: =ROUNDUP(F34,0) -> 5 | I30: Cartridges | J30: =+H30*0.8 -> 4
A31: Week 3 | B31: Daily | C31: 2000 | D31: 60 | E31: =IF(B31="Daily",7, IF(B31="Weekly",1, IF(B31="Every Other Day",4,""))) -> 7 | F31: =+D31*E31 -> 420 | H31: =H29 -> 30 | I31: Alochol Prep | J31: =(5/100)*H31 -> 1.5
A32: Week 4 | B32: Daily | C32: 2000 | D32: 60 | E32: =IF(B32="Daily",7, IF(B32="Weekly",1, IF(B32="Every Other Day",4,""))) -> 7 | F32: =+D32*E32 -> 420 | H32: 1 | I32: Case | J32: =H32*3.65 -> 3.65
E33: =SUM(E29:E32) -> 28 | F33: =SUM(F29:F32) -> 1260 | J33: =SUM(J27:J32) -> 408.51 | K33: =ROUNDUP(SUM(K27:K32),0) -> 560 | M33: Profit | N33: =+K33-J33 -> 151.49
E34: Number of Cartridges needed | F34: =+F33/300 -> 4.2 | I34: Per Unit | J34: =+J33/H27 -> 0.32421429 | K34: =+K33/H27 -> 0.44444444
K38: Reg Price
H39: =ROUNDUP(F45,0) -> 1680 | I39: Units | J39: =+B7*F45 -> 522.48 | K39: =+F45*G7 -> 746.48
A40: Month 2 | B40: Frequency of Injection | C40: mcg | D40: Units per Injections | E40: # of Injections | F40: Units Needed | H40: 0 | I40: Pen | J40: =+H40*45 -> 0 | K40: =+H40*85 -> 0
A41: Week 5 | B41: Daily | C41: 2000 | D41: 60 | E41: =IF(B41="Daily",7, IF(B41="Weekly",1, IF(B41="Every Other Day",4,""))) -> 7 | F41: =+D41*E41 -> 420 | H41: =IF(E45>=25, E45+2, E45+1) -> 30 | I41: Pen Needles | J41: =0.25*H41 -> 7.5
A42: Week 6 | B42: Daily | C42: 2000 | D42: 60 | E42: =IF(B42="Daily",7, IF(B42="Weekly",1, IF(B42="Every Other Day",4,""))) -> 7 | F42: =+D42*E42 -> 420 | H42: =ROUNDUP(F46,0) -> 6 | I42: Cartridges | J42: =+H42*0.8 -> 4.8
A43: Week 7 | B43: Daily | C43: 2000 | D43: 60 | E43: =IF(B43="Daily",7, IF(B43="Weekly",1, IF(B43="Every Other Day",4,""))) -> 7 | F43: =+D43*E43 -> 420 | H43: =H41 -> 30 | I43: Alochol Prep | J43: =(5/100)*H43 -> 1.5
A44: Week 8 | B44: Daily | C44: 2000 | D44: 60 | E44: =IF(B44="Daily",7, IF(B44="Weekly",1, IF(B44="Every Other Day",4,""))) -> 7 | F44: =+D44*E44 -> 420 | H44: 0 | I44: Case | J44: =H44*3.65 -> 0
E45: =SUM(E41:E44) -> 28 | F45: =SUM(F41:F44) -> 1680 | J45: =SUM(J39:J44) -> 536.28 | K45: =ROUNDUP(SUM(K39:K44),0) -> 747 | M45: Profit | N45: =+K45-J45 -> 210.72
E46: Number of Cartridges needed | F46: =+F45/300 -> 5.6 | I46: Per Unit | J46: =+J45/H39 -> 0.31921429 | K46: =+K45/H39 -> 0.44464286
K50: Reg Price
H51: =ROUNDUP(F57,0) -> 1680 | I51: Units | J51: =+B7*F57 -> 522.48 | K51: =+F57*G7 -> 746.48
A52: Month 3 | B52: Frequency of Injection | C52: mcg | D52: Units per Injections | E52: # of Injections | F52: Units Needed | H52: 0 | I52: Pen | J52: =+H52*45 -> 0 | K52: =+H52*85 -> 0
A53: Week 9 | B53: Daily | C53: 2000 | D53: 60 | E53: =IF(B53="Daily",7, IF(B53="Weekly",1, IF(B53="Every Other Day",4,""))) -> 7 | F53: =+D53*E53 -> 420 | H53: =IF(E57>=25, E57+2, E57+1) -> 30 | I53: Pen Needles | J53: =0.25*H53 -> 7.5
A54: Week 10 | B54: Daily | C54: 2000 | D54: 60 | E54: =IF(B54="Daily",7, IF(B54="Weekly",1, IF(B54="Every Other Day",4,""))) -> 7 | F54: =+D54*E54 -> 420 | H54: =ROUNDUP(F58,0) -> 6 | I54: Cartridges | J54: =+H54*0.8 -> 4.8
A55: Week 11 | B55: Daily | C55: 2000 | D55: 60 | E55: =IF(B55="Daily",7, IF(B55="Weekly",1, IF(B55="Every Other Day",4,""))) -> 7 | F55: =+D55*E55 -> 420 | H55: =H53 -> 30 | I55: Alochol Prep | J55: =(5/100)*H55 -> 1.5
A56: Week 12 | B56: Daily | C56: 2000 | D56: 60 | E56: =IF(B56="Daily",7, IF(B56="Weekly",1, IF(B56="Every Other Day",4,""))) -> 7 | F56: =+D56*E56 -> 420 | H56: 0 | I56: Case | J56: =H56*3.65 -> 0
E57: =SUM(E53:E56) -> 28 | F57: =SUM(F53:F56) -> 1680 | J57: =SUM(J51:J56) -> 536.28 | K57: =ROUNDUP(SUM(K51:K56),0) -> 747 | M57: Profit | N57: =+K57-J57 -> 210.72
E58: Number of Cartridges needed | F58: =+F57/300 -> 5.6 | I58: Per Unit | J58: =+J57/H51 -> 0.31921429 | K58: =+K57/H51 -> 0.44464286
A62: Month 4 | B62: The patient needs to have a conversation with Unruh as they will most likely take this month OFF.
A70: Over 10 months
D71: Sell the bottle?
A72: If we sell exactly what the need: | D72: how many vials do you need for 10 months?
E73: Units per month | F73: =F45 -> 1680
A74: Monthly Profit | B74: =N45 -> 210.72 | E74: Months | F74: 10
F75: =+F74*F73 -> 16800 | G75: Unts needed
E76: Number of vials (div by 300) | F76: =ROUNDUP((F75/300),0) -> 56
E77: $100 per vial | F77: =+F76*F5 -> 2240
E79: Average montly profit | F79: =+F77/10 -> 224
A88: What is the largest disocunt/Sale we can offer on Peptides? | G88: What is the largest disocunt/Sale we can offer on Peptides?
A89: Based on highest dosage: | G89: Based on FIRSTS MONTH
B91: Pt Price | C91: Cost | D91: Profit | H91: Pt Price | I91: Cost | J91: Profit
A92: 0 | B92: =K45 -> 747 | C92: =J45 -> 536.28 | D92: =+B92-C92 -> 210.72 | G92: 0 | H92: =K33 -> 560 | I92: =J33 -> 408.51 | J92: =+H92-I92 -> 151.49
A93: 0.1 | B93: =0.9*B92 -> 672.3 | C93: =C92 -> 536.28 | D93: =+B93-C93 -> 136.02 | G93: 0.1 | H93: =0.9*H92 -> 504 | I93: =I92 -> 408.51 | J93: =+H93-I93 -> 95.49
A94: 0.15 | B94: =+B92*0.85 -> 634.95 | C94: =C93 -> 536.28 | D94: =+B94-C94 -> 98.67 | G94: 0.15 | H94: =+H92*0.85 -> 476 | I94: =I93 -> 408.51 | J94: =+H94-I94 -> 67.49
A95: 0.2 | B95: =0.8*B92 -> 597.6 | C95: =C94 -> 536.28 | D95: =+B95-C95 -> 61.32 | G95: 0.2 | H95: =0.8*H92 -> 448 | I95: =I94 -> 408.51 | J95: =+H95-I95 -> 39.49
A96: 0.25 | B96: =0.75*B92 -> 560.25 | C96: =C95 -> 536.28 | D96: =+B96-C96 -> 23.97 | G96: 0.25 | H96: =0.755*H92 -> 422.8 | I96: =I95 -> 408.51 | J96: =+H96-I96 -> 14.29

Sheet Keith Tesa
A1: Tesamorelin 10mg | O1: Daily
B2: ='Pep Costs'!B51 -> 75 | C2: cost | O2: Every Other Day
B3: 3.3 | C3: BAC | O3: Weekly
B4: 15 | C4: Needles, cartrdiges, Alcohol Prep | F4: Add per vial | G4: Reg Price
B5: =SUM(B2:B4) -> 93.3 | F5: 57 | G5: =+F5+B5 -> 150.3
N6: at2ml one bottle lasts 10 injections
A7: Per Unit | B7: =+B5/300 -> 0.311 | F7: Per Unit | G7: =+G5/300 -> 0.501 | N7: at 3ml same
A13: CUSTOM PROTOCOL | K13: Reg Price
H14: =ROUNDUP(F20,0) -> 0 | I14: Units | J14: =+B7*F20 -> 0 | K14: =+F20*G7 -> 0
B15: Frequency of Injection | C15: mcg | D15: Units per Injections | E15: # of Injections | F15: Units Needed | I15: Pen | J15: =+H15*45 -> 0 | K15: =+H15*85 -> 0
A16: Week 1 | E16: 5 | F16: =+D16*E16 -> 0 | H16: =IF(E20>=25, E20+2, E20+1) -> 21 | I16: Pen Needles | J16: =0.25*H16 -> 5.25
A17: Week 2 | E17: 5 | F17: =+D17*E17 -> 0 | H17: =ROUNDUP(F21,0) -> 0 | I17: Cartridges | J17: =+H17*0.8 -> 0
A18: Week 3 | E18: 5 | F18: =+D18*E18 -> 0 | H18: =H16 -> 21 | I18: Alochol Prep | J18: =(5/100)*H18 -> 1.05
A19: Week 4 | E19: 5 | F19: =+D19*E19 -> 0 | H19: 0 | I19: Case | J19: =H19*3.65 -> 0
E20: =SUM(E16:E19) -> 20 | F20: =SUM(F16:F19) -> 0 | J20: =SUM(J14:J19) -> 6.3 | K20: =ROUNDUP(SUM(K14:K19),0) -> 0 | M20: Profit | N20: =+K20-J20 -> -6.3
E21: Number of Cartridges needed | F21: =+F20/300 -> 0 | I21: Per Unit | J21: =+J20/H14 -> #DIV/0! | K21: =+K20/H14 -> #DIV/0!
K26: Reg Price
H27: =ROUNDUP(F33,0) -> 300 | I27: Units | J27: =+B7*F33 -> 93.3 | K27: =F33*G7 -> 150.3
A28: Month 1 | B28: Frequency of Injection | C28: mcg | D28: Units per Injections | E28: # of Injections | F28: Units Needed | H28: 0 | I28: Pen | J28: =+H28*45 -> 0 | K28: =+H28*85 -> 0 | N28: 0.1 | O28: =+K33*0.9 -> 270 | P28: =J33 -> 104.05 | Q28: =+O28-P28 -> 165.95
A29: Week 1 | B29: Daily | C29: 500mcg | D29: 15 | E29: 5 | F29: =+D29*E29 -> 75 | H29: =IF(E33>=25, E33+2, E33+1) -> 21 | I29: Pen Needles | J29: =0.25*H29 -> 5.25 | N29: 0.15 | O29: =0.85*K33 -> 255 | P29: =J33 -> 104.05 | Q29: =+O29-P29 -> 150.95
A30: Week 2 | B30: Daily | C30: 500mcg | D30: 15 | E30: 5 | F30: =+D30*E30 -> 75 | H30: =ROUNDUP(F34,0) -> 1 | I30: Cartridges | J30: =+H30*0.8 -> 0.8 | N30: 0.2 | O30: =0.8*K33 -> 240 | P30: =J33 -> 104.05 | Q30: =+O30-P30 -> 135.95
A31: Week 3 | B31: Daily | C31: 500mcg | D31: 15 | E31: 5 | F31: =+D31*E31 -> 75 | H31: =H29 -> 21 | I31: Alochol Prep | J31: =(5/100)*H31 -> 1.05 | N31: 0.25 | O31: =0.75*K33 -> 225 | P31: =J33 -> 104.05 | Q31: =+O31-P31 -> 120.95
A32: Week 4 | B32: Daily | C32: 500mcg | D32: 15 | E32: 5 | F32: =+D32*E32 -> 75 | H32: 1 | I32: Case | J32: =H32*3.65 -> 3.65
E33: =SUM(E29:E32) -> 20 | F33: =SUM(F29:F32) -> 300 | J33: =SUM(J27:J32) -> 104.05 | K33: 300 | M33: Profit | N33: =+K33-J33 -> 195.95
E34: Number of Cartridges needed | F34: =+F33/300 -> 1 | I34: Per Unit | J34: =+J33/H27 -> 0.34683333 | K34: =+K33/H27 -> 1
K37: Reg Price
H38: =ROUNDUP(F44,0) -> 600 | I38: Units | J38: =+B18*F44 -> 0 | K38: =F44*G18 -> 0
A39: Month 2 | B39: Frequency of Injection | C39: mcg | D39: Units per Injections | E39: # of Injections | F39: Units Needed | H39: 0 | I39: Pen | J39: =+H39*45 -> 0 | K39: =+H39*85 -> 0 | N39: 0.1 | O39: =+K44*0.9 -> 270 | P39: =J44 -> 11.55 | Q39: =+O39-P39 -> 258.45
A40: Week 5 | B40: Daily | C40: 1000mcg | D40: 30 | E40: 5 | F40: =+D40*E40 -> 150 | H40: =IF(E44>=25, E44+2, E44+1) -> 21 | I40: Pen Needles | J40: =0.25*H40 -> 5.25 | N40: 0.15 | O40: =0.85*K44 -> 255 | P40: =J44 -> 11.55 | Q40: =+O40-P40 -> 243.45
A41: Week 5 | B41: Daily | C41: 1000mcg | D41: 30 | E41: 5 | F41: =+D41*E41 -> 150 | H41: =ROUNDUP(F45,0) -> 2 | I41: Cartridges | J41: =+H41*0.8 -> 1.6 | N41: 0.2 | O41: =0.8*K44 -> 240 | P41: =J44 -> 11.55 | Q41: =+O41-P41 -> 228.45
A42: Week 7 | B42: Daily | C42: 1000mcg | D42: 30 | E42: 5 | F42: =+D42*E42 -> 150 | H42: =H40 -> 21 | I42: Alochol Prep | J42: =(5/100)*H42 -> 1.05 | N42: 0.25 | O42: =0.75*K44 -> 225 | P42: =J44 -> 11.55 | Q42: =+O42-P42 -> 213.45
A43: Week 8 | B43: Daily | C43: 1000mcg | D43: 30 | E43: 5 | F43: =+D43*E43 -> 150 | H43: 1 | I43: Case | J43: =H43*3.65 -> 3.65
E44: =SUM(E40:E43) -> 20 | F44: =SUM(F40:F43) -> 600 | J44: =SUM(J38:J43) -> 11.55 | K44: 300 | M44: Profit | N44: =+K44-J44 -> 288.45
E45: Number of Cartridges needed | F45: =+F44/300 -> 2 | I45: Per Unit | J45: =+J44/H38 -> 0.01925 | K45: =+K44/H38 -> 0.5
A49: Month 3-12+ is the same as Month 2
A59: Over 10 months
D60: Sell the bottle?
A61: If we sell exactly what the need: | D61: how many vials do you need for 10 months?
E62: Units per month | F62: =#REF! -> #REF!
A63: Monthly Profit | B63: =#REF! -> #REF! | E63: Months | F63: 10
F64: =+F63*F62 -> #REF! | G64: Unts needed
E65: Number of vials (div by 300) | F65: =ROUNDUP((F64/300),0) -> #REF!
E66: $100 per vial | F66: =+F65*F5 -> #REF!
E68: Average montly profit | F68: =+F66/10 -> #REF!
A77: What is the largest disocunt/Sale we can offer on Peptides? | G77: What is the largest disocunt/Sale we can offer on Peptides?
A78: Based on highest dosage: | G78: Based on FIRSTS MONTH
B80: Pt Price | C80: Cost | D80: Profit | H80: Pt Price | I80: Cost | J80: Profit
A81: 0 | B81: =#REF! -> #REF! | C81: =#REF! -> #REF! | D81: =+B81-C81 -> #REF! | G81: 0 | H81: =K33 -> 300 | I81: =J33 -> 104.05 | J81: =+H81-I81 -> 195.95
A82: 0.1 | B82: =0.9*B81 -> #REF! | C82: =C81 -> #REF! | D82: =+B82-C82 -> #REF! | G82: 0.1 | H82: =0.9*H81 -> 270 | I82: =I81 -> 104.05 | J82: =+H82-I82 -> 165.95
A83: 0.15 | B83: =+B81*0.85 -> #REF! | C83: =C82 -> #REF! | D83: =+B83-C83 -> #REF! | G83: 0.15 | H83: =+H81*0.85 -> 255 | I83: =I82 -> 104.05 | J83: =+H83-I83 -> 150.95
A84: 0.2 | B84: =0.8*B81 -> #REF! | C84: =C83 -> #REF! | D84: =+B84-C84 -> #REF! | G84: 0.2 | H84: =0.8*H81 -> 240 | I84: =I83 -> 104.05 | J84: =+H84-I84 -> 135.95
A85: 0.25 | B85: =0.75*B81 -> #REF! | C85: =C84 -> #REF! | D85: =+B85-C85 -> #REF! | G85: 0.25 | H85: =0.755*H81 -> 226.5 | I85: =I84 -> 104.05 | J85: =+H85-I85 -> 122.45

Sheet Tirz 30mg
A1: Tirzepatide 30mg | O1: Daily
B2: ='Pep Costs'!B55 -> 195 | C2: cost | O2: Every Other Day
B3: 3.3 | C3: BAC | O3: Weekly
B4: 5 | C4: 4 syringes, 4 alcohol prep | F4: Add per vial | G4: Reg Price
B5: =SUM(B2:B4) -> 203.3 | F5: 100 | G5: =+F5+B5 -> 303.3
A7: Per Unit | B7: =+B5/300 -> 0.67766667 | F7: Per Unit | G7: =+G5/300 -> 1.011
B11: Per Unruh TRZ 30mg is going to be a FLAT $350.00 per month for the first 4 months…up to a max of 100 Units per Week for one month.
A17: CUSTOM PROTOCOL
B19: Frequency of Injection | C19: mcg | D19: Units per Injections | E19: # of Injections | F19: Units Needed | K19: Reg Price
A20: Week | B20: Weekly | E20: 0 | F20: =+D20*E20 -> 0 | H20: =ROUNDUP(F24,0) -> 30 | I20: Units | J20: =B7*F24 -> 20.33 | K20: =+F24*G7 -> 30.33
A21: Week | B21: 3 per week | C21: 1000 | D21: 10 | E21: 3 | F21: =+D21*E21 -> 30 | H21: =E24 -> 3 | I21: Syringe | J21: =+H21*0.24 -> 0.72
A22: Week | B22: Weekly | E22: 0 | F22: =+D22*E22 -> 0 | H22: =E24 -> 3 | I22: Alochol Prep | J22: =0.05*H22 -> 0.15
A23: Week | B23: Weekly | E23: 0 | F23: =+D23*E23 -> 0 | H23: 0 | I23: Case | J23: =H23*3.65 -> 0
E24: =SUM(E20:E23) -> 3 | F24: =SUM(F20:F23) -> 30 | J24: =SUM(J20:J23) -> 21.2 | K24: =ROUNDUP(SUM(K20:K23),0) -> 31 | M24: Profit | N24: =+K24-J24 -> 9.8
I25: Per Unit | J25: =+J24/H20 -> 0.70666667 | K25: =+K24/H20 -> 1.0333333
A31: Month 1 | B31: Frequency of Injection | C31: mcg | D31: Units per Injections | E31: # of Injections | F31: Units Needed | K31: Reg Price
A32: Week 1 | B32: Weekly | D32: 25 | E32: =IF(B32="Daily",7, IF(B32="Weekly",1, IF(B32="Every Other Day",4,""))) -> 1 | F32: =+D32*E32 -> 25 | H32: =ROUNDUP(F36,0) -> 100 | I32: Units | J32: =+B7*F36 -> 67.766667 | K32: =F36*G7 -> 101.1
A33: Week 2 | B33: Weekly | D33: 25 | E33: =IF(B33="Daily",7, IF(B33="Weekly",1, IF(B33="Every Other Day",4,""))) -> 1 | F33: =+D33*E33 -> 25 | H33: =E36 -> 4 | I33: Syringe | J33: =H33*0.24 -> 0.96
A34: Week 3 | B34: Weekly | D34: 25 | E34: =IF(B34="Daily",7, IF(B34="Weekly",1, IF(B34="Every Other Day",4,""))) -> 1 | F34: =+D34*E34 -> 25 | H34: =H33 -> 4 | I34: Alochol Prep | J34: =+H34*0.05 -> 0.2
A35: Week 4 | B35: Weekly | D35: 25 | E35: =IF(B35="Daily",7, IF(B35="Weekly",1, IF(B35="Every Other Day",4,""))) -> 1 | F35: =+D35*E35 -> 25 | H35: 1 | I35: Case | J35: =H35*3.65 -> 3.65
E36: =SUM(E32:E35) -> 4 | F36: =SUM(F32:F35) -> 100 | J36: =SUM(J32:J35) -> 72.576667 | K36: 350 | M36: Profit | N36: =+K36-J36 -> 277.42333
I37: Per Unit | J37: =+J36/H32 -> 0.72576667 | K37: =+K36/H32 -> 3.5
A41: Month 2 | B41: Frequency of Injection | C41: mcg | D41: Units per Injections | E41: # of Injections | F41: Units Needed | K41: Reg Price
A42: Week 5 | B42: Weekly | D42: 50 | E42: =IF(B42="Daily",7, IF(B42="Weekly",1, IF(B42="Every Other Day",4,""))) -> 1 | F42: =+D42*E42 -> 50 | H42: =ROUNDUP(F46,0) -> 200 | I42: Units | J42: =+B7*F46 -> 135.53333 | K42: =+F46*G7 -> 202.2
A43: Week 6 | B43: Weekly | D43: 50 | E43: =IF(B43="Daily",7, IF(B43="Weekly",1, IF(B43="Every Other Day",4,""))) -> 1 | F43: =+D43*E43 -> 50 | H43: =E46 -> 4 | I43: Syringe | J43: =H43*0.24 -> 0.96
A44: Week 7 | B44: Weekly | D44: 50 | E44: =IF(B44="Daily",7, IF(B44="Weekly",1, IF(B44="Every Other Day",4,""))) -> 1 | F44: =+D44*E44 -> 50 | H44: =E46 -> 4 | I44: Alochol Prep | J44: =+H44*0.05 -> 0.2
A45: Week 8 | B45: Weekly | D45: 50 | E45: =IF(B45="Daily",7, IF(B45="Weekly",1, IF(B45="Every Other Day",4,""))) -> 1 | F45: =+D45*E45 -> 50 | H45: 0 | I45: Case | J45: =H45*3.65 -> 0
E46: =SUM(E42:E45) -> 4 | F46: =SUM(F42:F45) -> 200 | J46: =SUM(J42:J45) -> 136.69333 | K46: 350 | M46: Profit | N46: =+K46-J46 -> 213.30667
I47: Per Unit | J47: =+J46/H42 -> 0.68346667 | K47: =+K46/H42 -> 1.75
A51: Month 3 | B51: Frequency of Injection | C51: mcg | D51: Units per Injections | E51: # of Injections | F51: Units Needed | K51: Reg Price
A52: Week 9 | B52: Weekly | D52: 75 | E52: =IF(B52="Daily",7, IF(B52="Weekly",1, IF(B52="Every Other Day",4,""))) -> 1 | F52: =+D52*E52 -> 75 | H52: =ROUNDUP(F56,0) -> 300 | I52: Units | J52: =+B7*F56 -> 203.3 | K52: =+F56*G7 -> 303.3
A53: week 10 | B53: Weekly | D53: 75 | E53: =IF(B53="Daily",7, IF(B53="Weekly",1, IF(B53="Every Other Day",4,""))) -> 1 | F53: =+D53*E53 -> 75 | H53: =E56 -> 4 | I53: Syringe | J53: =+H53*0.24 -> 0.96
A54: Week 11 | B54: Weekly | D54: 75 | E54: =IF(B54="Daily",7, IF(B54="Weekly",1, IF(B54="Every Other Day",4,""))) -> 1 | F54: =+D54*E54 -> 75 | H54: =E56 -> 4 | I54: Alochol Prep | J54: =H54*0.05 -> 0.2
A55: Week 12 | B55: Weekly | D55: 75 | E55: =IF(B55="Daily",7, IF(B55="Weekly",1, IF(B55="Every Other Day",4,""))) -> 1 | F55: =+D55*E55 -> 75 | H55: 0 | I55: Case | J55: =H55*3.65 -> 0
E56: =SUM(E52:E55) -> 4 | F56: =SUM(F52:F55) -> 300 | J56: =SUM(J52:J55) -> 204.46 | K56: 350 | M56: Profit | N56: =+K56-J56 -> 145.54
E57: Number of Cartridges needed | F57: =+F56/300 -> 1 | I57: Per Unit | J57: =+J56/H52 -> 0.68153333 | K57: =+K56/H52 -> 1.1666667
A61: Month 4 | B61: Frequency of Injection | C61: mcg | D61: Units per Injections | E61: # of Injections | F61: Units Needed | K61: Reg Price
A62: Week 13 | B62: Weekly | C62: 1000mcg | D62: 100 | E62: =IF(B62="Daily",7, IF(B62="Weekly",1, IF(B62="Every Other Day",4,""))) -> 1 | F62: =+D62*E62 -> 100 | H62: =ROUNDUP(F66,0) -> 400 | I62: Units | J62: =F66*B7 -> 271.06667 | K62: =+F66*G7 -> 404.4
A63: Week 14 | B63: Weekly | D63: 100 | E63: =IF(B63="Daily",7, IF(B63="Weekly",1, IF(B63="Every Other Day",4,""))) -> 1 | F63: =+D63*E63 -> 100 | H63: =E66 -> 4 | I63: Syringe | J63: =+H63*0.24 -> 0.96
A64: Week 15 | B64: Weekly | D64: 100 | E64: =IF(B64="Daily",7, IF(B64="Weekly",1, IF(B64="Every Other Day",4,""))) -> 1 | F64: =+D64*E64 -> 100 | H64: =E66 -> 4 | I64: Alochol Prep | J64: =H64*0.05 -> 0.2
A65: Week 16 | B65: Weekly | D65: 100 | E65: =IF(B65="Daily",7, IF(B65="Weekly",1, IF(B65="Every Other Day",4,""))) -> 1 | F65: =+D65*E65 -> 100 | H65: 0 | I65: Case | J65: =H65*3.65 -> 0
E66: =SUM(E62:E65) -> 4 | F66: =SUM(F62:F65) -> 400 | J66: =SUM(J62:J65) -> 272.22667 | K66: 350 | M66: Profit | N66: =+K66-J66 -> 77.773333
E67: Number of Cartridges needed | F67: =+F66/300 -> 1.3333333 | I67: Per Unit | J67: =+J66/H62 -> 0.68056667 | K67: =+K66/H62 -> 0.875
A74: Over 10 months
D75: Sell the bottle?
A76: If we sell exactly what the need: | D76: how many vials do you need for 10 months?
E77: Units per month | F77: =F66 -> 400
A78: Monthly Profit | B78: =N66 -> 77.773333 | E78: Months | F78: 10
F79: =+F78*F77 -> 4000 | G79: Unts needed
E80: Number of vials (div by 300) | F80: =ROUNDUP((F79/300),0) -> 14
E81: $100 per vial | F81: =+F80*F5 -> 1400
E83: Average montly profit | F83: =+F81/10 -> 140
A93: What is the largest disocunt/Sale we can offer on Peptides? | I93: What is the largest disocunt/Sale we can offer on Peptides?
A94: Based on highest dosage: | I94: Based on FIRSTS MONTH
B96: Pt Price | C96: Cost | D96: Profit | J96: Pt Price | K96: Cost | L96: Profit
A97: 0 | B97: =K66 -> 350 | C97: =J66 -> 272.22667 | D97: =+B97-C97 -> 77.773333 | I97: 0 | J97: =K36 -> 350 | K97: =J36 -> 72.576667 | L97: =+J97-K97 -> 277.42333
A98: 0.1 | B98: =0.9*B97 -> 315 | C98: =C97 -> 272.22667 | D98: =+B98-C98 -> 42.773333 | I98: 0.1 | J98: =0.9*J97 -> 315 | K98: =K97 -> 72.576667 | L98: =+J98-K98 -> 242.42333
A99: 0.15 | B99: =+B97*0.85 -> 297.5 | C99: =C98 -> 272.22667 | D99: =+B99-C99 -> 25.273333 | I99: 0.15 | J99: =+J97*0.85 -> 297.5 | K99: =K98 -> 72.576667 | L99: =+J99-K99 -> 224.92333
A100: 0.2 | B100: =0.8*B97 -> 280 | C100: =C99 -> 272.22667 | D100: =+B100-C100 -> 7.7733333 | I100: 0.2 | J100: =0.8*J97 -> 280 | K100: =K99 -> 72.576667 | L100: =+J100-K100 -> 207.42333
A101: 0.25 | B101: =0.75*B97 -> 262.5 | C101: =C100 -> 272.22667 | D101: =+B101-C101 -> -9.7266667 | I101: 0.25 | J101: =0.755*J97 -> 264.25 | K101: =K100 -> 72.576667 | L101: =+J101-K101 -> 191.67333

Sheet Burkman SLOW
A1: Tirzepatide 30mg | O1: Daily
B2: ='Pep Costs'!B55 -> 195 | C2: cost | O2: Every Other Day
B3: 3.3 | C3: BAC | O3: Weekly
B4: 5 | C4: 4 syringes, 4 alcohol prep | F4: Add per vial | G4: Reg Price
B5: =SUM(B2:B4) -> 203.3 | F5: 100 | G5: =+F5+B5 -> 303.3
A7: Per Unit | B7: =+B5/300 -> 0.67766667 | F7: Per Unit | G7: =+G5/300 -> 1.011
B11: Per Unruh TRZ 30mg is going to be a FLAT $350.00 per month for the first 4 months…up to a max of 100 Units per Week for one month.
A17: Month 1 | B17: Frequency of Injection | C17: mcg | D17: Units per Injections | E17: # of Injections | F17: Units Needed | K17: Reg Price
A18: Week 1 | B18: Weekly | C18: 1.7mg-1700mcg | D18: 16 | E18: =IF(B18="Daily",7, IF(B18="Weekly",1, IF(B18="Every Other Day",4,""))) -> 1 | F18: =+D18*E18 -> 16 | H18: =ROUNDUP(F22,0) -> 64 | I18: Units | J18: =+B7*F22 -> 43.370667 | K18: =F22*G7 -> 64.704
A19: Week 2 | B19: Weekly | C19: 1.7mg-1700mcg | D19: 16 | E19: =IF(B19="Daily",7, IF(B19="Weekly",1, IF(B19="Every Other Day",4,""))) -> 1 | F19: =+D19*E19 -> 16 | H19: =E22 -> 4 | I19: Syringe | J19: =H19*0.24 -> 0.96
A20: Week 3 | B20: Weekly | C20: 3.3mg = 3300mcg | D20: 16 | E20: =IF(B20="Daily",7, IF(B20="Weekly",1, IF(B20="Every Other Day",4,""))) -> 1 | F20: =+D20*E20 -> 16 | H20: =H19 -> 4 | I20: Alochol Prep | J20: =+H20*0.05 -> 0.2
A21: Week 4 | B21: Weekly | C21: 3.3mg = 3300mcg | D21: 16 | E21: =IF(B21="Daily",7, IF(B21="Weekly",1, IF(B21="Every Other Day",4,""))) -> 1 | F21: =+D21*E21 -> 16 | H21: 1 | I21: Case | J21: =H21*3.65 -> 3.65
E22: =SUM(E18:E21) -> 4 | F22: =SUM(F18:F21) -> 64 | J22: =SUM(J18:J21) -> 48.180667 | K22: 350 | M22: Profit | N22: =+K22-J22 -> 301.81933
I23: Per Unit | J23: =+J22/H18 -> 0.75282292 | K23: =+K22/H18 -> 5.46875
A27: Month 2 | B27: Frequency of Injection | C27: mcg | D27: Units per Injections | E27: # of Injections | F27: Units Needed | K27: Reg Price
A28: Week 5 | B28: Weekly | C28: 4mg | D28: 40 | E28: =IF(B28="Daily",7, IF(B28="Weekly",1, IF(B28="Every Other Day",4,""))) -> 1 | F28: =+D28*E28 -> 40 | H28: =ROUNDUP(F32,0) -> 160 | I28: Units | J28: =+B7*F32 -> 108.42667 | K28: =+F32*G7 -> 161.76
A29: Week 6 | B29: Weekly | D29: 40 | E29: =IF(B29="Daily",7, IF(B29="Weekly",1, IF(B29="Every Other Day",4,""))) -> 1 | F29: =+D29*E29 -> 40 | H29: =E32 -> 4 | I29: Syringe | J29: =H29*0.24 -> 0.96
A30: Week 7 | B30: Weekly | D30: 40 | E30: =IF(B30="Daily",7, IF(B30="Weekly",1, IF(B30="Every Other Day",4,""))) -> 1 | F30: =+D30*E30 -> 40 | H30: =E32 -> 4 | I30: Alochol Prep | J30: =+H30*0.05 -> 0.2
A31: Week 8 | B31: Weekly | D31: 40 | E31: =IF(B31="Daily",7, IF(B31="Weekly",1, IF(B31="Every Other Day",4,""))) -> 1 | F31: =+D31*E31 -> 40 | H31: 0 | I31: Case | J31: =H31*3.65 -> 0
E32: =SUM(E28:E31) -> 4 | F32: =SUM(F28:F31) -> 160 | J32: =SUM(J28:J31) -> 109.58667 | K32: 350 | M32: Profit | N32: =+K32-J32 -> 240.41333
I33: Per Unit | J33: =+J32/H28 -> 0.68491667 | K33: =+K32/H28 -> 2.1875
A37: Month 3 | B37: Frequency of Injection | C37: mcg | D37: Units per Injections | E37: # of Injections | F37: Units Needed | K37: Reg Price
A38: Week 9 | B38: Weekly | C38: 5mg | D38: 50 | E38: =IF(B38="Daily",7, IF(B38="Weekly",1, IF(B38="Every Other Day",4,""))) -> 1 | F38: =+D38*E38 -> 50 | H38: =ROUNDUP(F42,0) -> 200 | I38: Units | J38: =+B7*F42 -> 135.53333 | K38: =+F42*G7 -> 202.2
A39: week 10 | B39: Weekly | D39: 50 | E39: =IF(B39="Daily",7, IF(B39="Weekly",1, IF(B39="Every Other Day",4,""))) -> 1 | F39: =+D39*E39 -> 50 | H39: =E42 -> 4 | I39: Syringe | J39: =+H39*0.24 -> 0.96
A40: Week 11 | B40: Weekly | D40: 50 | E40: =IF(B40="Daily",7, IF(B40="Weekly",1, IF(B40="Every Other Day",4,""))) -> 1 | F40: =+D40*E40 -> 50 | H40: =E42 -> 4 | I40: Alochol Prep | J40: =H40*0.05 -> 0.2
A41: Week 12 | B41: Weekly | D41: 50 | E41: =IF(B41="Daily",7, IF(B41="Weekly",1, IF(B41="Every Other Day",4,""))) -> 1 | F41: =+D41*E41 -> 50 | H41: 0 | I41: Case | J41: =H41*3.65 -> 0
E42: =SUM(E38:E41) -> 4 | F42: =SUM(F38:F41) -> 200 | J42: =SUM(J38:J41) -> 136.69333 | K42: 350 | M42: Profit | N42: =+K42-J42 -> 213.30667
E43: Number of Cartridges needed | F43: =+F42/300 -> 0.66666667 | I43: Per Unit | J43: =+J42/H38 -> 0.68346667 | K43: =+K42/H38 -> 1.75
A47: Month 4 | B47: Frequency of Injection | C47: mcg | D47: Units per Injections | E47: # of Injections | F47: Units Needed | K47: Reg Price
A48: Week 13 | B48: Weekly | C48: 6mg | D48: 60 | E48: =IF(B48="Daily",7, IF(B48="Weekly",1, IF(B48="Every Other Day",4,""))) -> 1 | F48: =+D48*E48 -> 60 | H48: =ROUNDUP(F52,0) -> 240 | I48: Units | J48: =F52*B7 -> 162.64 | K48: =+F52*G7 -> 242.64
A49: Week 14 | B49: Weekly | D49: 60 | E49: =IF(B49="Daily",7, IF(B49="Weekly",1, IF(B49="Every Other Day",4,""))) -> 1 | F49: =+D49*E49 -> 60 | H49: =E52 -> 4 | I49: Syringe | J49: =+H49*0.24 -> 0.96
A50: Week 15 | B50: Weekly | D50: 60 | E50: =IF(B50="Daily",7, IF(B50="Weekly",1, IF(B50="Every Other Day",4,""))) -> 1 | F50: =+D50*E50 -> 60 | H50: =E52 -> 4 | I50: Alochol Prep | J50: =H50*0.05 -> 0.2
A51: Week 16 | B51: Weekly | D51: 60 | E51: =IF(B51="Daily",7, IF(B51="Weekly",1, IF(B51="Every Other Day",4,""))) -> 1 | F51: =+D51*E51 -> 60 | H51: 0 | I51: Case | J51: =H51*3.65 -> 0
E52: =SUM(E48:E51) -> 4 | F52: =SUM(F48:F51) -> 240 | J52: =SUM(J48:J51) -> 163.8 | K52: 350 | M52: Profit | N52: =+K52-J52 -> 186.2
E53: Number of Cartridges needed | F53: =+F52/300 -> 0.8 | I53: Per Unit | J53: =+J52/H48 -> 0.6825 | K53: =+K52/H48 -> 1.4583333
A57: Month 5 | B57: Frequency of Injection | C57: mcg | D57: Units per Injections | E57: # of Injections | F57: Units Needed | K57: Reg Price
A58: Week 17 | B58: Weekly | C58: 7mg | D58: 70 | E58: =IF(B58="Daily",7, IF(B58="Weekly",1, IF(B58="Every Other Day",4,""))) -> 1 | F58: =+D58*E58 -> 70 | H58: =ROUNDUP(F62,0) -> 280 | I58: Units | J58: =F62*B7 -> 189.74667 | K58: =+F62*G7 -> 283.08
A59: Week 18 | B59: Weekly | D59: 70 | E59: =IF(B59="Daily",7, IF(B59="Weekly",1, IF(B59="Every Other Day",4,""))) -> 1 | F59: =+D59*E59 -> 70 | H59: =E62 -> 4 | I59: Syringe | J59: =+H59*0.24 -> 0.96
A60: Week 19 | B60: Weekly | D60: 70 | E60: =IF(B60="Daily",7, IF(B60="Weekly",1, IF(B60="Every Other Day",4,""))) -> 1 | F60: =+D60*E60 -> 70 | H60: =E62 -> 4 | I60: Alochol Prep | J60: =H60*0.05 -> 0.2
A61: Week 20 | B61: Weekly | D61: 70 | E61: =IF(B61="Daily",7, IF(B61="Weekly",1, IF(B61="Every Other Day",4,""))) -> 1 | F61: =+D61*E61 -> 70 | H61: 0 | I61: Case | J61: =H61*3.65 -> 0
E62: =SUM(E58:E61) -> 4 | F62: =SUM(F58:F61) -> 280 | J62: =SUM(J58:J61) -> 190.90667 | K62: 350 | M62: Profit | N62: =+K62-J62 -> 159.09333
E63: Number of Cartridges needed | F63: =+F62/300 -> 0.93333333 | I63: Per Unit | J63: =+J62/H58 -> 0.68180952 | K63: =+K62/H58 -> 1.25
A67: Month 6 | B67: Frequency of Injection | C67: mcg | D67: Units per Injections | E67: # of Injections | F67: Units Needed | K67: Reg Price
A68: Week 21 | B68: Weekly | C68: 8mg | D68: 80 | E68: =IF(B68="Daily",7, IF(B68="Weekly",1, IF(B68="Every Other Day",4,""))) -> 1 | F68: =+D68*E68 -> 80 | H68: =ROUNDUP(F72,0) -> 320 | I68: Units | J68: =F72*B7 -> 216.85333 | K68: =+F72*G7 -> 323.52
A69: Week 22 | B69: Weekly | D69: 80 | E69: =IF(B69="Daily",7, IF(B69="Weekly",1, IF(B69="Every Other Day",4,""))) -> 1 | F69: =+D69*E69 -> 80 | H69: =E72 -> 4 | I69: Syringe | J69: =+H69*0.24 -> 0.96
A70: Week 23 | B70: Weekly | D70: 80 | E70: =IF(B70="Daily",7, IF(B70="Weekly",1, IF(B70="Every Other Day",4,""))) -> 1 | F70: =+D70*E70 -> 80 | H70: =E72 -> 4 | I70: Alochol Prep | J70: =H70*0.05 -> 0.2
A71: Week 24 | B71: Weekly | D71: 80 | E71: =IF(B71="Daily",7, IF(B71="Weekly",1, IF(B71="Every Other Day",4,""))) -> 1 | F71: =+D71*E71 -> 80 | H71: 0 | I71: Case | J71: =H71*3.65 -> 0
E72: =SUM(E68:E71) -> 4 | F72: =SUM(F68:F71) -> 320 | J72: =SUM(J68:J71) -> 218.01333 | K72: 350 | M72: Profit | N72: =+K72-J72 -> 131.98667
E73: Number of Cartridges needed | F73: =+F72/300 -> 1.0666667 | I73: Per Unit | J73: =+J72/H68 -> 0.68129167 | K73: =+K72/H68 -> 1.09375
A77: Month 7 | B77: Frequency of Injection | C77: mcg | D77: Units per Injections | E77: # of Injections | F77: Units Needed | K77: Reg Price
A78: Week 25 | B78: Weekly | C78: 9mg | D78: 90 | E78: =IF(B78="Daily",7, IF(B78="Weekly",1, IF(B78="Every Other Day",4,""))) -> 1 | F78: =+D78*E78 -> 90 | H78: =ROUNDUP(F82,0) -> 360 | I78: Units | J78: =F82*B7 -> 243.96 | K78: =+F82*G7 -> 363.96
A79: Week 26 | B79: Weekly | D79: 90 | E79: =IF(B79="Daily",7, IF(B79="Weekly",1, IF(B79="Every Other Day",4,""))) -> 1 | F79: =+D79*E79 -> 90 | H79: =E82 -> 4 | I79: Syringe | J79: =+H79*0.24 -> 0.96
A80: Week 27 | B80: Weekly | D80: 90 | E80: =IF(B80="Daily",7, IF(B80="Weekly",1, IF(B80="Every Other Day",4,""))) -> 1 | F80: =+D80*E80 -> 90 | H80: =E82 -> 4 | I80: Alochol Prep | J80: =H80*0.05 -> 0.2
A81: Week 28 | B81: Weekly | D81: 90 | E81: =IF(B81="Daily",7, IF(B81="Weekly",1, IF(B81="Every Other Day",4,""))) -> 1 | F81: =+D81*E81 -> 90 | H81: 0 | I81: Case | J81: =H81*3.65 -> 0
E82: =SUM(E78:E81) -> 4 | F82: =SUM(F78:F81) -> 360 | J82: =SUM(J78:J81) -> 245.12 | K82: 350 | M82: Profit | N82: =+K82-J82 -> 104.88
E83: Number of Cartridges needed | F83: =+F82/300 -> 1.2 | I83: Per Unit | J83: =+J82/H78 -> 0.68088889 | K83: =+K82/H78 -> 0.97222222
A87: Month 8 | B87: Frequency of Injection | C87: mcg | D87: Units per Injections | E87: # of Injections | F87: Units Needed | K87: Reg Price
A88: Week 29 | B88: Weekly | C88: 10mg | D88: 100 | E88: =IF(B88="Daily",7, IF(B88="Weekly",1, IF(B88="Every Other Day",4,""))) -> 1 | F88: =+D88*E88 -> 100 | H88: =ROUNDUP(F92,0) -> 400 | I88: Units | J88: =F92*B7 -> 271.06667 | K88: =+F92*G7 -> 404.4
A89: Week 30 | B89: Weekly | D89: 100 | E89: =IF(B89="Daily",7, IF(B89="Weekly",1, IF(B89="Every Other Day",4,""))) -> 1 | F89: =+D89*E89 -> 100 | H89: =E92 -> 4 | I89: Syringe | J89: =+H89*0.24 -> 0.96
A90: Week 31 | B90: Weekly | D90: 100 | E90: =IF(B90="Daily",7, IF(B90="Weekly",1, IF(B90="Every Other Day",4,""))) -> 1 | F90: =+D90*E90 -> 100 | H90: =E92 -> 4 | I90: Alochol Prep | J90: =H90*0.05 -> 0.2
A91: Week 32 | B91: Weekly | D91: 100 | E91: =IF(B91="Daily",7, IF(B91="Weekly",1, IF(B91="Every Other Day",4,""))) -> 1 | F91: =+D91*E91 -> 100 | H91: 0 | I91: Case | J91: =H91*3.65 -> 0
E92: =SUM(E88:E91) -> 4 | F92: =SUM(F88:F91) -> 400 | J92: =SUM(J88:J91) -> 272.22667 | K92: 350 | M92: Profit | N92: =+K92-J92 -> 77.773333
E93: Number of Cartridges needed | F93: =+F92/300 -> 1.3333333 | I93: Per Unit | J93: =+J92/H88 -> 0.68056667 | K93: =+K92/H88 -> 0.875
A100: Over 10 months
D101: Sell the bottle?
A102: If we sell exactly what the need: | D102: how many vials do you need for 10 months?
E103: Units per month | F103: =F52 -> 240
A104: Monthly Profit | B104: =N52 -> 186.2 | E104: Months | F104: 10
F105: =+F104*F103 -> 2400 | G105: Unts needed
E106: Number of vials (div by 300) | F106: =ROUNDUP((F105/300),0) -> 8
E107: $100 per vial | F107: =+F106*F5 -> 800
E109: Average montly profit | F109: =+F107/10 -> 80
A119: What is the largest disocunt/Sale we can offer on Peptides? | I119: What is the largest disocunt/Sale we can offer on Peptides?
A120: Based on highest dosage: | I120: Based on FIRSTS MONTH
B122: Pt Price | C122: Cost | D122: Profit | J122: Pt Price | K122: Cost | L122: Profit
A123: 0 | B123: =K52 -> 350 | C123: =J52 -> 163.8 | D123: =+B123-C123 -> 186.2 | I123: 0 | J123: =K22 -> 350 | K123: =J22 -> 48.180667 | L123: =+J123-K123 -> 301.81933
A124: 0.1 | B124: =0.9*B123 -> 315 | C124: =C123 -> 163.8 | D124: =+B124-C124 -> 151.2 | I124: 0.1 | J124: =0.9*J123 -> 315 | K124: =K123 -> 48.180667 | L124: =+J124-K124 -> 266.81933
A125: 0.15 | B125: =+B123*0.85 -> 297.5 | C125: =C124 -> 163.8 | D125: =+B125-C125 -> 133.7 | I125: 0.15 | J125: =+J123*0.85 -> 297.5 | K125: =K124 -> 48.180667 | L125: =+J125-K125 -> 249.31933
A126: 0.2 | B126: =0.8*B123 -> 280 | C126: =C125 -> 163.8 | D126: =+B126-C126 -> 116.2 | I126: 0.2 | J126: =0.8*J123 -> 280 | K126: =K125 -> 48.180667 | L126: =+J126-K126 -> 231.81933
A127: 0.25 | B127: =0.75*B123 -> 262.5 | C127: =C126 -> 163.8 | D127: =+B127-C127 -> 98.7 | I127: 0.25 | J127: =0.755*J123 -> 264.25 | K127: =K126 -> 48.180667 | L127: =+J127-K127 -> 216.06933

Sheet TRZ DOWN
A1: Tirzepatide 30mg | O1: Daily
B2: ='Pep Costs'!B55 -> 195 | C2: cost | E2: (TITRATE DOWN) | O2: Every Other Day
B3: 3.3 | C3: BAC | O3: Weekly
B4: 5 | C4: 4 syringes, 4 alcohol prep | F4: Add per vial | G4: Reg Price
B5: =SUM(B2:B4) -> 203.3 | F5: 100 | G5: =+F5+B5 -> 303.3
A7: Per Unit | B7: =+B5/300 -> 0.67766667 | F7: Per Unit | G7: =+G5/300 -> 1.011
B11: Per Unruh TRZ 30mg is going to be a FLAT $350.00 per month for the first 4 months…up to a max of 100 Units per Week for one month.
A17: Month 1 | B17: Frequency of Injection | C17: mcg | D17: Units per Injections | E17: # of Injections | F17: Units Needed | K17: Reg Price | M17: (TITRATE DOWN)
A18: Week 1 | B18: Weekly | C18: 9mg | D18: 90 | E18: =IF(B18="Daily",7, IF(B18="Weekly",1, IF(B18="Every Other Day",4,""))) -> 1 | F18: =+D18*E18 -> 90 | H18: =ROUNDUP(F22,0) -> 340 | I18: Units | J18: =+B7*F22 -> 230.40667 | K18: =F22*G7 -> 343.74
A19: Week 2 | B19: Weekly | D19: 90 | E19: =IF(B19="Daily",7, IF(B19="Weekly",1, IF(B19="Every Other Day",4,""))) -> 1 | F19: =+D19*E19 -> 90 | H19: =E22 -> 4 | I19: Syringe | J19: =H19*0.24 -> 0.96
A20: Week 3 | B20: Weekly | C20: 8mg | D20: 80 | E20: =IF(B20="Daily",7, IF(B20="Weekly",1, IF(B20="Every Other Day",4,""))) -> 1 | F20: =+D20*E20 -> 80 | H20: =H19 -> 4 | I20: Alochol Prep | J20: =+H20*0.05 -> 0.2
A21: Week 4 | B21: Weekly | D21: 80 | E21: =IF(B21="Daily",7, IF(B21="Weekly",1, IF(B21="Every Other Day",4,""))) -> 1 | F21: =+D21*E21 -> 80 | H21: 1 | I21: Case | J21: =H21*3.65 -> 3.65
E22: =SUM(E18:E21) -> 4 | F22: =SUM(F18:F21) -> 340 | J22: =SUM(J18:J21) -> 235.21667 | K22: 350 | M22: Profit | N22: =+K22-J22 -> 114.78333
I23: Per Unit | J23: =+J22/H18 -> 0.69181373 | K23: =+K22/H18 -> 1.0294118
A27: Month 2 | B27: Frequency of Injection | C27: mcg | D27: Units per Injections | E27: # of Injections | F27: Units Needed | K27: Reg Price | M27: (TITRATE DOWN)
A28: Week 5 | B28: Weekly | C28: 7mg | D28: 70 | E28: =IF(B28="Daily",7, IF(B28="Weekly",1, IF(B28="Every Other Day",4,""))) -> 1 | F28: =+D28*E28 -> 70 | H28: =ROUNDUP(F32,0) -> 260 | I28: Units | J28: =+B7*F32 -> 176.19333 | K28: =+F32*G7 -> 262.86
A29: Week 6 | B29: Weekly | D29: 70 | E29: =IF(B29="Daily",7, IF(B29="Weekly",1, IF(B29="Every Other Day",4,""))) -> 1 | F29: =+D29*E29 -> 70 | H29: =E32 -> 4 | I29: Syringe | J29: =H29*0.24 -> 0.96
A30: Week 7 | B30: Weekly | C30: 6mg | D30: 60 | E30: =IF(B30="Daily",7, IF(B30="Weekly",1, IF(B30="Every Other Day",4,""))) -> 1 | F30: =+D30*E30 -> 60 | H30: =E32 -> 4 | I30: Alochol Prep | J30: =+H30*0.05 -> 0.2
A31: Week 8 | B31: Weekly | D31: 60 | E31: =IF(B31="Daily",7, IF(B31="Weekly",1, IF(B31="Every Other Day",4,""))) -> 1 | F31: =+D31*E31 -> 60 | H31: 0 | I31: Case | J31: =H31*3.65 -> 0
E32: =SUM(E28:E31) -> 4 | F32: =SUM(F28:F31) -> 260 | J32: =SUM(J28:J31) -> 177.35333 | K32: 350 | M32: Profit | N32: =+K32-J32 -> 172.64667
I33: Per Unit | J33: =+J32/H28 -> 0.68212821 | K33: =+K32/H28 -> 1.3461538
A37: Month 3 | B37: Frequency of Injection | C37: mcg | D37: Units per Injections | E37: # of Injections | F37: Units Needed | K37: Reg Price | M37: (TITRATE DOWN)
A38: Week 9 | B38: Weekly | C38: 5mg | D38: 50 | E38: =IF(B38="Daily",7, IF(B38="Weekly",1, IF(B38="Every Other Day",4,""))) -> 1 | F38: =+D38*E38 -> 50 | H38: =ROUNDUP(F42,0) -> 180 | I38: Units | J38: =+B7*F42 -> 121.98 | K38: =+F42*G7 -> 181.98
A39: week 10 | B39: Weekly | D39: 50 | E39: =IF(B39="Daily",7, IF(B39="Weekly",1, IF(B39="Every Other Day",4,""))) -> 1 | F39: =+D39*E39 -> 50 | H39: =E42 -> 4 | I39: Syringe | J39: =+H39*0.24 -> 0.96
A40: Week 11 | B40: Weekly | C40: 4mg | D40: 40 | E40: =IF(B40="Daily",7, IF(B40="Weekly",1, IF(B40="Every Other Day",4,""))) -> 1 | F40: =+D40*E40 -> 40 | H40: =E42 -> 4 | I40: Alochol Prep | J40: =H40*0.05 -> 0.2
A41: Week 12 | B41: Weekly | D41: 40 | E41: =IF(B41="Daily",7, IF(B41="Weekly",1, IF(B41="Every Other Day",4,""))) -> 1 | F41: =+D41*E41 -> 40 | H41: 0 | I41: Case | J41: =H41*3.65 -> 0
E42: =SUM(E38:E41) -> 4 | F42: =SUM(F38:F41) -> 180 | J42: =SUM(J38:J41) -> 123.14 | K42: 350 | M42: Profit | N42: =+K42-J42 -> 226.86
E43: Number of Cartridges needed | F43: =+F42/300 -> 0.6 | I43: Per Unit | J43: =+J42/H38 -> 0.68411111 | K43: =+K42/H38 -> 1.9444444
A47: Month 4 | B47: Frequency of Injection | C47: mcg | D47: Units per Injections | E47: # of Injections | F47: Units Needed | K47: Reg Price | M47: (TITRATE DOWN)
A48: Week 13 | B48: Weekly | C48: 3mg | D48: 30 | E48: =IF(B48="Daily",7, IF(B48="Weekly",1, IF(B48="Every Other Day",4,""))) -> 1 | F48: =+D48*E48 -> 30 | H48: =ROUNDUP(F52,0) -> 100 | I48: Units | J48: =F52*B7 -> 67.766667 | K48: =+F52*G7 -> 101.1
A49: Week 14 | B49: Weekly | D49: 30 | E49: =IF(B49="Daily",7, IF(B49="Weekly",1, IF(B49="Every Other Day",4,""))) -> 1 | F49: =+D49*E49 -> 30 | H49: =E52 -> 4 | I49: Syringe | J49: =+H49*0.24 -> 0.96
A50: Week 15 | B50: Weekly | C50: 2mg | D50: 20 | E50: =IF(B50="Daily",7, IF(B50="Weekly",1, IF(B50="Every Other Day",4,""))) -> 1 | F50: =+D50*E50 -> 20 | H50: =E52 -> 4 | I50: Alochol Prep | J50: =H50*0.05 -> 0.2
A51: Week 16 | B51: Weekly | D51: 20 | E51: =IF(B51="Daily",7, IF(B51="Weekly",1, IF(B51="Every Other Day",4,""))) -> 1 | F51: =+D51*E51 -> 20 | H51: 0 | I51: Case | J51: =H51*3.65 -> 0
E52: =SUM(E48:E51) -> 4 | F52: =SUM(F48:F51) -> 100 | J52: =SUM(J48:J51) -> 68.926667 | K52: 350 | M52: Profit | N52: =+K52-J52 -> 281.07333
E53: Number of Cartridges needed | F53: =+F52/300 -> 0.33333333 | I53: Per Unit | J53: =+J52/H48 -> 0.68926667 | K53: =+K52/H48 -> 3.5
A57: Month 5 | B57: Frequency of Injection | C57: mcg | D57: Units per Injections | E57: # of Injections | F57: Units Needed | K57: Reg Price | M57: (TITRATE DOWN)
A58: Week 17 | B58: Weekly | C58: 1mg | D58: 10 | E58: =IF(B58="Daily",7, IF(B58="Weekly",1, IF(B58="Every Other Day",4,""))) -> 1 | F58: =+D58*E58 -> 10 | H58: =ROUNDUP(F62,0) -> 30 | I58: Units | J58: =F62*B7 -> 20.33 | K58: =+F62*G7 -> 30.33
A59: Week 18 | B59: Weekly | D59: 10 | E59: =IF(B59="Daily",7, IF(B59="Weekly",1, IF(B59="Every Other Day",4,""))) -> 1 | F59: =+D59*E59 -> 10 | H59: =E62 -> 4 | I59: Syringe | J59: =+H59*0.24 -> 0.96
A60: Week 19 | B60: Weekly | C60: 0.5mg | D60: 5 | E60: =IF(B60="Daily",7, IF(B60="Weekly",1, IF(B60="Every Other Day",4,""))) -> 1 | F60: =+D60*E60 -> 5 | H60: =E62 -> 4 | I60: Alochol Prep | J60: =H60*0.05 -> 0.2
A61: Week 20 | B61: Weekly | D61: 5 | E61: =IF(B61="Daily",7, IF(B61="Weekly",1, IF(B61="Every Other Day",4,""))) -> 1 | F61: =+D61*E61 -> 5 | H61: 0 | I61: Case | J61: =H61*3.65 -> 0
E62: =SUM(E58:E61) -> 4 | F62: =SUM(F58:F61) -> 30 | J62: =SUM(J58:J61) -> 21.49 | K62: 350 | M62: Profit | N62: =+K62-J62 -> 328.51
E63: Number of Cartridges needed | F63: =+F62/300 -> 0.1 | I63: Per Unit | J63: =+J62/H58 -> 0.71633333 | K63: =+K62/H58 -> 11.666667
A70: Over 10 months
D71: Sell the bottle?
A72: If we sell exactly what the need: | D72: how many vials do you need for 10 months?
E73: Units per month | F73: =F52 -> 100
A74: Monthly Profit | B74: =N52 -> 281.07333 | E74: Months | F74: 10
F75: =+F74*F73 -> 1000 | G75: Unts needed
E76: Number of vials (div by 300) | F76: =ROUNDUP((F75/300),0) -> 4
E77: $100 per vial | F77: =+F76*F5 -> 400
